Workbook
Name ExternalData_1: '5Y Fin. Summary'!$A$3:$E$14
Name ExternalData_1: SOFP!$A$2:$A$60
Name ExternalData_6: CF!$A$2:$G$99

Sheet 5Y Fin. Summary
A1: Financial Summary - Ceylon Beverage Holdings
B2: 2020 | C2: 2021 | D2: 2022 | E2: 2023 | F2: 2024 | G2: 2025 | H2: 2026 | I2: 2027 | J2: 2028 | K2: 2029 | L2: 2030
A3: OPERATING RESULTS
A4: Revenue | B4: =IS!C3 -> 49215361 | C4: =IS!D3 -> 51172154 | D4: =IS!E3 -> 60211220 | E4: =IS!F3 -> 96938522 | F4: =IS!G3 -> 111930270 | G4: =IS!H3 -> 125172015 | H4: =IS!I3 -> 1.4036001e+08 | I4: =IS!J3 -> 1.5739567e+08 | ... L4: =IS!M3 -> 2.21985e+08
A5: Other income | B5: =IS!$C5 -> 11012389 | C5: =IS!$D5 -> 10506410 | D5: =IS!$E5 -> 12377783 | E5: =IS!$F5 -> 23182851 | F5: 530383 | G5: =IS!$B5 -> 11263256 | H5: =IS!I6 -> 421080.04 | I5: =IS!J6 -> 472187.02 | J5: =IS!K6 -> 529513.45 | K5: =IS!L6 -> 593818.65 | L5: =IS!M6 -> 665955.01
A6: Net gains arising from changes in fair value of investment properties | B6: 155609 | C6: - | D6: 160230 | E6: 163100 | F6: 5000 | G6: 350172 | H6: =IS!I7 -> 75677 | I6: =IS!J7 -> 75677 | J6: =IS!K7 -> 75677 | K6: =IS!L7 -> 75677 | L6: =IS!M7 -> 75677
B7: 49524307 | C7: 51,516,023 | D7: 60565372 | E7: 97406036 | F7: 112465653 | G7: =SUM(G4+G5+G6) -> 136785443 | H7: =SUM(H4+H5+H6) -> 1.4085677e+08 | I7: =SUM(I4+I5+I6) -> 1.5794354e+08 | J7: =SUM(J4+J5+J6) -> 1.7710967e+08 | K7: =SUM(K4+K5+K6) -> 1.9860905e+08 | L7: =SUM(L4+L5+L6) -> 2.2272664e+08
A8: Total expenditure | B8: -43550492 | C8: (46,194,221) | D8: -54389494 | E8: -83587984 | F8: -97099425 | G8: =G10-G7 -> -120186589 | H8: =H10-H7 -> -1.2153583e+08 | I8: =I10-I7 -> -1.3615532e+08 | J8: =J10-J7 -> -1.5269708e+08 | K8: =K10-K7 -> -1.7138539e+08 | L8: =L10-L7 -> -1.9234168e+08
A9: Reversal / (provision) impairment of intangible assets | B9: -740315 | C9: (449,084) | D9: -463578 | E9: -353229 | F9: 291063 | G9: - | H9: =IS!I12 -> 0 | I9: =IS!J12 -> 0 | J9: =IS!K12 -> 0 | K9: =IS!L12 -> 0 | L9: =IS!M12 -> 0
A10: EBIT | B10: 5233500 | C10: 4,872,718 | D10: 5712300 | E10: 13464823 | F10: 15657291 | G10: 16598854 | H10: =IS!I15 -> 19320940 | I10: =IS!J15 -> 21788217 | J10: =IS!K15 -> 24412591 | K10: =IS!L15 -> 27223652 | L10: =IS!M15 -> 30384955
A11: Net finance income/(costs) | B11: -739260 | C11: (588,211) | D11: 172876 | E11: -2203920 | F11: -1633998 | G11: -562630 | H11: =IS!I17 -> -1077448.6 | I11: =IS!J17 -> -883951.22 | J11: =IS!K17 -> -647652.2 | K11: =IS!L17 -> -359083.84 | L11: =IS!M17 -> -6684.1523
A12: EBT | B12: 4494240 | C12: 4,284,507 | D12: 5885176 | E12: 11260903 | F12: 14023293 | G12: 16036224 | H12: =IS!I19 -> 19368016 | I12: =IS!J19 -> 22165276 | J12: =IS!K19 -> 25179043 | K12: =IS!L19 -> 28450405 | L12: =IS!M19 -> 32156752
A13: Income tax expense | B13: -1677977 | C13: (1,850,010) | D13: -2063378 | E13: -4514799 | F13: -6047684 | G13: -6378562 | H13: =IS!I20 -> -7940540.7 | I13: =IS!J20 -> -9154271 | J13: =IS!K20 -> -10245708 | K13: =IS!L20 -> -11663687 | L13: =IS!M20 -> -13182985
A14: Net Income | B14: 2816263 | C14: 2,434,497 | D14: 3821798 | E14: 6746104 | F14: 7975609 | G14: 9657662 | H14: =IS!I21 -> 11427476 | I14: =IS!J21 -> 13011005 | J14: =IS!K21 -> 14933336 | K14: =IS!L21 -> 16786718 | L14: =IS!M21 -> 18973768

Sheet Assumptions
A1: Assumptions Sheet | B1: 2019 | C1: 2020 | D1: 2021 | E1: 2022 | F1: 2023 | G1: 2024 | H1: 2025 | I1: 2026 | J1: 2027 | K1: 2028 | L1: 2029 | M1: 2030
A3: Revenue Assumptions
A4: Revenue Growth Rates
A5: Domestic Revenue | C5: =IS!C36/IS!B36-1 -> 0.11677425 | D5: =IS!D36/IS!C36-1 -> 0.042923152 | E5: =IS!E36/IS!D36-1 -> 0.17535269 | F5: =IS!F36/IS!E36-1 -> 0.59634201 | G5: =IS!G36/IS!F36-1 -> 0.15453027 | H5: =IS!H36/IS!G36-1 -> 0.11734451 | I5: 0.12 | J5: =I5 -> 0.12 | K5: =J5 -> 0.12 | L5: =K5 -> 0.12 | M5: =L5 -> 0.12
A6: Export revenue | C6: =IS!C37/IS!B37-1 -> 0.024864954 | D6: =IS!D37/IS!C37-1 -> -0.041769119 | E6: =IS!E37/IS!D37-1 -> 0.21275971 | F6: =IS!F37/IS!E37-1 -> 0.98057985 | G6: =IS!G37/IS!F37-1 -> 0.15732203 | H6: =IS!H37/IS!G37-1 -> 0.13926632 | I6: 0.15 | J6: =I6 -> 0.15 | K6: =J6 -> 0.15 | L6: =K6 -> 0.15 | M6: =L6 -> 0.15
A8: Other Income
A9: As a % of revenue | B9: =IS!B6/IS!B3 -> 0.0031215492 | C9: =IS!C6/IS!C3 -> 0.0031156329 | D9: =IS!D6/IS!D3 -> 0.0067198461 | E9: =IS!E6/IS!E3 -> 0.0032206954 | F9: =IS!F6/IS!F3 -> 0.0031402789 | G9: =IS!G6/IS!G3 -> 0.0047385126 | H9: =IS!H6/IS!H3 -> 0.0027975263 | I9: 0.003 | J9: =I9 -> 0.003 | K9: =J9 -> 0.003 | L9: =K9 -> 0.003 | M9: =L9 -> 0.003
A12: Cost Assumptions
A13: Cost of Sales
A14: As a % of revenue | B14: =ABS(IS!B4/IS!B3) -> 0.74527218 | C14: =ABS(IS!C4/IS!C3) -> 0.77624082 | D14: =ABS(IS!D4/IS!D3) -> 0.79468502 | E14: =ABS(IS!E4/IS!E3) -> 0.7944273 | F14: =ABS(IS!F4/IS!F3) -> 0.76084996 | G14: =ABS(IS!G4/IS!G3) -> 0.75818146 | H14: =ABS(IS!H4/IS!H3) -> 0.76371535 | I14: =ABS(AVERAGE(F14:H14)) -> 0.76091559 | J14: =I14 -> 0.76091559 | K14: =J14 -> 0.76091559 | L14: =K14 -> 0.76091559 | M14: =L14 -> 0.76091559
A16: Distribution expenses
A17: As a % of revenue | B17: =ABS(IS!B9/IS!B3) -> 0.068543385 | C17: =ABS(IS!C9/IS!C3) -> 0.061399265 | D17: =ABS(IS!D9/IS!D3) -> 0.056819007 | E17: =ABS(IS!E9/IS!E3) -> 0.058350204 | F17: =ABS(IS!F9/IS!F3) -> 0.062073352 | G17: =ABS(IS!G9/IS!G3) -> 0.067127838 | H17: =ABS(IS!H9/IS!H3) -> 0.064565894 | I17: =AVERAGE(B17:H17) -> 0.062696992 | J17: =AVERAGE(C17:I17) -> 0.061861793 | K17: =AVERAGE(D17:J17) -> 0.061927869 | L17: =AVERAGE(E17:K17) -> 0.062657706 | M17: =AVERAGE(F17:L17) -> 0.063273063
A19: Administrative expenses
A20: As a % of revenue | B20: =ABS(IS!B10/IS!B3) -> 0.037471685 | C20: =ABS(IS!C10/IS!C3) -> 0.036180716 | D20: =ABS(IS!D10/IS!D3) -> 0.03710731 | E20: =ABS(IS!E10/IS!E3) -> 0.03930221 | F20: =ABS(IS!F10/IS!F3) -> 0.031977886 | G20: =ABS(IS!G10/IS!G3) -> 0.037163325 | H20: =ABS(IS!H10/IS!H3) -> 0.037051349 | I20: =H20 -> 0.037051349 | J20: =I20 -> 0.037051349 | K20: =J20 -> 0.037051349 | L20: =K20 -> 0.037051349 | M20: =L20 -> 0.037051349
A22: Other expenses
A23: As a % of revenue | B23: =ABS(IS!B11/IS!B3) -> 0.0093440898 | C23: =ABS(IS!C11/IS!C3) -> 0.011075526 | D23: =ABS(IS!D11/IS!D3) -> 0.014110506 | E23: =ABS(IS!E11/IS!E3) -> 0.011231893 | F23: =ABS(IS!F11/IS!F3) -> 0.0073770982 | G23: =ABS(IS!G11/IS!G3) -> 0.0050266206 | H23: =ABS(IS!H11/IS!H3) -> 0.0052224932 | I23: =H23 -> 0.0052224932 | J23: =I23 -> 0.0052224932 | K23: =J23 -> 0.0052224932 | L23: =K23 -> 0.0052224932 | M23: =L23 -> 0.0052224932
A25: Finance income
A26: As a % of revenue | B26: =IS!B16/IS!B3 -> 0.022840241 | C26: =IS!C16/IS!C3 -> 0.019321305 | D26: =IS!D16/IS!D3 -> 0.012979579 | E26: =IS!E16/IS!E3 -> 0.01042324 | F26: =IS!F16/IS!F3 -> 0.014560992 | G26: =IS!G16/IS!G3 -> 0.010293266 | H26: =IS!H16/IS!H3 -> 0.0080117189 | I26: =H26 -> 0.0080117189 | J26: =I26 -> 0.0080117189 | K26: =J26 -> 0.0080117189 | L26: =K26 -> 0.0080117189 | M26: =L26 -> 0.0080117189
A29: Effective Tax Rate | B29: =ABS(IS!B20/IS!B19) -> 0.41232024 | C29: =ABS(IS!C20/IS!C19) -> 0.37336168 | D29: =ABS(IS!D20/IS!D19) -> 0.43179064 | E29: =ABS(IS!E20/IS!E19) -> 0.350606 | F29: =ABS(IS!F20/IS!F19) -> 0.40092691 | G29: =ABS(IS!G20/IS!G19) -> 0.4312599 | H29: =ABS(IS!H20/IS!H19) -> 0.3977596 | I29: =AVERAGE(F29:H29) -> 0.40998214 | J29: =AVERAGE(G29:I29) -> 0.41300055 | K29: =AVERAGE(H29:J29) -> 0.40691409 | L29: =AVERAGE(I29:K29) -> 0.40996559 | M29: =AVERAGE(J29:L29) -> 0.40996008
A31: Depreciation Rate | B31: =CF!B8/SOFP!B5 -> 0.067415487 | C31: =CF!C8/SOFP!C5 -> 0.064160855 | D31: =CF!D8/SOFP!D5 -> 0.069907165 | E31: =CF!E8/SOFP!E5 -> 0.074509277 | F31: =CF!F8/SOFP!F5 -> 0.078128969 | G31: =CF!G8/SOFP!G5 -> 0.086868488 | H31: =CF!H8/SOFP!H5 -> 0.09514721 | I31: =H31 -> 0.09514721 | J31: =I31 -> 0.09514721 | K31: =J31 -> 0.09514721 | L31: =K31 -> 0.09514721 | M31: =L31 -> 0.09514721
A32: Ammortization Rate (5years -> 20% ) | B32: 0.2 | C32: 0.2 | D32: 0.2 | E32: 0.2 | F32: 0.2 | G32: 0.2 | H32: 0.2 | I32: 0.2 | J32: 0.2 | K32: 0.2 | L32: 0.2 | M32: 0.2
A33: Lease Rate (20%) | C33: =CF!C6/SOFP!C9 -> 0.22709008 | D33: =CF!D6/SOFP!D9 -> 0.32529093 | E33: =CF!E6/SOFP!E9 -> 0.33845842 | F33: =CF!F6/SOFP!F9 -> 0.31325049 | G33: =CF!G6/SOFP!G9 -> 0.28359282 | H33: =CF!H6/SOFP!H9 -> 0.074148719 | I33: =AVERAGE(F33:H33) -> 0.22366401 | J33: =I33 -> 0.22366401 | K33: =J33 -> 0.22366401 | L33: =K33 -> 0.22366401 | M33: =L33 -> 0.22366401
A35: PPE Addition (As a % of GDP) | I35: 0.025 | J35: 0.025 | K35: 0.025 | L35: 0.025 | M35: 0.025
A36: Intangible Additions (As a % to Revenue) | B36: =CapEx!B13/IS!B3 -> 0.0011128116 | C36: =CapEx!C13/IS!C3 -> 0.00011675217 | D36: =CapEx!D13/IS!D3 -> 0.00053146092 | E36: =CapEx!E13/IS!E3 -> 0.00012384735 | F36: =CapEx!F13/IS!F3 -> 8.0618106e-05 | G36: =CapEx!G13/IS!G3 -> 0.00036828286 | H36: =CapEx!H13/IS!H3 -> 0.00020887257 | I36: 0.0005 | J36: =I36 -> 0.0005 | K36: =J36 -> 0.0005 | L36: =K36 -> 0.0005 | M36: =L36 -> 0.0005
A37: ROU Addition (Lease to revenue) | B37: =CapEx!B21/IS!B3 -> 0 | C37: =CapEx!C21/IS!C3 -> 0.0047797882 | D37: =CapEx!D21/IS!D3 -> 0.00097293149 | E37: =CapEx!E21/IS!E3 -> 0.00067856124 | F37: =CapEx!F21/IS!F3 -> 0.00078447658 | G37: =CapEx!G21/IS!G3 -> 0.00082131491 | H37: =CapEx!H21/IS!H3 -> 0.00047905277 | I37: =H37 -> 0.00047905277 | J37: =I37 -> 0.00047905277 | K37: =J37 -> 0.00047905277 | L37: =K37 -> 0.00047905277 | M37: =L37 -> 0.00047905277

Sheet IS
A1: STATEMENT OF PROFIT OR LOSS
A2: For the year ended 31st March (In Rs.’000s) | B2: 2019 | C2: 2020 | D2: 2021 | E2: 2022 | F2: 2023 | G2: 2024 | H2: 2025 | I2: 2026 | J2: 2027 | K2: 2028 | L2: 2029 | M2: 2030
A3: Revenue | B3: 44216827 | C3: 49215361 | D3: 51172154 | E3: 60211220 | F3: 96938522 | G3: 111930270 | H3: 125172015 | I3: =I38 -> 1.4036001e+08 | J3: =J38 -> 1.5739567e+08 | K3: =K38 -> 1.7650448e+08 | L3: =L38 -> 1.9793955e+08 | M3: =M38 -> 2.21985e+08
A4: Cost of sales | B4: -32953571 | C4: -38202972 | D4: -40665744 | E4: -47833437 | F4: -73755671 | G4: -84863456 | H4: -95595789 | I4: =-I3*(Assumptions!I14) -> -1.0680212e+08 | J4: =-J3*(Assumptions!J14) -> -1.1976482e+08 | K4: =-K3*(Assumptions!K14) -> -1.3430501e+08 | L4: =-L3*(Assumptions!L14) -> -1.5061529e+08 | M4: =-M3*(Assumptions!M14) -> -1.6891185e+08
A5: Gross profit | B5: 11263256 | C5: 11012389 | D5: 10506410 | E5: 12377783 | F5: 23182851 | G5: 27066814 | H5: 29576226 | I5: =I3+I4 -> 33557891 | J5: =J3+J4 -> 37630852 | K5: =K3+K4 -> 42199470 | L5: =L3+L4 -> 47324260 | M5: =M3+M4 -> 53073153
A6: Other income | B6: 138025 | C6: 153337 | D6: 343869 | E6: 193922 | F6: 304414 | G6: 530383 | H6: 350172 | I6: =I3*Assumptions!I9 -> 421080.04 | J6: =J3*Assumptions!J9 -> 472187.02 | K6: =K3*Assumptions!K9 -> 529513.45 | L6: =L3*Assumptions!L9 -> 593818.65 | M6: =M3*Assumptions!M9 -> 665955.01
A7: Net gains arising from changes in fair value of investment properties | B7: 0 | C7: 155609 | D7: 0 | E7: 160230 | F7: 163100 | G7: 5000 | H7: 45800 | I7: =AVERAGE(B7:H7) -> 75677 | J7: =I7 -> 75677 | K7: =J7 -> 75677 | L7: =K7 -> 75677 | M7: =L7 -> 75677
B8: =SUM(B5:B7) -> 11401281 | C8: =SUM(C5:C7) -> 11321335 | D8: =SUM(D5:D7) -> 10850279 | E8: =SUM(E5:E7) -> 12731935 | F8: =SUM(F5:F7) -> 23650365 | G8: =SUM(G5:G7) -> 27602197 | H8: =SUM(H5:H7) -> 29972198 | I8: =SUM(I5:I7) -> 34054648 | ... M8: =SUM(M5:M7) -> 53814785
A9: Distribution expenses | B9: -3030771 | C9: -3021787 | D9: -2907551 | E9: -3513337 | F9: -6017299 | G9: -7513637 | H9: -8081843 | I9: =-I3*Assumptions!I17 -> -8800150.7 | J9: =-J3*Assumptions!J17 -> -9736778.7 | K9: =-K3*Assumptions!K17 -> -10930547 | L9: =-L3*Assumptions!L17 -> -12402438 | M9: =-M3*Assumptions!M17 -> -14045671
A10: Administrative expenses | B10: -1656879 | C10: -1780647 | D10: -1898861 | E10: -2366434 | F10: -3099889 | G10: -4159701 | H10: -4637792 | I10: =-(I3*Assumptions!I20) -> -5200527.8 | J10: =-(J3*Assumptions!J20) -> -5831722 | K10: =-(K3*Assumptions!K20) -> -6539729.2 | L10: =-(L3*Assumptions!L20) -> -7333927.3 | M10: =-(M3*Assumptions!M20) -> -8224843.8
A11: Other expenses | B11: -413166 | C11: -545086 | D11: -722065 | E11: -676286 | F11: -715125 | G11: -562631 | H11: -653710 | I11: =-I3*Assumptions!I23 -> -733029.22 | J11: =-J3*Assumptions!J23 -> -821997.84 | K11: =-K3*Assumptions!K23 -> -921793.47 | L11: =-L3*Assumptions!L23 -> -1033738 | M11: =-M3*Assumptions!M23 -> -1159315.2
A12: Reversal / (provision) - impairment of intercompany receivable | D12: 0 | E12: 0 | F12: 0 | G12: 0 | H12: 0 | I12: 0 | J12: 0 | K12: 0 | L12: 0 | M12: 0
A13: Impairment of investments in subsidiaries | B13: 0 | C13: 0 | D13: 0 | E13: 0 | F13: 0 | G13: 0 | H13: 0 | I13: 0 | J13: 0 | K13: 0 | L13: 0 | M13: 0
A14: Reversal / (provision) - impairment of intangible assets | B14: - | C14: -740315 | E14: -463578 | F14: -353229 | G14: 291063 | H14: -
A15: Operating Income (EBIT) | B15: =SUM(B8:B14) -> 6300465 | C15: =SUM(C8:C14) -> 5233500 | D15: =SUM(D8:D14) -> 5321802 | E15: 5712300 | F15: =SUM(F8:F14) -> 13464823 | G15: =SUM(G8:G14) -> 15657291 | H15: 16598854 | I15: =SUM(I8:I14) -> 19320940 | J15: =SUM(J8:J14) -> 21788217 | K15: =SUM(K8:K14) -> 24412591 | L15: =SUM(L8:L14) -> 27223652 | M15: =SUM(M8:M14) -> 30384955
A16: Finance income | B16: 1009923 | C16: 950905 | D16: 664193 | E16: 627596 | F16: 1411521 | G16: 1152128 | H16: 1002843 | I16: =I3*Assumptions!I26 -> 1124525 | J16: =J3*Assumptions!J26 -> 1261009.9 | K16: =K3*Assumptions!K26 -> 1414104.3 | L16: =L3*Assumptions!L26 -> 1585836 | M16: =M3*Assumptions!M26 -> 1778481.5
A17: Finance costs | B17: -2094515 | C17: -1690165 | D17: -1252404 | E17: -454720 | F17: -3615441 | G17: -2786126 | H17: -1565473 | I17: =-'Loan Schedule'!B5 -> -1077448.6 | J17: =-'Loan Schedule'!C5 -> -883951.22 | K17: =-'Loan Schedule'!D5 -> -647652.2 | L17: =-'Loan Schedule'!E5 -> -359083.84 | M17: =-'Loan Schedule'!F5 -> -6684.1523
A18: Net finance income / (costs) | B18: -1084592 | C18: -739260 | D18: -588211 | E18: 172876 | F18: -2203920 | G18: -1633998 | H18: -562630 | I18: =I16+I17 -> 47076.362 | J18: =J16+J17 -> 377058.69 | K18: =K16+K17 -> 766452.12 | L18: =L16+L17 -> 1226752.2 | M18: =M16+M17 -> 1771797.3
A19: Income before Tax (EBT) | B19: 5215873 | C19: 4494240 | D19: 4284507 | E19: 5885176 | F19: 11260903 | G19: 14023293 | H19: 16036224 | I19: =I15+I18 -> 19368016 | J19: =J15+J18 -> 22165276 | K19: =K15+K18 -> 25179043 | L19: =L15+L18 -> 28450405 | M19: =M15+M18 -> 32156752
A20: Less: Income tax expenses | B20: -2150610 | C20: -1677977 | D20: -1850010 | E20: -2063378 | F20: -4514799 | G20: -6047684 | H20: -6378562 | I20: =-I19*Assumptions!I29 -> -7940540.7 | J20: =-J19*Assumptions!J29 -> -9154271 | K20: =-K19*Assumptions!K29 -> -10245708 | L20: =-L19*Assumptions!L29 -> -11663687 | M20: =-M19*Assumptions!M29 -> -13182985
A21: Net Income | B21: 3065263 | C21: 2816263 | D21: 2434497 | E21: 3821798 | F21: 6746104 | G21: 7975609 | H21: 9657662 | I21: =I19+I20 -> 11427476 | J21: =J19+J20 -> 13011005 | K21: =K19+K20 -> 14933336 | L21: =L19+L20 -> 16786718 | M21: =M19+M20 -> 18973768
A24: Profit/(loss) attributable to
A25: - Equity holders of the company | B25: 1527293 | C25: 1473471 | D25: 1254900 | E25: 2452270 | F25: 3407614 | G25: 3962948 | H25: 4958100 | I25: =I21*0.5 -> 5713737.8 | J25: =J21*0.5 -> 6505502.4 | K25: =K21*0.5 -> 7466667.9 | L25: =L21*0.5 -> 8393358.8 | M25: =M21*0.5 -> 9486883.8
A26: - Non controlling interest | B26: 1537970 | C26: 1342792 | D26: 1180269 | E26: 2100614 | F26: 3338490 | G26: 4012661 | H26: 4394730 | I26: =I21*0.5 -> 5713737.8 | J26: =J21*0.5 -> 6505502.4 | K26: =K21*0.5 -> 7466667.9 | L26: =L21*0.5 -> 8393358.8 | M26: =M21*0.5 -> 9486883.8
A27: Profit available for appropriation | B27: 3065263 | C27: 2816263 | D27: 2434497 | E27: 3821798 | F27: 6746104 | G27: 7975609 | H27: =H25+H26 -> 9352830 | I27: =I25+I26 -> 11427476 | J27: =J25+J26 -> 13011005 | K27: =K25+K26 -> 14933336 | L27: =L25+L26 -> 16786718 | M27: =M25+M26 -> 18973768
A29: Earnings per Ordinary Share (Rs.) | B29: 72.77 | C29: 70.21 | D29: 59.77 | E29: 98.64 | F29: 162.36 | G29: 188.82 | H29: 243.82 | I29: =I25/DCF!$C$21 -> 272.23715 | J29: =J25/DCF!$C$21 -> 309.96162 | K29: =K25/DCF!$C$21 -> 355.75738 | L29: =L25/DCF!$C$21 -> 399.91056 | M29: =M25/DCF!$C$21 -> 452.01273
B31: =B25/B21 -> 0.49825839 | C31: =C25/C21 -> 0.52320078 | D31: =D25/D21 -> 0.51546582 | E31: =E25/E21 -> 0.64165348
A34: Revenue Breakdown
A35: Net Revenue by Geographical Split
A36: Domestic Revenue | B36: 42423178 | C36: 47377113 | D36: 49410688 | E36: 58074985 | F36: 92707538 | G36: 107033659 | H36: 119593471 | I36: =H36*(1+Assumptions!I5) -> 1.3394469e+08 | J36: =I36*(1+Assumptions!J5) -> 1.5001805e+08 | K36: =J36*(1+Assumptions!K5) -> 1.6802022e+08 | L36: =K36*(1+Assumptions!L5) -> 1.8818264e+08 | M36: =L36*(1+Assumptions!M5) -> 2.1076456e+08
A37: Export Revenue | B37: 1793649 | C37: 1838248 | D37: 1761466 | E37: 2136235 | F37: 4230984 | G37: 4896611 | H37: 5578544 | I37: =H37*(1+Assumptions!I6) -> 6415325.6 | J37: =I37*(1+Assumptions!J6) -> 7377624.4 | K37: =J37*(1+Assumptions!K6) -> 8484268.1 | L37: =K37*(1+Assumptions!L6) -> 9756908.3 | M37: =L37*(1+Assumptions!M6) -> 11220445
A38: Total Revenue | B38: =SUM(B36:B37) -> 44216827 | C38: =SUM(C36:C37) -> 49215361 | D38: =SUM(D36:D37) -> 51172154 | E38: =SUM(E36:E37) -> 60211220 | F38: =SUM(F36:F37) -> 96938522 | G38: =SUM(G36:G37) -> 111930270 | H38: =SUM(H36:H37) -> 125172015 | I38: =SUM(I36:I37) -> 1.4036001e+08 | ... M38: =SUM(M36:M37) -> 2.21985e+08

Sheet SOFP
A1: STATEMENT OF FINANCIAL POSITION | AO1: STATEMENT OF PROFIT OR LOSS | AW1: STATEMENT OF PROFIT OR LOSS | BE1: STATEMENT OF PROFIT OR LOSS | BM1: STATEMENT OF PROFIT OR LOSS | BU1: STATEMENT OF PROFIT OR LOSS | CC1: STATEMENT OF PROFIT OR LOSS | CK1: STATEMENT OF PROFIT OR LOSS | CS1: STATEMENT OF PROFIT OR LOSS | DA1: STATEMENT OF PROFIT OR LOSS | DI1: STATEMENT OF PROFIT OR LOSS | DQ1: STATEMENT OF PROFIT OR LOSS | DY1: STATEMENT OF PROFIT OR LOSS | EG1: STATEMENT OF PROFIT OR LOSS | EO1: STATEMENT OF PROFIT OR LOSS | EW1: STATEMENT OF PROFIT OR LOSS | FE1: STATEMENT OF PROFIT OR LOSS | FM1: STATEMENT OF PROFIT OR LOSS | FU1: STATEMENT OF PROFIT OR LOSS | GC1: STATEMENT OF PROFIT OR LOSS | GK1: STATEMENT OF PROFIT OR LOSS | GS1: STATEMENT OF PROFIT OR LOSS | HA1: STATEMENT OF PROFIT OR LOSS | HI1: STATEMENT OF PROFIT OR LOSS | HQ1: STATEMENT OF PROFIT OR LOSS | HY1: STATEMENT OF PROFIT OR LOSS | IG1: STATEMENT OF PROFIT OR LOSS | IO1: STATEMENT OF PROFIT OR LOSS | IW1: STATEMENT OF PROFIT OR LOSS | JE1: STATEMENT OF PROFIT OR LOSS | JM1: STATEMENT OF PROFIT OR LOSS | JU1: STATEMENT OF PROFIT OR LOSS | KC1: STATEMENT OF PROFIT OR LOSS | KK1: STATEMENT OF PROFIT OR LOSS | KS1: STATEMENT OF PROFIT OR LOSS | LA1: STATEMENT OF PROFIT OR LOSS | LI1: STATEMENT OF PROFIT OR LOSS | LQ1: STATEMENT OF PROFIT OR LOSS | LY1: STATEMENT OF PROFIT OR LOSS | MG1: STATEMENT OF PROFIT OR LOSS | MO1: STATEMENT OF PROFIT OR LOSS | MW1: STATEMENT OF PROFIT OR LOSS | NE1: STATEMENT OF PROFIT OR LOSS | NM1: STATEMENT OF PROFIT OR LOSS | NU1: STATEMENT OF PROFIT OR LOSS | OC1: STATEMENT OF PROFIT OR LOSS | OK1: STATEMENT OF PROFIT OR LOSS | OS1: STATEMENT OF PROFIT OR LOSS | PA1: STATEMENT OF PROFIT OR LOSS | PI1: STATEMENT OF PROFIT OR LOSS | PQ1: STATEMENT OF PROFIT OR LOSS | PY1: STATEMENT OF PROFIT OR LOSS | QG1: STATEMENT OF PROFIT OR LOSS | QO1: STATEMENT OF PROFIT OR LOSS | QW1: STATEMENT OF PROFIT OR LOSS | RE1: STATEMENT OF PROFIT OR LOSS | RM1: STATEMENT OF PROFIT OR LOSS | RU1: STATEMENT OF PROFIT OR LOSS | SC1: STATEMENT OF PROFIT OR LOSS | SK1: STATEMENT OF PROFIT OR LOSS | SS1: STATEMENT OF PROFIT OR LOSS | TA1: STATEMENT OF PROFIT OR LOSS | TI1: STATEMENT OF PROFIT OR LOSS | TQ1: STATEMENT OF PROFIT OR LOSS | TY1: STATEMENT OF PROFIT OR LOSS | UG1: STATEMENT OF PROFIT OR LOSS | UO1: STATEMENT OF PROFIT OR LOSS | UW1: STATEMENT OF PROFIT OR LOSS | VE1: STATEMENT OF PROFIT OR LOSS | VM1: STATEMENT OF PROFIT OR LOSS | VU1: STATEMENT OF PROFIT OR LOSS | WC1: STATEMENT OF PROFIT OR LOSS | WK1: STATEMENT OF PROFIT OR LOSS | WS1: STATEMENT OF PROFIT OR LOSS | XA1: STATEMENT OF PROFIT OR LOSS | XI1: STATEMENT OF PROFIT OR LOSS | XQ1: STATEMENT OF PROFIT OR LOSS | XY1: STATEMENT OF PROFIT OR LOSS | YG1: STATEMENT OF PROFIT OR LOSS | YO1: STATEMENT OF PROFIT OR LOSS | YW1: STATEMENT OF PROFIT OR LOSS | ZE1: STATEMENT OF PROFIT OR LOSS | ZM1: STATEMENT OF PROFIT OR LOSS | ZU1: STATEMENT OF PROFIT OR LOSS | AAC1: STATEMENT OF PROFIT OR LOSS | AAK1: STATEMENT OF PROFIT OR LOSS | AAS1: STATEMENT OF PROFIT OR LOSS | ABA1: STATEMENT OF PROFIT OR LOSS | ABI1: STATEMENT OF PROFIT OR LOSS | ABQ1: STATEMENT OF PROFIT OR LOSS | ABY1: STATEMENT OF PROFIT OR LOSS | ACG1: STATEMENT OF PROFIT OR LOSS | ACO1: STATEMENT OF PROFIT OR LOSS | ACW1: STATEMENT OF PROFIT OR LOSS | ADE1: STATEMENT OF PROFIT OR LOSS | ADM1: STATEMENT OF PROFIT OR LOSS | ADU1: STATEMENT OF PROFIT OR LOSS | AEC1: STATEMENT OF PROFIT OR LOSS | AEK1: STATEMENT OF PROFIT OR LOSS | AES1: STATEMENT OF PROFIT OR LOSS | AFA1: STATEMENT OF PROFIT OR LOSS | AFI1: STATEMENT OF PROFIT OR LOSS | AFQ1: STATEMENT OF PROFIT OR LOSS | AFY1: STATEMENT OF PROFIT OR LOSS | AGG1: STATEMENT OF PROFIT OR LOSS | AGO1: STATEMENT OF PROFIT OR LOSS | AGW1: STATEMENT OF PROFIT OR LOSS | AHE1: STATEMENT OF PROFIT OR LOSS | AHM1: STATEMENT OF PROFIT OR LOSS | AHU1: STATEMENT OF PROFIT OR LOSS | AIC1: STATEMENT OF PROFIT OR LOSS | AIK1: STATEMENT OF PROFIT OR LOSS | AIS1: STATEMENT OF PROFIT OR LOSS | AJA1: STATEMENT OF PROFIT OR LOSS | AJI1: STATEMENT OF PROFIT OR LOSS | AJQ1: STATEMENT OF PROFIT OR LOSS | AJY1: STATEMENT OF PROFIT OR LOSS | AKG1: STATEMENT OF PROFIT OR LOSS | AKO1: STATEMENT OF PROFIT OR LOSS | AKW1: STATEMENT OF PROFIT OR LOSS | ALE1: STATEMENT OF PROFIT OR LOSS | ALM1: STATEMENT OF PROFIT OR LOSS | ALU1: STATEMENT OF PROFIT OR LOSS | AMC1: STATEMENT OF PROFIT OR LOSS | AMK1: STATEMENT OF PROFIT OR LOSS | AMS1: STATEMENT OF PROFIT OR LOSS | ANA1: STATEMENT OF PROFIT OR LOSS | ANI1: STATEMENT OF PROFIT OR LOSS | ANQ1: STATEMENT OF PROFIT OR LOSS | ANY1: STATEMENT OF PROFIT OR LOSS | AOG1: STATEMENT OF PROFIT OR LOSS | AOO1: STATEMENT OF PROFIT OR LOSS | AOW1: STATEMENT OF PROFIT OR LOSS | APE1: STATEMENT OF PROFIT OR LOSS | APM1: STATEMENT OF PROFIT OR LOSS | APU1: STATEMENT OF PROFIT OR LOSS | AQC1: STATEMENT OF PROFIT OR LOSS | AQK1: STATEMENT OF PROFIT OR LOSS | AQS1: STATEMENT OF PROFIT OR LOSS | ARA1: STATEMENT OF PROFIT OR LOSS | ARI1: STATEMENT OF PROFIT OR LOSS | ARQ1: STATEMENT OF PROFIT OR LOSS | ARY1: STATEMENT OF PROFIT OR LOSS | ASG1: STATEMENT OF PROFIT OR LOSS | ASO1: STATEMENT OF PROFIT OR LOSS | ASW1: STATEMENT OF PROFIT OR LOSS | ATE1: STATEMENT OF PROFIT OR LOSS | ATM1: STATEMENT OF PROFIT OR LOSS | ATU1: STATEMENT OF PROFIT OR LOSS | AUC1: STATEMENT OF PROFIT OR LOSS | AUK1: STATEMENT OF PROFIT OR LOSS | AUS1: STATEMENT OF PROFIT OR LOSS | AVA1: STATEMENT OF PROFIT OR LOSS | AVI1: STATEMENT OF PROFIT OR LOSS | AVQ1: STATEMENT OF PROFIT OR LOSS | AVY1: STATEMENT OF PROFIT OR LOSS | AWG1: STATEMENT OF PROFIT OR LOSS | AWO1: STATEMENT OF PROFIT OR LOSS | AWW1: STATEMENT OF PROFIT OR LOSS | AXE1: STATEMENT OF PROFIT OR LOSS | AXM1: STATEMENT OF PROFIT OR LOSS | AXU1: STATEMENT OF PROFIT OR LOSS | AYC1: STATEMENT OF PROFIT OR LOSS | AYK1: STATEMENT OF PROFIT OR LOSS | AYS1: STATEMENT OF PROFIT OR LOSS | AZA1: STATEMENT OF PROFIT OR LOSS | AZI1: STATEMENT OF PROFIT OR LOSS | AZQ1: STATEMENT OF PROFIT OR LOSS | AZY1: STATEMENT OF PROFIT OR LOSS | BAG1: STATEMENT OF PROFIT OR LOSS | BAO1: STATEMENT OF PROFIT OR LOSS | BAW1: STATEMENT OF PROFIT OR LOSS | BBE1: STATEMENT OF PROFIT OR LOSS | BBM1: STATEMENT OF PROFIT OR LOSS | BBU1: STATEMENT OF PROFIT OR LOSS | BCC1: STATEMENT OF PROFIT OR LOSS | BCK1: STATEMENT OF PROFIT OR LOSS | BCS1: STATEMENT OF PROFIT OR LOSS | BDA1: STATEMENT OF PROFIT OR LOSS | BDI1: STATEMENT OF PROFIT OR LOSS | BDQ1: STATEMENT OF PROFIT OR LOSS | BDY1: STATEMENT OF PROFIT OR LOSS | BEG1: STATEMENT OF PROFIT OR LOSS | BEO1: STATEMENT OF PROFIT OR LOSS | BEW1: STATEMENT OF PROFIT OR LOSS | BFE1: STATEMENT OF PROFIT OR LOSS | BFM1: STATEMENT OF PROFIT OR LOSS | BFU1: STATEMENT OF PROFIT OR LOSS | BGC1: STATEMENT OF PROFIT OR LOSS | BGK1: STATEMENT OF PROFIT OR LOSS | BGS1: STATEMENT OF PROFIT OR LOSS | BHA1: STATEMENT OF PROFIT OR LOSS | BHI1: STATEMENT OF PROFIT OR LOSS | BHQ1: STATEMENT OF PROFIT OR LOSS | BHY1: STATEMENT OF PROFIT OR LOSS | BIG1: STATEMENT OF PROFIT OR LOSS | BIO1: STATEMENT OF PROFIT OR LOSS | BIW1: STATEMENT OF PROFIT OR LOSS | BJE1: STATEMENT OF PROFIT OR LOSS | BJM1: STATEMENT OF PROFIT OR LOSS | BJU1: STATEMENT OF PROFIT OR LOSS | BKC1: STATEMENT OF PROFIT OR LOSS | BKK1: STATEMENT OF PROFIT OR LOSS | BKS1: STATEMENT OF PROFIT OR LOSS | BLA1: STATEMENT OF PROFIT OR LOSS | BLI1: STATEMENT OF PROFIT OR LOSS | BLQ1: STATEMENT OF PROFIT OR LOSS | BLY1: STATEMENT OF PROFIT OR LOSS | BMG1: STATEMENT OF PROFIT OR LOSS | BMO1: STATEMENT OF PROFIT OR LOSS | BMW1: STATEMENT OF PROFIT OR LOSS | BNE1: STATEMENT OF PROFIT OR LOSS | BNM1: STATEMENT OF PROFIT OR LOSS | BNU1: STATEMENT OF PROFIT OR LOSS | BOC1: STATEMENT OF PROFIT OR LOSS | BOK1: STATEMENT OF PROFIT OR LOSS | BOS1: STATEMENT OF PROFIT OR LOSS | BPA1: STATEMENT OF PROFIT OR LOSS | BPI1: STATEMENT OF PROFIT OR LOSS | BPQ1: STATEMENT OF PROFIT OR LOSS | BPY1: STATEMENT OF PROFIT OR LOSS | BQG1: STATEMENT OF PROFIT OR LOSS | BQO1: STATEMENT OF PROFIT OR LOSS | BQW1: STATEMENT OF PROFIT OR LOSS | BRE1: STATEMENT OF PROFIT OR LOSS | BRM1: STATEMENT OF PROFIT OR LOSS | BRU1: STATEMENT OF PROFIT OR LOSS | BSC1: STATEMENT OF PROFIT OR LOSS | BSK1: STATEMENT OF PROFIT OR LOSS | BSS1: STATEMENT OF PROFIT OR LOSS | BTA1: STATEMENT OF PROFIT OR LOSS | BTI1: STATEMENT OF PROFIT OR LOSS | BTQ1: STATEMENT OF PROFIT OR LOSS | BTY1: STATEMENT OF PROFIT OR LOSS | BUG1: STATEMENT OF PROFIT OR LOSS | BUO1: STATEMENT OF PROFIT OR LOSS | BUW1: STATEMENT OF PROFIT OR LOSS | BVE1: STATEMENT OF PROFIT OR LOSS | BVM1: STATEMENT OF PROFIT OR LOSS | BVU1: STATEMENT OF PROFIT OR LOSS | BWC1: STATEMENT OF PROFIT OR LOSS | BWK1: STATEMENT OF PROFIT OR LOSS | BWS1: STATEMENT OF PROFIT OR LOSS | BXA1: STATEMENT OF PROFIT OR LOSS | BXI1: STATEMENT OF PROFIT OR LOSS | BXQ1: STATEMENT OF PROFIT OR LOSS | BXY1: STATEMENT OF PROFIT OR LOSS | BYG1: STATEMENT OF PROFIT OR LOSS | BYO1: STATEMENT OF PROFIT OR LOSS | BYW1: STATEMENT OF PROFIT OR LOSS | BZE1: STATEMENT OF PROFIT OR LOSS | BZM1: STATEMENT OF PROFIT OR LOSS | BZU1: STATEMENT OF PROFIT OR LOSS | CAC1: STATEMENT OF PROFIT OR LOSS | CAK1: STATEMENT OF PROFIT OR LOSS | CAS1: STATEMENT OF PROFIT OR LOSS | CBA1: STATEMENT OF PROFIT OR LOSS | CBI1: STATEMENT OF PROFIT OR LOSS | CBQ1: STATEMENT OF PROFIT OR LOSS | CBY1: STATEMENT OF PROFIT OR LOSS | CCG1: STATEMENT OF PROFIT OR LOSS | CCO1: STATEMENT OF PROFIT OR LOSS | CCW1: STATEMENT OF PROFIT OR LOSS | CDE1: STATEMENT OF PROFIT OR LOSS | CDM1: STATEMENT OF PROFIT OR LOSS | CDU1: STATEMENT OF PROFIT OR LOSS | CEC1: STATEMENT OF PROFIT OR LOSS | CEK1: STATEMENT OF PROFIT OR LOSS | CES1: STATEMENT OF PROFIT OR LOSS | CFA1: STATEMENT OF PROFIT OR LOSS | CFI1: STATEMENT OF PROFIT OR LOSS | CFQ1: STATEMENT OF PROFIT OR LOSS | CFY1: STATEMENT OF PROFIT OR LOSS | CGG1: STATEMENT OF PROFIT OR LOSS | CGO1: STATEMENT OF PROFIT OR LOSS | CGW1: STATEMENT OF PROFIT OR LOSS | CHE1: STATEMENT OF PROFIT OR LOSS | CHM1: STATEMENT OF PROFIT OR LOSS | CHU1: STATEMENT OF PROFIT OR LOSS | CIC1: STATEMENT OF PROFIT OR LOSS | CIK1: STATEMENT OF PROFIT OR LOSS | CIS1: STATEMENT OF PROFIT OR LOSS | CJA1: STATEMENT OF PROFIT OR LOSS | CJI1: STATEMENT OF PROFIT OR LOSS | CJQ1: STATEMENT OF PROFIT OR LOSS | CJY1: STATEMENT OF PROFIT OR LOSS | CKG1: STATEMENT OF PROFIT OR LOSS | CKO1: STATEMENT OF PROFIT OR LOSS | CKW1: STATEMENT OF PROFIT OR LOSS | CLE1: STATEMENT OF PROFIT OR LOSS | CLM1: STATEMENT OF PROFIT OR LOSS | CLU1: STATEMENT OF PROFIT OR LOSS | CMC1: STATEMENT OF PROFIT OR LOSS | CMK1: STATEMENT OF PROFIT OR LOSS | CMS1: STATEMENT OF PROFIT OR LOSS | CNA1: STATEMENT OF PROFIT OR LOSS | CNI1: STATEMENT OF PROFIT OR LOSS | CNQ1: STATEMENT OF PROFIT OR LOSS | CNY1: STATEMENT OF PROFIT OR LOSS | COG1: STATEMENT OF PROFIT OR LOSS | COO1: STATEMENT OF PROFIT OR LOSS | COW1: STATEMENT OF PROFIT OR LOSS | CPE1: STATEMENT OF PROFIT OR LOSS | CPM1: STATEMENT OF PROFIT OR LOSS | CPU1: STATEMENT OF PROFIT OR LOSS | CQC1: STATEMENT OF PROFIT OR LOSS | CQK1: STATEMENT OF PROFIT OR LOSS | CQS1: STATEMENT OF PROFIT OR LOSS | CRA1: STATEMENT OF PROFIT OR LOSS | CRI1: STATEMENT OF PROFIT OR LOSS | CRQ1: STATEMENT OF PROFIT OR LOSS | CRY1: STATEMENT OF PROFIT OR LOSS | CSG1: STATEMENT OF PROFIT OR LOSS | CSO1: STATEMENT OF PROFIT OR LOSS | CSW1: STATEMENT OF PROFIT OR LOSS | CTE1: STATEMENT OF PROFIT OR LOSS | CTM1: STATEMENT OF PROFIT OR LOSS | CTU1: STATEMENT OF PROFIT OR LOSS | CUC1: STATEMENT OF PROFIT OR LOSS | CUK1: STATEMENT OF PROFIT OR LOSS | CUS1: STATEMENT OF PROFIT OR LOSS | CVA1: STATEMENT OF PROFIT OR LOSS | CVI1: STATEMENT OF PROFIT OR LOSS | CVQ1: STATEMENT OF PROFIT OR LOSS | CVY1: STATEMENT OF PROFIT OR LOSS | CWG1: STATEMENT OF PROFIT OR LOSS | CWO1: STATEMENT OF PROFIT OR LOSS | CWW1: STATEMENT OF PROFIT OR LOSS | CXE1: STATEMENT OF PROFIT OR LOSS | CXM1: STATEMENT OF PROFIT OR LOSS | CXU1: STATEMENT OF PROFIT OR LOSS | CYC1: STATEMENT OF PROFIT OR LOSS | CYK1: STATEMENT OF PROFIT OR LOSS | CYS1: STATEMENT OF PROFIT OR LOSS | CZA1: STATEMENT OF PROFIT OR LOSS | CZI1: STATEMENT OF PROFIT OR LOSS | CZQ1: STATEMENT OF PROFIT OR LOSS | CZY1: STATEMENT OF PROFIT OR LOSS | DAG1: STATEMENT OF PROFIT OR LOSS | DAO1: STATEMENT OF PROFIT OR LOSS | DAW1: STATEMENT OF PROFIT OR LOSS | DBE1: STATEMENT OF PROFIT OR LOSS | DBM1: STATEMENT OF PROFIT OR LOSS | DBU1: STATEMENT OF PROFIT OR LOSS | DCC1: STATEMENT OF PROFIT OR LOSS | DCK1: STATEMENT OF PROFIT OR LOSS | DCS1: STATEMENT OF PROFIT OR LOSS | DDA1: STATEMENT OF PROFIT OR LOSS | DDI1: STATEMENT OF PROFIT OR LOSS | DDQ1: STATEMENT OF PROFIT OR LOSS | DDY1: STATEMENT OF PROFIT OR LOSS | DEG1: STATEMENT OF PROFIT OR LOSS | DEO1: STATEMENT OF PROFIT OR LOSS | DEW1: STATEMENT OF PROFIT OR LOSS | DFE1: STATEMENT OF PROFIT OR LOSS | DFM1: STATEMENT OF PROFIT OR LOSS | DFU1: STATEMENT OF PROFIT OR LOSS | DGC1: STATEMENT OF PROFIT OR LOSS | DGK1: STATEMENT OF PROFIT OR LOSS | DGS1: STATEMENT OF PROFIT OR LOSS | DHA1: STATEMENT OF PROFIT OR LOSS | DHI1: STATEMENT OF PROFIT OR LOSS | DHQ1: STATEMENT OF PROFIT OR LOSS | DHY1: STATEMENT OF PROFIT OR LOSS | DIG1: STATEMENT OF PROFIT OR LOSS | DIO1: STATEMENT OF PROFIT OR LOSS | DIW1: STATEMENT OF PROFIT OR LOSS | DJE1: STATEMENT OF PROFIT OR LOSS | DJM1: STATEMENT OF PROFIT OR LOSS | DJU1: STATEMENT OF PROFIT OR LOSS | DKC1: STATEMENT OF PROFIT OR LOSS | DKK1: STATEMENT OF PROFIT OR LOSS | DKS1: STATEMENT OF PROFIT OR LOSS | DLA1: STATEMENT OF PROFIT OR LOSS | DLI1: STATEMENT OF PROFIT OR LOSS | DLQ1: STATEMENT OF PROFIT OR LOSS | DLY1: STATEMENT OF PROFIT OR LOSS | DMG1: STATEMENT OF PROFIT OR LOSS | DMO1: STATEMENT OF PROFIT OR LOSS | DMW1: STATEMENT OF PROFIT OR LOSS | DNE1: STATEMENT OF PROFIT OR LOSS | DNM1: STATEMENT OF PROFIT OR LOSS | DNU1: STATEMENT OF PROFIT OR LOSS | DOC1: STATEMENT OF PROFIT OR LOSS | DOK1: STATEMENT OF PROFIT OR LOSS | DOS1: STATEMENT OF PROFIT OR LOSS | DPA1: STATEMENT OF PROFIT OR LOSS | DPI1: STATEMENT OF PROFIT OR LOSS | DPQ1: STATEMENT OF PROFIT OR LOSS | DPY1: STATEMENT OF PROFIT OR LOSS | DQG1: STATEMENT OF PROFIT OR LOSS | DQO1: STATEMENT OF PROFIT OR LOSS | DQW1: STATEMENT OF PROFIT OR LOSS | DRE1: STATEMENT OF PROFIT OR LOSS | DRM1: STATEMENT OF PROFIT OR LOSS | DRU1: STATEMENT OF PROFIT OR LOSS | DSC1: STATEMENT OF PROFIT OR LOSS | DSK1: STATEMENT OF PROFIT OR LOSS | DSS1: STATEMENT OF PROFIT OR LOSS | DTA1: STATEMENT OF PROFIT OR LOSS | DTI1: STATEMENT OF PROFIT OR LOSS | DTQ1: STATEMENT OF PROFIT OR LOSS | DTY1: STATEMENT OF PROFIT OR LOSS | DUG1: STATEMENT OF PROFIT OR LOSS | DUO1: STATEMENT OF PROFIT OR LOSS | DUW1: STATEMENT OF PROFIT OR LOSS | DVE1: STATEMENT OF PROFIT OR LOSS | DVM1: STATEMENT OF PROFIT OR LOSS | DVU1: STATEMENT OF PROFIT OR LOSS | DWC1: STATEMENT OF PROFIT OR LOSS | DWK1: STATEMENT OF PROFIT OR LOSS | DWS1: STATEMENT OF PROFIT OR LOSS | DXA1: STATEMENT OF PROFIT OR LOSS | DXI1: STATEMENT OF PROFIT OR LOSS | DXQ1: STATEMENT OF PROFIT OR LOSS | DXY1: STATEMENT OF PROFIT OR LOSS | DYG1: STATEMENT OF PROFIT OR LOSS | DYO1: STATEMENT OF PROFIT OR LOSS | DYW1: STATEMENT OF PROFIT OR LOSS | DZE1: STATEMENT OF PROFIT OR LOSS | DZM1: STATEMENT OF PROFIT OR LOSS | DZU1: STATEMENT OF PROFIT OR LOSS | EAC1: STATEMENT OF PROFIT OR LOSS | EAK1: STATEMENT OF PROFIT OR LOSS | EAS1: STATEMENT OF PROFIT OR LOSS | EBA1: STATEMENT OF PROFIT OR LOSS | EBI1: STATEMENT OF PROFIT OR LOSS | EBQ1: STATEMENT OF PROFIT OR LOSS | EBY1: STATEMENT OF PROFIT OR LOSS | ECG1: STATEMENT OF PROFIT OR LOSS | ECO1: STATEMENT OF PROFIT OR LOSS | ECW1: STATEMENT OF PROFIT OR LOSS | EDE1: STATEMENT OF PROFIT OR LOSS | EDM1: STATEMENT OF PROFIT OR LOSS | EDU1: STATEMENT OF PROFIT OR LOSS | EEC1: STATEMENT OF PROFIT OR LOSS | EEK1: STATEMENT OF PROFIT OR LOSS | EES1: STATEMENT OF PROFIT OR LOSS | EFA1: STATEMENT OF PROFIT OR LOSS | EFI1: STATEMENT OF PROFIT OR LOSS | EFQ1: STATEMENT OF PROFIT OR LOSS | EFY1: STATEMENT OF PROFIT OR LOSS | EGG1: STATEMENT OF PROFIT OR LOSS | EGO1: STATEMENT OF PROFIT OR LOSS | EGW1: STATEMENT OF PROFIT OR LOSS | EHE1: STATEMENT OF PROFIT OR LOSS | EHM1: STATEMENT OF PROFIT OR LOSS | EHU1: STATEMENT OF PROFIT OR LOSS | EIC1: STATEMENT OF PROFIT OR LOSS | EIK1: STATEMENT OF PROFIT OR LOSS | EIS1: STATEMENT OF PROFIT OR LOSS | EJA1: STATEMENT OF PROFIT OR LOSS | EJI1: STATEMENT OF PROFIT OR LOSS | EJQ1: STATEMENT OF PROFIT OR LOSS | EJY1: STATEMENT OF PROFIT OR LOSS | EKG1: STATEMENT OF PROFIT OR LOSS | EKO1: STATEMENT OF PROFIT OR LOSS | EKW1: STATEMENT OF PROFIT OR LOSS | ELE1: STATEMENT OF PROFIT OR LOSS | ELM1: STATEMENT OF PROFIT OR LOSS | ELU1: STATEMENT OF PROFIT OR LOSS | EMC1: STATEMENT OF PROFIT OR LOSS | EMK1: STATEMENT OF PROFIT OR LOSS | EMS1: STATEMENT OF PROFIT OR LOSS | ENA1: STATEMENT OF PROFIT OR LOSS | ENI1: STATEMENT OF PROFIT OR LOSS | ENQ1: STATEMENT OF PROFIT OR LOSS | ENY1: STATEMENT OF PROFIT OR LOSS | EOG1: STATEMENT OF PROFIT OR LOSS | EOO1: STATEMENT OF PROFIT OR LOSS | EOW1: STATEMENT OF PROFIT OR LOSS | EPE1: STATEMENT OF PROFIT OR LOSS | EPM1: STATEMENT OF PROFIT OR LOSS | EPU1: STATEMENT OF PROFIT OR LOSS | EQC1: STATEMENT OF PROFIT OR LOSS | EQK1: STATEMENT OF PROFIT OR LOSS | EQS1: STATEMENT OF PROFIT OR LOSS | ERA1: STATEMENT OF PROFIT OR LOSS | ERI1: STATEMENT OF PROFIT OR LOSS | ERQ1: STATEMENT OF PROFIT OR LOSS | ERY1: STATEMENT OF PROFIT OR LOSS | ESG1: STATEMENT OF PROFIT OR LOSS | ESO1: STATEMENT OF PROFIT OR LOSS | ESW1: STATEMENT OF PROFIT OR LOSS | ETE1: STATEMENT OF PROFIT OR LOSS | ETM1: STATEMENT OF PROFIT OR LOSS | ETU1: STATEMENT OF PROFIT OR LOSS | EUC1: STATEMENT OF PROFIT OR LOSS | EUK1: STATEMENT OF PROFIT OR LOSS | EUS1: STATEMENT OF PROFIT OR LOSS | EVA1: STATEMENT OF PROFIT OR LOSS | EVI1: STATEMENT OF PROFIT OR LOSS | EVQ1: STATEMENT OF PROFIT OR LOSS | EVY1: STATEMENT OF PROFIT OR LOSS | EWG1: STATEMENT OF PROFIT OR LOSS | EWO1: STATEMENT OF PROFIT OR LOSS | EWW1: STATEMENT OF PROFIT OR LOSS | EXE1: STATEMENT OF PROFIT OR LOSS | EXM1: STATEMENT OF PROFIT OR LOSS | EXU1: STATEMENT OF PROFIT OR LOSS | EYC1: STATEMENT OF PROFIT OR LOSS | EYK1: STATEMENT OF PROFIT OR LOSS | EYS1: STATEMENT OF PROFIT OR LOSS | EZA1: STATEMENT OF PROFIT OR LOSS | EZI1: STATEMENT OF PROFIT OR LOSS | EZQ1: STATEMENT OF PROFIT OR LOSS | EZY1: STATEMENT OF PROFIT OR LOSS | FAG1: STATEMENT OF PROFIT OR LOSS | FAO1: STATEMENT OF PROFIT OR LOSS | FAW1: STATEMENT OF PROFIT OR LOSS | FBE1: STATEMENT OF PROFIT OR LOSS | FBM1: STATEMENT OF PROFIT OR LOSS | FBU1: STATEMENT OF PROFIT OR LOSS | FCC1: STATEMENT OF PROFIT OR LOSS | FCK1: STATEMENT OF PROFIT OR LOSS | FCS1: STATEMENT OF PROFIT OR LOSS | FDA1: STATEMENT OF PROFIT OR LOSS | FDI1: STATEMENT OF PROFIT OR LOSS | FDQ1: STATEMENT OF PROFIT OR LOSS | FDY1: STATEMENT OF PROFIT OR LOSS | FEG1: STATEMENT OF PROFIT OR LOSS | FEO1: STATEMENT OF PROFIT OR LOSS | FEW1: STATEMENT OF PROFIT OR LOSS | FFE1: STATEMENT OF PROFIT OR LOSS | FFM1: STATEMENT OF PROFIT OR LOSS | FFU1: STATEMENT OF PROFIT OR LOSS | FGC1: STATEMENT OF PROFIT OR LOSS | FGK1: STATEMENT OF PROFIT OR LOSS | FGS1: STATEMENT OF PROFIT OR LOSS | FHA1: STATEMENT OF PROFIT OR LOSS | FHI1: STATEMENT OF PROFIT OR LOSS | FHQ1: STATEMENT OF PROFIT OR LOSS | FHY1: STATEMENT OF PROFIT OR LOSS | FIG1: STATEMENT OF PROFIT OR LOSS | FIO1: STATEMENT OF PROFIT OR LOSS | FIW1: STATEMENT OF PROFIT OR LOSS | FJE1: STATEMENT OF PROFIT OR LOSS | FJM1: STATEMENT OF PROFIT OR LOSS | FJU1: STATEMENT OF PROFIT OR LOSS | FKC1: STATEMENT OF PROFIT OR LOSS | FKK1: STATEMENT OF PROFIT OR LOSS | FKS1: STATEMENT OF PROFIT OR LOSS | FLA1: STATEMENT OF PROFIT OR LOSS | FLI1: STATEMENT OF PROFIT OR LOSS | FLQ1: STATEMENT OF PROFIT OR LOSS | FLY1: STATEMENT OF PROFIT OR LOSS | FMG1: STATEMENT OF PROFIT OR LOSS | FMO1: STATEMENT OF PROFIT OR LOSS | FMW1: STATEMENT OF PROFIT OR LOSS | FNE1: STATEMENT OF PROFIT OR LOSS | FNM1: STATEMENT OF PROFIT OR LOSS | FNU1: STATEMENT OF PROFIT OR LOSS | FOC1: STATEMENT OF PROFIT OR LOSS | FOK1: STATEMENT OF PROFIT OR LOSS | FOS1: STATEMENT OF PROFIT OR LOSS | FPA1: STATEMENT OF PROFIT OR LOSS | FPI1: STATEMENT OF PROFIT OR LOSS | FPQ1: STATEMENT OF PROFIT OR LOSS | FPY1: STATEMENT OF PROFIT OR LOSS | FQG1: STATEMENT OF PROFIT OR LOSS | FQO1: STATEMENT OF PROFIT OR LOSS | FQW1: STATEMENT OF PROFIT OR LOSS | FRE1: STATEMENT OF PROFIT OR LOSS | FRM1: STATEMENT OF PROFIT OR LOSS | FRU1: STATEMENT OF PROFIT OR LOSS | FSC1: STATEMENT OF PROFIT OR LOSS | FSK1: STATEMENT OF PROFIT OR LOSS | FSS1: STATEMENT OF PROFIT OR LOSS | FTA1: STATEMENT OF PROFIT OR LOSS | FTI1: STATEMENT OF PROFIT OR LOSS | FTQ1: STATEMENT OF PROFIT OR LOSS | FTY1: STATEMENT OF PROFIT OR LOSS | FUG1: STATEMENT OF PROFIT OR LOSS | FUO1: STATEMENT OF PROFIT OR LOSS | FUW1: STATEMENT OF PROFIT OR LOSS | FVE1: STATEMENT OF PROFIT OR LOSS | FVM1: STATEMENT OF PROFIT OR LOSS | FVU1: STATEMENT OF PROFIT OR LOSS | FWC1: STATEMENT OF PROFIT OR LOSS | FWK1: STATEMENT OF PROFIT OR LOSS | FWS1: STATEMENT OF PROFIT OR LOSS | FXA1: STATEMENT OF PROFIT OR LOSS | FXI1: STATEMENT OF PROFIT OR LOSS | FXQ1: STATEMENT OF PROFIT OR LOSS | FXY1: STATEMENT OF PROFIT OR LOSS | FYG1: STATEMENT OF PROFIT OR LOSS | FYO1: STATEMENT OF PROFIT OR LOSS | FYW1: STATEMENT OF PROFIT OR LOSS | FZE1: STATEMENT OF PROFIT OR LOSS | FZM1: STATEMENT OF PROFIT OR LOSS | FZU1: STATEMENT OF PROFIT OR LOSS | GAC1: STATEMENT OF PROFIT OR LOSS | GAK1: STATEMENT OF PROFIT OR LOSS | GAS1: STATEMENT OF PROFIT OR LOSS | GBA1: STATEMENT OF PROFIT OR LOSS | GBI1: STATEMENT OF PROFIT OR LOSS | GBQ1: STATEMENT OF PROFIT OR LOSS | GBY1: STATEMENT OF PROFIT OR LOSS | GCG1: STATEMENT OF PROFIT OR LOSS | GCO1: STATEMENT OF PROFIT OR LOSS | GCW1: STATEMENT OF PROFIT OR LOSS | GDE1: STATEMENT OF PROFIT OR LOSS | GDM1: STATEMENT OF PROFIT OR LOSS | GDU1: STATEMENT OF PROFIT OR LOSS | GEC1: STATEMENT OF PROFIT OR LOSS | GEK1: STATEMENT OF PROFIT OR LOSS | GES1: STATEMENT OF PROFIT OR LOSS | GFA1: STATEMENT OF PROFIT OR LOSS | GFI1: STATEMENT OF PROFIT OR LOSS | GFQ1: STATEMENT OF PROFIT OR LOSS | GFY1: STATEMENT OF PROFIT OR LOSS | GGG1: STATEMENT OF PROFIT OR LOSS | GGO1: STATEMENT OF PROFIT OR LOSS | GGW1: STATEMENT OF PROFIT OR LOSS | GHE1: STATEMENT OF PROFIT OR LOSS | GHM1: STATEMENT OF PROFIT OR LOSS | GHU1: STATEMENT OF PROFIT OR LOSS | GIC1: STATEMENT OF PROFIT OR LOSS | GIK1: STATEMENT OF PROFIT OR LOSS | GIS1: STATEMENT OF PROFIT OR LOSS | GJA1: STATEMENT OF PROFIT OR LOSS | GJI1: STATEMENT OF PROFIT OR LOSS | GJQ1: STATEMENT OF PROFIT OR LOSS | GJY1: STATEMENT OF PROFIT OR LOSS | GKG1: STATEMENT OF PROFIT OR LOSS | GKO1: STATEMENT OF PROFIT OR LOSS | GKW1: STATEMENT OF PROFIT OR LOSS | GLE1: STATEMENT OF PROFIT OR LOSS | GLM1: STATEMENT OF PROFIT OR LOSS | GLU1: STATEMENT OF PROFIT OR LOSS | GMC1: STATEMENT OF PROFIT OR LOSS | GMK1: STATEMENT OF PROFIT OR LOSS | GMS1: STATEMENT OF PROFIT OR LOSS | GNA1: STATEMENT OF PROFIT OR LOSS | GNI1: STATEMENT OF PROFIT OR LOSS | GNQ1: STATEMENT OF PROFIT OR LOSS | GNY1: STATEMENT OF PROFIT OR LOSS | GOG1: STATEMENT OF PROFIT OR LOSS | GOO1: STATEMENT OF PROFIT OR LOSS | GOW1: STATEMENT OF PROFIT OR LOSS | GPE1: STATEMENT OF PROFIT OR LOSS | GPM1: STATEMENT OF PROFIT OR LOSS | GPU1: STATEMENT OF PROFIT OR LOSS | GQC1: STATEMENT OF PROFIT OR LOSS | GQK1: STATEMENT OF PROFIT OR LOSS | GQS1: STATEMENT OF PROFIT OR LOSS | GRA1: STATEMENT OF PROFIT OR LOSS | GRI1: STATEMENT OF PROFIT OR LOSS | GRQ1: STATEMENT OF PROFIT OR LOSS | GRY1: STATEMENT OF PROFIT OR LOSS | GSG1: STATEMENT OF PROFIT OR LOSS | GSO1: STATEMENT OF PROFIT OR LOSS | GSW1: STATEMENT OF PROFIT OR LOSS | GTE1: STATEMENT OF PROFIT OR LOSS | GTM1: STATEMENT OF PROFIT OR LOSS | GTU1: STATEMENT OF PROFIT OR LOSS | GUC1: STATEMENT OF PROFIT OR LOSS | GUK1: STATEMENT OF PROFIT OR LOSS | GUS1: STATEMENT OF PROFIT OR LOSS | GVA1: STATEMENT OF PROFIT OR LOSS | GVI1: STATEMENT OF PROFIT OR LOSS | GVQ1: STATEMENT OF PROFIT OR LOSS | GVY1: STATEMENT OF PROFIT OR LOSS | GWG1: STATEMENT OF PROFIT OR LOSS | GWO1: STATEMENT OF PROFIT OR LOSS | GWW1: STATEMENT OF PROFIT OR LOSS | GXE1: STATEMENT OF PROFIT OR LOSS | GXM1: STATEMENT OF PROFIT OR LOSS | GXU1: STATEMENT OF PROFIT OR LOSS | GYC1: STATEMENT OF PROFIT OR LOSS | GYK1: STATEMENT OF PROFIT OR LOSS | GYS1: STATEMENT OF PROFIT OR LOSS | GZA1: STATEMENT OF PROFIT OR LOSS | GZI1: STATEMENT OF PROFIT OR LOSS | GZQ1: STATEMENT OF PROFIT OR LOSS | GZY1: STATEMENT OF PROFIT OR LOSS | HAG1: STATEMENT OF PROFIT OR LOSS | HAO1: STATEMENT OF PROFIT OR LOSS | HAW1: STATEMENT OF PROFIT OR LOSS | HBE1: STATEMENT OF PROFIT OR LOSS | HBM1: STATEMENT OF PROFIT OR LOSS | HBU1: STATEMENT OF PROFIT OR LOSS | HCC1: STATEMENT OF PROFIT OR LOSS | HCK1: STATEMENT OF PROFIT OR LOSS | HCS1: STATEMENT OF PROFIT OR LOSS | HDA1: STATEMENT OF PROFIT OR LOSS | HDI1: STATEMENT OF PROFIT OR LOSS | HDQ1: STATEMENT OF PROFIT OR LOSS | HDY1: STATEMENT OF PROFIT OR LOSS | HEG1: STATEMENT OF PROFIT OR LOSS | HEO1: STATEMENT OF PROFIT OR LOSS | HEW1: STATEMENT OF PROFIT OR LOSS | HFE1: STATEMENT OF PROFIT OR LOSS | HFM1: STATEMENT OF PROFIT OR LOSS | HFU1: STATEMENT OF PROFIT OR LOSS | HGC1: STATEMENT OF PROFIT OR LOSS | HGK1: STATEMENT OF PROFIT OR LOSS | HGS1: STATEMENT OF PROFIT OR LOSS | HHA1: STATEMENT OF PROFIT OR LOSS | HHI1: STATEMENT OF PROFIT OR LOSS | HHQ1: STATEMENT OF PROFIT OR LOSS | HHY1: STATEMENT OF PROFIT OR LOSS | HIG1: STATEMENT OF PROFIT OR LOSS | HIO1: STATEMENT OF PROFIT OR LOSS | HIW1: STATEMENT OF PROFIT OR LOSS | HJE1: STATEMENT OF PROFIT OR LOSS | HJM1: STATEMENT OF PROFIT OR LOSS | HJU1: STATEMENT OF PROFIT OR LOSS | HKC1: STATEMENT OF PROFIT OR LOSS | HKK1: STATEMENT OF PROFIT OR LOSS | HKS1: STATEMENT OF PROFIT OR LOSS | HLA1: STATEMENT OF PROFIT OR LOSS | HLI1: STATEMENT OF PROFIT OR LOSS | HLQ1: STATEMENT OF PROFIT OR LOSS | HLY1: STATEMENT OF PROFIT OR LOSS | HMG1: STATEMENT OF PROFIT OR LOSS | HMO1: STATEMENT OF PROFIT OR LOSS | HMW1: STATEMENT OF PROFIT OR LOSS | HNE1: STATEMENT OF PROFIT OR LOSS | HNM1: STATEMENT OF PROFIT OR LOSS | HNU1: STATEMENT OF PROFIT OR LOSS | HOC1: STATEMENT OF PROFIT OR LOSS | HOK1: STATEMENT OF PROFIT OR LOSS | HOS1: STATEMENT OF PROFIT OR LOSS | HPA1: STATEMENT OF PROFIT OR LOSS | HPI1: STATEMENT OF PROFIT OR LOSS | HPQ1: STATEMENT OF PROFIT OR LOSS | HPY1: STATEMENT OF PROFIT OR LOSS | HQG1: STATEMENT OF PROFIT OR LOSS | HQO1: STATEMENT OF PROFIT OR LOSS | HQW1: STATEMENT OF PROFIT OR LOSS | HRE1: STATEMENT OF PROFIT OR LOSS | HRM1: STATEMENT OF PROFIT OR LOSS | HRU1: STATEMENT OF PROFIT OR LOSS | HSC1: STATEMENT OF PROFIT OR LOSS | HSK1: STATEMENT OF PROFIT OR LOSS | HSS1: STATEMENT OF PROFIT OR LOSS | HTA1: STATEMENT OF PROFIT OR LOSS | HTI1: STATEMENT OF PROFIT OR LOSS | HTQ1: STATEMENT OF PROFIT OR LOSS | HTY1: STATEMENT OF PROFIT OR LOSS | HUG1: STATEMENT OF PROFIT OR LOSS | HUO1: STATEMENT OF PROFIT OR LOSS | HUW1: STATEMENT OF PROFIT OR LOSS | HVE1: STATEMENT OF PROFIT OR LOSS | HVM1: STATEMENT OF PROFIT OR LOSS | HVU1: STATEMENT OF PROFIT OR LOSS | HWC1: STATEMENT OF PROFIT OR LOSS | HWK1: STATEMENT OF PROFIT OR LOSS | HWS1: STATEMENT OF PROFIT OR LOSS | HXA1: STATEMENT OF PROFIT OR LOSS | HXI1: STATEMENT OF PROFIT OR LOSS | HXQ1: STATEMENT OF PROFIT OR LOSS | HXY1: STATEMENT OF PROFIT OR LOSS | HYG1: STATEMENT OF PROFIT OR LOSS | HYO1: STATEMENT OF PROFIT OR LOSS | HYW1: STATEMENT OF PROFIT OR LOSS | HZE1: STATEMENT OF PROFIT OR LOSS | HZM1: STATEMENT OF PROFIT OR LOSS | HZU1: STATEMENT OF PROFIT OR LOSS | IAC1: STATEMENT OF PROFIT OR LOSS | IAK1: STATEMENT OF PROFIT OR LOSS | IAS1: STATEMENT OF PROFIT OR LOSS | IBA1: STATEMENT OF PROFIT OR LOSS | IBI1: STATEMENT OF PROFIT OR LOSS | IBQ1: STATEMENT OF PROFIT OR LOSS | IBY1: STATEMENT OF PROFIT OR LOSS | ICG1: STATEMENT OF PROFIT OR LOSS | ICO1: STATEMENT OF PROFIT OR LOSS | ICW1: STATEMENT OF PROFIT OR LOSS | IDE1: STATEMENT OF PROFIT OR LOSS | IDM1: STATEMENT OF PROFIT OR LOSS | IDU1: STATEMENT OF PROFIT OR LOSS | IEC1: STATEMENT OF PROFIT OR LOSS | IEK1: STATEMENT OF PROFIT OR LOSS | IES1: STATEMENT OF PROFIT OR LOSS | IFA1: STATEMENT OF PROFIT OR LOSS | IFI1: STATEMENT OF PROFIT OR LOSS | IFQ1: STATEMENT OF PROFIT OR LOSS | IFY1: STATEMENT OF PROFIT OR LOSS | IGG1: STATEMENT OF PROFIT OR LOSS | IGO1: STATEMENT OF PROFIT OR LOSS | IGW1: STATEMENT OF PROFIT OR LOSS | IHE1: STATEMENT OF PROFIT OR LOSS | IHM1: STATEMENT OF PROFIT OR LOSS | IHU1: STATEMENT OF PROFIT OR LOSS | IIC1: STATEMENT OF PROFIT OR LOSS | IIK1: STATEMENT OF PROFIT OR LOSS | IIS1: STATEMENT OF PROFIT OR LOSS | IJA1: STATEMENT OF PROFIT OR LOSS | IJI1: STATEMENT OF PROFIT OR LOSS | IJQ1: STATEMENT OF PROFIT OR LOSS | IJY1: STATEMENT OF PROFIT OR LOSS | IKG1: STATEMENT OF PROFIT OR LOSS | IKO1: STATEMENT OF PROFIT OR LOSS | IKW1: STATEMENT OF PROFIT OR LOSS | ILE1: STATEMENT OF PROFIT OR LOSS | ILM1: STATEMENT OF PROFIT OR LOSS | ILU1: STATEMENT OF PROFIT OR LOSS | IMC1: STATEMENT OF PROFIT OR LOSS | IMK1: STATEMENT OF PROFIT OR LOSS | IMS1: STATEMENT OF PROFIT OR LOSS | INA1: STATEMENT OF PROFIT OR LOSS | INI1: STATEMENT OF PROFIT OR LOSS | INQ1: STATEMENT OF PROFIT OR LOSS | INY1: STATEMENT OF PROFIT OR LOSS | IOG1: STATEMENT OF PROFIT OR LOSS | IOO1: STATEMENT OF PROFIT OR LOSS | IOW1: STATEMENT OF PROFIT OR LOSS | IPE1: STATEMENT OF PROFIT OR LOSS | IPM1: STATEMENT OF PROFIT OR LOSS | IPU1: STATEMENT OF PROFIT OR LOSS | IQC1: STATEMENT OF PROFIT OR LOSS | IQK1: STATEMENT OF PROFIT OR LOSS | IQS1: STATEMENT OF PROFIT OR LOSS | IRA1: STATEMENT OF PROFIT OR LOSS | IRI1: STATEMENT OF PROFIT OR LOSS | IRQ1: STATEMENT OF PROFIT OR LOSS | IRY1: STATEMENT OF PROFIT OR LOSS | ISG1: STATEMENT OF PROFIT OR LOSS | ISO1: STATEMENT OF PROFIT OR LOSS | ISW1: STATEMENT OF PROFIT OR LOSS | ITE1: STATEMENT OF PROFIT OR LOSS | ITM1: STATEMENT OF PROFIT OR LOSS | ITU1: STATEMENT OF PROFIT OR LOSS | IUC1: STATEMENT OF PROFIT OR LOSS | IUK1: STATEMENT OF PROFIT OR LOSS | IUS1: STATEMENT OF PROFIT OR LOSS | IVA1: STATEMENT OF PROFIT OR LOSS | IVI1: STATEMENT OF PROFIT OR LOSS | IVQ1: STATEMENT OF PROFIT OR LOSS | IVY1: STATEMENT OF PROFIT OR LOSS | IWG1: STATEMENT OF PROFIT OR LOSS | IWO1: STATEMENT OF PROFIT OR LOSS | IWW1: STATEMENT OF PROFIT OR LOSS | IXE1: STATEMENT OF PROFIT OR LOSS | IXM1: STATEMENT OF PROFIT OR LOSS | IXU1: STATEMENT OF PROFIT OR LOSS | IYC1: STATEMENT OF PROFIT OR LOSS | IYK1: STATEMENT OF PROFIT OR LOSS | IYS1: STATEMENT OF PROFIT OR LOSS | IZA1: STATEMENT OF PROFIT OR LOSS | IZI1: STATEMENT OF PROFIT OR LOSS | IZQ1: STATEMENT OF PROFIT OR LOSS | IZY1: STATEMENT OF PROFIT OR LOSS | JAG1: STATEMENT OF PROFIT OR LOSS | JAO1: STATEMENT OF PROFIT OR LOSS | JAW1: STATEMENT OF PROFIT OR LOSS | JBE1: STATEMENT OF PROFIT OR LOSS | JBM1: STATEMENT OF PROFIT OR LOSS | JBU1: STATEMENT OF PROFIT OR LOSS | JCC1: STATEMENT OF PROFIT OR LOSS | JCK1: STATEMENT OF PROFIT OR LOSS | JCS1: STATEMENT OF PROFIT OR LOSS | JDA1: STATEMENT OF PROFIT OR LOSS | JDI1: STATEMENT OF PROFIT OR LOSS | JDQ1: STATEMENT OF PROFIT OR LOSS | JDY1: STATEMENT OF PROFIT OR LOSS | JEG1: STATEMENT OF PROFIT OR LOSS | JEO1: STATEMENT OF PROFIT OR LOSS | JEW1: STATEMENT OF PROFIT OR LOSS | JFE1: STATEMENT OF PROFIT OR LOSS | JFM1: STATEMENT OF PROFIT OR LOSS | JFU1: STATEMENT OF PROFIT OR LOSS | JGC1: STATEMENT OF PROFIT OR LOSS | JGK1: STATEMENT OF PROFIT OR LOSS | JGS1: STATEMENT OF PROFIT OR LOSS | JHA1: STATEMENT OF PROFIT OR LOSS | JHI1: STATEMENT OF PROFIT OR LOSS | JHQ1: STATEMENT OF PROFIT OR LOSS | JHY1: STATEMENT OF PROFIT OR LOSS | JIG1: STATEMENT OF PROFIT OR LOSS | JIO1: STATEMENT OF PROFIT OR LOSS | JIW1: STATEMENT OF PROFIT OR LOSS | JJE1: STATEMENT OF PROFIT OR LOSS | JJM1: STATEMENT OF PROFIT OR LOSS | JJU1: STATEMENT OF PROFIT OR LOSS | JKC1: STATEMENT OF PROFIT OR LOSS | JKK1: STATEMENT OF PROFIT OR LOSS | JKS1: STATEMENT OF PROFIT OR LOSS | JLA1: STATEMENT OF PROFIT OR LOSS | JLI1: STATEMENT OF PROFIT OR LOSS | JLQ1: STATEMENT OF PROFIT OR LOSS | JLY1: STATEMENT OF PROFIT OR LOSS | JMG1: STATEMENT OF PROFIT OR LOSS | JMO1: STATEMENT OF PROFIT OR LOSS | JMW1: STATEMENT OF PROFIT OR LOSS | JNE1: STATEMENT OF PROFIT OR LOSS | JNM1: STATEMENT OF PROFIT OR LOSS | JNU1: STATEMENT OF PROFIT OR LOSS | JOC1: STATEMENT OF PROFIT OR LOSS | JOK1: STATEMENT OF PROFIT OR LOSS | JOS1: STATEMENT OF PROFIT OR LOSS | JPA1: STATEMENT OF PROFIT OR LOSS | JPI1: STATEMENT OF PROFIT OR LOSS | JPQ1: STATEMENT OF PROFIT OR LOSS | JPY1: STATEMENT OF PROFIT OR LOSS | JQG1: STATEMENT OF PROFIT OR LOSS | JQO1: STATEMENT OF PROFIT OR LOSS | JQW1: STATEMENT OF PROFIT OR LOSS | JRE1: STATEMENT OF PROFIT OR LOSS | JRM1: STATEMENT OF PROFIT OR LOSS | JRU1: STATEMENT OF PROFIT OR LOSS | JSC1: STATEMENT OF PROFIT OR LOSS | JSK1: STATEMENT OF PROFIT OR LOSS | JSS1: STATEMENT OF PROFIT OR LOSS | JTA1: STATEMENT OF PROFIT OR LOSS | JTI1: STATEMENT OF PROFIT OR LOSS | JTQ1: STATEMENT OF PROFIT OR LOSS | JTY1: STATEMENT OF PROFIT OR LOSS | JUG1: STATEMENT OF PROFIT OR LOSS | JUO1: STATEMENT OF PROFIT OR LOSS | JUW1: STATEMENT OF PROFIT OR LOSS | JVE1: STATEMENT OF PROFIT OR LOSS | JVM1: STATEMENT OF PROFIT OR LOSS | JVU1: STATEMENT OF PROFIT OR LOSS | JWC1: STATEMENT OF PROFIT OR LOSS | JWK1: STATEMENT OF PROFIT OR LOSS | JWS1: STATEMENT OF PROFIT OR LOSS | JXA1: STATEMENT OF PROFIT OR LOSS | JXI1: STATEMENT OF PROFIT OR LOSS | JXQ1: STATEMENT OF PROFIT OR LOSS | JXY1: STATEMENT OF PROFIT OR LOSS | JYG1: STATEMENT OF PROFIT OR LOSS | JYO1: STATEMENT OF PROFIT OR LOSS | JYW1: STATEMENT OF PROFIT OR LOSS | JZE1: STATEMENT OF PROFIT OR LOSS | JZM1: STATEMENT OF PROFIT OR LOSS | JZU1: STATEMENT OF PROFIT OR LOSS | KAC1: STATEMENT OF PROFIT OR LOSS | KAK1: STATEMENT OF PROFIT OR LOSS | KAS1: STATEMENT OF PROFIT OR LOSS | KBA1: STATEMENT OF PROFIT OR LOSS | KBI1: STATEMENT OF PROFIT OR LOSS | KBQ1: STATEMENT OF PROFIT OR LOSS | KBY1: STATEMENT OF PROFIT OR LOSS | KCG1: STATEMENT OF PROFIT OR LOSS | KCO1: STATEMENT OF PROFIT OR LOSS | KCW1: STATEMENT OF PROFIT OR LOSS | KDE1: STATEMENT OF PROFIT OR LOSS | KDM1: STATEMENT OF PROFIT OR LOSS | KDU1: STATEMENT OF PROFIT OR LOSS | KEC1: STATEMENT OF PROFIT OR LOSS | KEK1: STATEMENT OF PROFIT OR LOSS | KES1: STATEMENT OF PROFIT OR LOSS | KFA1: STATEMENT OF PROFIT OR LOSS | KFI1: STATEMENT OF PROFIT OR LOSS | KFQ1: STATEMENT OF PROFIT OR LOSS | KFY1: STATEMENT OF PROFIT OR LOSS | KGG1: STATEMENT OF PROFIT OR LOSS | KGO1: STATEMENT OF PROFIT OR LOSS | KGW1: STATEMENT OF PROFIT OR LOSS | KHE1: STATEMENT OF PROFIT OR LOSS | KHM1: STATEMENT OF PROFIT OR LOSS | KHU1: STATEMENT OF PROFIT OR LOSS | KIC1: STATEMENT OF PROFIT OR LOSS | KIK1: STATEMENT OF PROFIT OR LOSS | KIS1: STATEMENT OF PROFIT OR LOSS | KJA1: STATEMENT OF PROFIT OR LOSS | KJI1: STATEMENT OF PROFIT OR LOSS | KJQ1: STATEMENT OF PROFIT OR LOSS | KJY1: STATEMENT OF PROFIT OR LOSS | KKG1: STATEMENT OF PROFIT OR LOSS | KKO1: STATEMENT OF PROFIT OR LOSS | KKW1: STATEMENT OF PROFIT OR LOSS | KLE1: STATEMENT OF PROFIT OR LOSS | KLM1: STATEMENT OF PROFIT OR LOSS | KLU1: STATEMENT OF PROFIT OR LOSS | KMC1: STATEMENT OF PROFIT OR LOSS | KMK1: STATEMENT OF PROFIT OR LOSS | KMS1: STATEMENT OF PROFIT OR LOSS | KNA1: STATEMENT OF PROFIT OR LOSS | KNI1: STATEMENT OF PROFIT OR LOSS | KNQ1: STATEMENT OF PROFIT OR LOSS | KNY1: STATEMENT OF PROFIT OR LOSS | KOG1: STATEMENT OF PROFIT OR LOSS | KOO1: STATEMENT OF PROFIT OR LOSS | KOW1: STATEMENT OF PROFIT OR LOSS | KPE1: STATEMENT OF PROFIT OR LOSS | KPM1: STATEMENT OF PROFIT OR LOSS | KPU1: STATEMENT OF PROFIT OR LOSS | KQC1: STATEMENT OF PROFIT OR LOSS | KQK1: STATEMENT OF PROFIT OR LOSS | KQS1: STATEMENT OF PROFIT OR LOSS | KRA1: STATEMENT OF PROFIT OR LOSS | KRI1: STATEMENT OF PROFIT OR LOSS | KRQ1: STATEMENT OF PROFIT OR LOSS | KRY1: STATEMENT OF PROFIT OR LOSS | KSG1: STATEMENT OF PROFIT OR LOSS | KSO1: STATEMENT OF PROFIT OR LOSS | KSW1: STATEMENT OF PROFIT OR LOSS | KTE1: STATEMENT OF PROFIT OR LOSS | KTM1: STATEMENT OF PROFIT OR LOSS | KTU1: STATEMENT OF PROFIT OR LOSS | KUC1: STATEMENT OF PROFIT OR LOSS | KUK1: STATEMENT OF PROFIT OR LOSS | KUS1: STATEMENT OF PROFIT OR LOSS | KVA1: STATEMENT OF PROFIT OR LOSS | KVI1: STATEMENT OF PROFIT OR LOSS | KVQ1: STATEMENT OF PROFIT OR LOSS | KVY1: STATEMENT OF PROFIT OR LOSS | KWG1: STATEMENT OF PROFIT OR LOSS | KWO1: STATEMENT OF PROFIT OR LOSS | KWW1: STATEMENT OF PROFIT OR LOSS | KXE1: STATEMENT OF PROFIT OR LOSS | KXM1: STATEMENT OF PROFIT OR LOSS | KXU1: STATEMENT OF PROFIT OR LOSS | KYC1: STATEMENT OF PROFIT OR LOSS | KYK1: STATEMENT OF PROFIT OR LOSS | KYS1: STATEMENT OF PROFIT OR LOSS | KZA1: STATEMENT OF PROFIT OR LOSS | KZI1: STATEMENT OF PROFIT OR LOSS | KZQ1: STATEMENT OF PROFIT OR LOSS | KZY1: STATEMENT OF PROFIT OR LOSS | LAG1: STATEMENT OF PROFIT OR LOSS | LAO1: STATEMENT OF PROFIT OR LOSS | LAW1: STATEMENT OF PROFIT OR LOSS | LBE1: STATEMENT OF PROFIT OR LOSS | LBM1: STATEMENT OF PROFIT OR LOSS | LBU1: STATEMENT OF PROFIT OR LOSS | LCC1: STATEMENT OF PROFIT OR LOSS | LCK1: STATEMENT OF PROFIT OR LOSS | LCS1: STATEMENT OF PROFIT OR LOSS | LDA1: STATEMENT OF PROFIT OR LOSS | LDI1: STATEMENT OF PROFIT OR LOSS | LDQ1: STATEMENT OF PROFIT OR LOSS | LDY1: STATEMENT OF PROFIT OR LOSS | LEG1: STATEMENT OF PROFIT OR LOSS | LEO1: STATEMENT OF PROFIT OR LOSS | LEW1: STATEMENT OF PROFIT OR LOSS | LFE1: STATEMENT OF PROFIT OR LOSS | LFM1: STATEMENT OF PROFIT OR LOSS | LFU1: STATEMENT OF PROFIT OR LOSS | LGC1: STATEMENT OF PROFIT OR LOSS | LGK1: STATEMENT OF PROFIT OR LOSS | LGS1: STATEMENT OF PROFIT OR LOSS | LHA1: STATEMENT OF PROFIT OR LOSS | LHI1: STATEMENT OF PROFIT OR LOSS | LHQ1: STATEMENT OF PROFIT OR LOSS | LHY1: STATEMENT OF PROFIT OR LOSS | LIG1: STATEMENT OF PROFIT OR LOSS | LIO1: STATEMENT OF PROFIT OR LOSS | LIW1: STATEMENT OF PROFIT OR LOSS | LJE1: STATEMENT OF PROFIT OR LOSS | LJM1: STATEMENT OF PROFIT OR LOSS | LJU1: STATEMENT OF PROFIT OR LOSS | LKC1: STATEMENT OF PROFIT OR LOSS | LKK1: STATEMENT OF PROFIT OR LOSS | LKS1: STATEMENT OF PROFIT OR LOSS | LLA1: STATEMENT OF PROFIT OR LOSS | LLI1: STATEMENT OF PROFIT OR LOSS | LLQ1: STATEMENT OF PROFIT OR LOSS | LLY1: STATEMENT OF PROFIT OR LOSS | LMG1: STATEMENT OF PROFIT OR LOSS | LMO1: STATEMENT OF PROFIT OR LOSS | LMW1: STATEMENT OF PROFIT OR LOSS | LNE1: STATEMENT OF PROFIT OR LOSS | LNM1: STATEMENT OF PROFIT OR LOSS | LNU1: STATEMENT OF PROFIT OR LOSS | LOC1: STATEMENT OF PROFIT OR LOSS | LOK1: STATEMENT OF PROFIT OR LOSS | LOS1: STATEMENT OF PROFIT OR LOSS | LPA1: STATEMENT OF PROFIT OR LOSS | LPI1: STATEMENT OF PROFIT OR LOSS | LPQ1: STATEMENT OF PROFIT OR LOSS | LPY1: STATEMENT OF PROFIT OR LOSS | LQG1: STATEMENT OF PROFIT OR LOSS | LQO1: STATEMENT OF PROFIT OR LOSS | LQW1: STATEMENT OF PROFIT OR LOSS | LRE1: STATEMENT OF PROFIT OR LOSS | LRM1: STATEMENT OF PROFIT OR LOSS | LRU1: STATEMENT OF PROFIT OR LOSS | LSC1: STATEMENT OF PROFIT OR LOSS | LSK1: STATEMENT OF PROFIT OR LOSS | LSS1: STATEMENT OF PROFIT OR LOSS | LTA1: STATEMENT OF PROFIT OR LOSS | LTI1: STATEMENT OF PROFIT OR LOSS | LTQ1: STATEMENT OF PROFIT OR LOSS | LTY1: STATEMENT OF PROFIT OR LOSS | LUG1: STATEMENT OF PROFIT OR LOSS | LUO1: STATEMENT OF PROFIT OR LOSS | LUW1: STATEMENT OF PROFIT OR LOSS | LVE1: STATEMENT OF PROFIT OR LOSS | LVM1: STATEMENT OF PROFIT OR LOSS | LVU1: STATEMENT OF PROFIT OR LOSS | LWC1: STATEMENT OF PROFIT OR LOSS | LWK1: STATEMENT OF PROFIT OR LOSS | LWS1: STATEMENT OF PROFIT OR LOSS | LXA1: STATEMENT OF PROFIT OR LOSS | LXI1: STATEMENT OF PROFIT OR LOSS | LXQ1: STATEMENT OF PROFIT OR LOSS | LXY1: STATEMENT OF PROFIT OR LOSS | LYG1: STATEMENT OF PROFIT OR LOSS | LYO1: STATEMENT OF PROFIT OR LOSS | LYW1: STATEMENT OF PROFIT OR LOSS | LZE1: STATEMENT OF PROFIT OR LOSS | LZM1: STATEMENT OF PROFIT OR LOSS | LZU1: STATEMENT OF PROFIT OR LOSS | MAC1: STATEMENT OF PROFIT OR LOSS | MAK1: STATEMENT OF PROFIT OR LOSS | MAS1: STATEMENT OF PROFIT OR LOSS | MBA1: STATEMENT OF PROFIT OR LOSS | MBI1: STATEMENT OF PROFIT OR LOSS | MBQ1: STATEMENT OF PROFIT OR LOSS | MBY1: STATEMENT OF PROFIT OR LOSS | MCG1: STATEMENT OF PROFIT OR LOSS | MCO1: STATEMENT OF PROFIT OR LOSS | MCW1: STATEMENT OF PROFIT OR LOSS | MDE1: STATEMENT OF PROFIT OR LOSS | MDM1: STATEMENT OF PROFIT OR LOSS | MDU1: STATEMENT OF PROFIT OR LOSS | MEC1: STATEMENT OF PROFIT OR LOSS | MEK1: STATEMENT OF PROFIT OR LOSS | MES1: STATEMENT OF PROFIT OR LOSS | MFA1: STATEMENT OF PROFIT OR LOSS | MFI1: STATEMENT OF PROFIT OR LOSS | MFQ1: STATEMENT OF PROFIT OR LOSS | MFY1: STATEMENT OF PROFIT OR LOSS | MGG1: STATEMENT OF PROFIT OR LOSS | MGO1: STATEMENT OF PROFIT OR LOSS | MGW1: STATEMENT OF PROFIT OR LOSS | MHE1: STATEMENT OF PROFIT OR LOSS | MHM1: STATEMENT OF PROFIT OR LOSS | MHU1: STATEMENT OF PROFIT OR LOSS | MIC1: STATEMENT OF PROFIT OR LOSS | MIK1: STATEMENT OF PROFIT OR LOSS | MIS1: STATEMENT OF PROFIT OR LOSS | MJA1: STATEMENT OF PROFIT OR LOSS | MJI1: STATEMENT OF PROFIT OR LOSS | MJQ1: STATEMENT OF PROFIT OR LOSS | MJY1: STATEMENT OF PROFIT OR LOSS | MKG1: STATEMENT OF PROFIT OR LOSS | MKO1: STATEMENT OF PROFIT OR LOSS | MKW1: STATEMENT OF PROFIT OR LOSS | MLE1: STATEMENT OF PROFIT OR LOSS | MLM1: STATEMENT OF PROFIT OR LOSS | MLU1: STATEMENT OF PROFIT OR LOSS | MMC1: STATEMENT OF PROFIT OR LOSS | MMK1: STATEMENT OF PROFIT OR LOSS | MMS1: STATEMENT OF PROFIT OR LOSS | MNA1: STATEMENT OF PROFIT OR LOSS | MNI1: STATEMENT OF PROFIT OR LOSS | MNQ1: STATEMENT OF PROFIT OR LOSS | MNY1: STATEMENT OF PROFIT OR LOSS | MOG1: STATEMENT OF PROFIT OR LOSS | MOO1: STATEMENT OF PROFIT OR LOSS | MOW1: STATEMENT OF PROFIT OR LOSS | MPE1: STATEMENT OF PROFIT OR LOSS | MPM1: STATEMENT OF PROFIT OR LOSS | MPU1: STATEMENT OF PROFIT OR LOSS | MQC1: STATEMENT OF PROFIT OR LOSS | MQK1: STATEMENT OF PROFIT OR LOSS | MQS1: STATEMENT OF PROFIT OR LOSS | MRA1: STATEMENT OF PROFIT OR LOSS | MRI1: STATEMENT OF PROFIT OR LOSS | MRQ1: STATEMENT OF PROFIT OR LOSS | MRY1: STATEMENT OF PROFIT OR LOSS | MSG1: STATEMENT OF PROFIT OR LOSS | MSO1: STATEMENT OF PROFIT OR LOSS | MSW1: STATEMENT OF PROFIT OR LOSS | MTE1: STATEMENT OF PROFIT OR LOSS | MTM1: STATEMENT OF PROFIT OR LOSS | MTU1: STATEMENT OF PROFIT OR LOSS | MUC1: STATEMENT OF PROFIT OR LOSS | MUK1: STATEMENT OF PROFIT OR LOSS | MUS1: STATEMENT OF PROFIT OR LOSS | MVA1: STATEMENT OF PROFIT OR LOSS | MVI1: STATEMENT OF PROFIT OR LOSS | MVQ1: STATEMENT OF PROFIT OR LOSS | MVY1: STATEMENT OF PROFIT OR LOSS | MWG1: STATEMENT OF PROFIT OR LOSS | MWO1: STATEMENT OF PROFIT OR LOSS | MWW1: STATEMENT OF PROFIT OR LOSS | MXE1: STATEMENT OF PROFIT OR LOSS | MXM1: STATEMENT OF PROFIT OR LOSS | MXU1: STATEMENT OF PROFIT OR LOSS | MYC1: STATEMENT OF PROFIT OR LOSS | MYK1: STATEMENT OF PROFIT OR LOSS | MYS1: STATEMENT OF PROFIT OR LOSS | MZA1: STATEMENT OF PROFIT OR LOSS | MZI1: STATEMENT OF PROFIT OR LOSS | MZQ1: STATEMENT OF PROFIT OR LOSS | MZY1: STATEMENT OF PROFIT OR LOSS | NAG1: STATEMENT OF PROFIT OR LOSS | NAO1: STATEMENT OF PROFIT OR LOSS | NAW1: STATEMENT OF PROFIT OR LOSS | NBE1: STATEMENT OF PROFIT OR LOSS | NBM1: STATEMENT OF PROFIT OR LOSS | NBU1: STATEMENT OF PROFIT OR LOSS | NCC1: STATEMENT OF PROFIT OR LOSS | NCK1: STATEMENT OF PROFIT OR LOSS | NCS1: STATEMENT OF PROFIT OR LOSS | NDA1: STATEMENT OF PROFIT OR LOSS | NDI1: STATEMENT OF PROFIT OR LOSS | NDQ1: STATEMENT OF PROFIT OR LOSS | NDY1: STATEMENT OF PROFIT OR LOSS | NEG1: STATEMENT OF PROFIT OR LOSS | NEO1: STATEMENT OF PROFIT OR LOSS | NEW1: STATEMENT OF PROFIT OR LOSS | NFE1: STATEMENT OF PROFIT OR LOSS | NFM1: STATEMENT OF PROFIT OR LOSS | NFU1: STATEMENT OF PROFIT OR LOSS | NGC1: STATEMENT OF PROFIT OR LOSS | NGK1: STATEMENT OF PROFIT OR LOSS | NGS1: STATEMENT OF PROFIT OR LOSS | NHA1: STATEMENT OF PROFIT OR LOSS | NHI1: STATEMENT OF PROFIT OR LOSS | NHQ1: STATEMENT OF PROFIT OR LOSS | NHY1: STATEMENT OF PROFIT OR LOSS | NIG1: STATEMENT OF PROFIT OR LOSS | NIO1: STATEMENT OF PROFIT OR LOSS | NIW1: STATEMENT OF PROFIT OR LOSS | NJE1: STATEMENT OF PROFIT OR LOSS | NJM1: STATEMENT OF PROFIT OR LOSS | NJU1: STATEMENT OF PROFIT OR LOSS | NKC1: STATEMENT OF PROFIT OR LOSS | NKK1: STATEMENT OF PROFIT OR LOSS | NKS1: STATEMENT OF PROFIT OR LOSS | NLA1: STATEMENT OF PROFIT OR LOSS | NLI1: STATEMENT OF PROFIT OR LOSS | NLQ1: STATEMENT OF PROFIT OR LOSS | NLY1: STATEMENT OF PROFIT OR LOSS | NMG1: STATEMENT OF PROFIT OR LOSS | NMO1: STATEMENT OF PROFIT OR LOSS | NMW1: STATEMENT OF PROFIT OR LOSS | NNE1: STATEMENT OF PROFIT OR LOSS | NNM1: STATEMENT OF PROFIT OR LOSS | NNU1: STATEMENT OF PROFIT OR LOSS | NOC1: STATEMENT OF PROFIT OR LOSS | NOK1: STATEMENT OF PROFIT OR LOSS | NOS1: STATEMENT OF PROFIT OR LOSS | NPA1: STATEMENT OF PROFIT OR LOSS | NPI1: STATEMENT OF PROFIT OR LOSS | NPQ1: STATEMENT OF PROFIT OR LOSS | NPY1: STATEMENT OF PROFIT OR LOSS | NQG1: STATEMENT OF PROFIT OR LOSS | NQO1: STATEMENT OF PROFIT OR LOSS | NQW1: STATEMENT OF PROFIT OR LOSS | NRE1: STATEMENT OF PROFIT OR LOSS | NRM1: STATEMENT OF PROFIT OR LOSS | NRU1: STATEMENT OF PROFIT OR LOSS | NSC1: STATEMENT OF PROFIT OR LOSS | NSK1: STATEMENT OF PROFIT OR LOSS | NSS1: STATEMENT OF PROFIT OR LOSS | NTA1: STATEMENT OF PROFIT OR LOSS | NTI1: STATEMENT OF PROFIT OR LOSS | NTQ1: STATEMENT OF PROFIT OR LOSS | NTY1: STATEMENT OF PROFIT OR LOSS | NUG1: STATEMENT OF PROFIT OR LOSS | NUO1: STATEMENT OF PROFIT OR LOSS | NUW1: STATEMENT OF PROFIT OR LOSS | NVE1: STATEMENT OF PROFIT OR LOSS | NVM1: STATEMENT OF PROFIT OR LOSS | NVU1: STATEMENT OF PROFIT OR LOSS | NWC1: STATEMENT OF PROFIT OR LOSS | NWK1: STATEMENT OF PROFIT OR LOSS | NWS1: STATEMENT OF PROFIT OR LOSS | NXA1: STATEMENT OF PROFIT OR LOSS | NXI1: STATEMENT OF PROFIT OR LOSS | NXQ1: STATEMENT OF PROFIT OR LOSS | NXY1: STATEMENT OF PROFIT OR LOSS | NYG1: STATEMENT OF PROFIT OR LOSS | NYO1: STATEMENT OF PROFIT OR LOSS | NYW1: STATEMENT OF PROFIT OR LOSS | NZE1: STATEMENT OF PROFIT OR LOSS | NZM1: STATEMENT OF PROFIT OR LOSS | NZU1: STATEMENT OF PROFIT OR LOSS | OAC1: STATEMENT OF PROFIT OR LOSS | OAK1: STATEMENT OF PROFIT OR LOSS | OAS1: STATEMENT OF PROFIT OR LOSS | OBA1: STATEMENT OF PROFIT OR LOSS | OBI1: STATEMENT OF PROFIT OR LOSS | OBQ1: STATEMENT OF PROFIT OR LOSS | OBY1: STATEMENT OF PROFIT OR LOSS | OCG1: STATEMENT OF PROFIT OR LOSS | OCO1: STATEMENT OF PROFIT OR LOSS | OCW1: STATEMENT OF PROFIT OR LOSS | ODE1: STATEMENT OF PROFIT OR LOSS | ODM1: STATEMENT OF PROFIT OR LOSS | ODU1: STATEMENT OF PROFIT OR LOSS | OEC1: STATEMENT OF PROFIT OR LOSS | OEK1: STATEMENT OF PROFIT OR LOSS | OES1: STATEMENT OF PROFIT OR LOSS | OFA1: STATEMENT OF PROFIT OR LOSS | OFI1: STATEMENT OF PROFIT OR LOSS | OFQ1: STATEMENT OF PROFIT OR LOSS | OFY1: STATEMENT OF PROFIT OR LOSS | OGG1: STATEMENT OF PROFIT OR LOSS | OGO1: STATEMENT OF PROFIT OR LOSS | OGW1: STATEMENT OF PROFIT OR LOSS | OHE1: STATEMENT OF PROFIT OR LOSS | OHM1: STATEMENT OF PROFIT OR LOSS | OHU1: STATEMENT OF PROFIT OR LOSS | OIC1: STATEMENT OF PROFIT OR LOSS | OIK1: STATEMENT OF PROFIT OR LOSS | OIS1: STATEMENT OF PROFIT OR LOSS | OJA1: STATEMENT OF PROFIT OR LOSS | OJI1: STATEMENT OF PROFIT OR LOSS | OJQ1: STATEMENT OF PROFIT OR LOSS | OJY1: STATEMENT OF PROFIT OR LOSS | OKG1: STATEMENT OF PROFIT OR LOSS | OKO1: STATEMENT OF PROFIT OR LOSS | OKW1: STATEMENT OF PROFIT OR LOSS | OLE1: STATEMENT OF PROFIT OR LOSS | OLM1: STATEMENT OF PROFIT OR LOSS | OLU1: STATEMENT OF PROFIT OR LOSS | OMC1: STATEMENT OF PROFIT OR LOSS | OMK1: STATEMENT OF PROFIT OR LOSS | OMS1: STATEMENT OF PROFIT OR LOSS | ONA1: STATEMENT OF PROFIT OR LOSS | ONI1: STATEMENT OF PROFIT OR LOSS | ONQ1: STATEMENT OF PROFIT OR LOSS | ONY1: STATEMENT OF PROFIT OR LOSS | OOG1: STATEMENT OF PROFIT OR LOSS | OOO1: STATEMENT OF PROFIT OR LOSS | OOW1: STATEMENT OF PROFIT OR LOSS | OPE1: STATEMENT OF PROFIT OR LOSS | OPM1: STATEMENT OF PROFIT OR LOSS | OPU1: STATEMENT OF PROFIT OR LOSS | OQC1: STATEMENT OF PROFIT OR LOSS | OQK1: STATEMENT OF PROFIT OR LOSS | OQS1: STATEMENT OF PROFIT OR LOSS | ORA1: STATEMENT OF PROFIT OR LOSS | ORI1: STATEMENT OF PROFIT OR LOSS | ORQ1: STATEMENT OF PROFIT OR LOSS | ORY1: STATEMENT OF PROFIT OR LOSS | OSG1: STATEMENT OF PROFIT OR LOSS | OSO1: STATEMENT OF PROFIT OR LOSS | OSW1: STATEMENT OF PROFIT OR LOSS | OTE1: STATEMENT OF PROFIT OR LOSS | OTM1: STATEMENT OF PROFIT OR LOSS | OTU1: STATEMENT OF PROFIT OR LOSS | OUC1: STATEMENT OF PROFIT OR LOSS | OUK1: STATEMENT OF PROFIT OR LOSS | OUS1: STATEMENT OF PROFIT OR LOSS | OVA1: STATEMENT OF PROFIT OR LOSS | OVI1: STATEMENT OF PROFIT OR LOSS | OVQ1: STATEMENT OF PROFIT OR LOSS | OVY1: STATEMENT OF PROFIT OR LOSS | OWG1: STATEMENT OF PROFIT OR LOSS | OWO1: STATEMENT OF PROFIT OR LOSS | OWW1: STATEMENT OF PROFIT OR LOSS | OXE1: STATEMENT OF PROFIT OR LOSS | OXM1: STATEMENT OF PROFIT OR LOSS | OXU1: STATEMENT OF PROFIT OR LOSS | OYC1: STATEMENT OF PROFIT OR LOSS | OYK1: STATEMENT OF PROFIT OR LOSS | OYS1: STATEMENT OF PROFIT OR LOSS | OZA1: STATEMENT OF PROFIT OR LOSS | OZI1: STATEMENT OF PROFIT OR LOSS | OZQ1: STATEMENT OF PROFIT OR LOSS | OZY1: STATEMENT OF PROFIT OR LOSS | PAG1: STATEMENT OF PROFIT OR LOSS | PAO1: STATEMENT OF PROFIT OR LOSS | PAW1: STATEMENT OF PROFIT OR LOSS | PBE1: STATEMENT OF PROFIT OR LOSS | PBM1: STATEMENT OF PROFIT OR LOSS | PBU1: STATEMENT OF PROFIT OR LOSS | PCC1: STATEMENT OF PROFIT OR LOSS | PCK1: STATEMENT OF PROFIT OR LOSS | PCS1: STATEMENT OF PROFIT OR LOSS | PDA1: STATEMENT OF PROFIT OR LOSS | PDI1: STATEMENT OF PROFIT OR LOSS | PDQ1: STATEMENT OF PROFIT OR LOSS | PDY1: STATEMENT OF PROFIT OR LOSS | PEG1: STATEMENT OF PROFIT OR LOSS | PEO1: STATEMENT OF PROFIT OR LOSS | PEW1: STATEMENT OF PROFIT OR LOSS | PFE1: STATEMENT OF PROFIT OR LOSS | PFM1: STATEMENT OF PROFIT OR LOSS | PFU1: STATEMENT OF PROFIT OR LOSS | PGC1: STATEMENT OF PROFIT OR LOSS | PGK1: STATEMENT OF PROFIT OR LOSS | PGS1: STATEMENT OF PROFIT OR LOSS | PHA1: STATEMENT OF PROFIT OR LOSS | PHI1: STATEMENT OF PROFIT OR LOSS | PHQ1: STATEMENT OF PROFIT OR LOSS | PHY1: STATEMENT OF PROFIT OR LOSS | PIG1: STATEMENT OF PROFIT OR LOSS | PIO1: STATEMENT OF PROFIT OR LOSS | PIW1: STATEMENT OF PROFIT OR LOSS | PJE1: STATEMENT OF PROFIT OR LOSS | PJM1: STATEMENT OF PROFIT OR LOSS | PJU1: STATEMENT OF PROFIT OR LOSS | PKC1: STATEMENT OF PROFIT OR LOSS | PKK1: STATEMENT OF PROFIT OR LOSS | PKS1: STATEMENT OF PROFIT OR LOSS | PLA1: STATEMENT OF PROFIT OR LOSS | PLI1: STATEMENT OF PROFIT OR LOSS | PLQ1: STATEMENT OF PROFIT OR LOSS | PLY1: STATEMENT OF PROFIT OR LOSS | PMG1: STATEMENT OF PROFIT OR LOSS | PMO1: STATEMENT OF PROFIT OR LOSS | PMW1: STATEMENT OF PROFIT OR LOSS | PNE1: STATEMENT OF PROFIT OR LOSS | PNM1: STATEMENT OF PROFIT OR LOSS | PNU1: STATEMENT OF PROFIT OR LOSS | POC1: STATEMENT OF PROFIT OR LOSS | POK1: STATEMENT OF PROFIT OR LOSS | POS1: STATEMENT OF PROFIT OR LOSS | PPA1: STATEMENT OF PROFIT OR LOSS | PPI1: STATEMENT OF PROFIT OR LOSS | PPQ1: STATEMENT OF PROFIT OR LOSS | PPY1: STATEMENT OF PROFIT OR LOSS | PQG1: STATEMENT OF PROFIT OR LOSS | PQO1: STATEMENT OF PROFIT OR LOSS | PQW1: STATEMENT OF PROFIT OR LOSS | PRE1: STATEMENT OF PROFIT OR LOSS | PRM1: STATEMENT OF PROFIT OR LOSS | PRU1: STATEMENT OF PROFIT OR LOSS | PSC1: STATEMENT OF PROFIT OR LOSS | PSK1: STATEMENT OF PROFIT OR LOSS | PSS1: STATEMENT OF PROFIT OR LOSS | PTA1: STATEMENT OF PROFIT OR LOSS | PTI1: STATEMENT OF PROFIT OR LOSS | PTQ1: STATEMENT OF PROFIT OR LOSS | PTY1: STATEMENT OF PROFIT OR LOSS | PUG1: STATEMENT OF PROFIT OR LOSS | PUO1: STATEMENT OF PROFIT OR LOSS | PUW1: STATEMENT OF PROFIT OR LOSS | PVE1: STATEMENT OF PROFIT OR LOSS | PVM1: STATEMENT OF PROFIT OR LOSS | PVU1: STATEMENT OF PROFIT OR LOSS | PWC1: STATEMENT OF PROFIT OR LOSS | PWK1: STATEMENT OF PROFIT OR LOSS | PWS1: STATEMENT OF PROFIT OR LOSS | PXA1: STATEMENT OF PROFIT OR LOSS | PXI1: STATEMENT OF PROFIT OR LOSS | PXQ1: STATEMENT OF PROFIT OR LOSS | PXY1: STATEMENT OF PROFIT OR LOSS | PYG1: STATEMENT OF PROFIT OR LOSS | PYO1: STATEMENT OF PROFIT OR LOSS | PYW1: STATEMENT OF PROFIT OR LOSS | PZE1: STATEMENT OF PROFIT OR LOSS | PZM1: STATEMENT OF PROFIT OR LOSS | PZU1: STATEMENT OF PROFIT OR LOSS | QAC1: STATEMENT OF PROFIT OR LOSS | QAK1: STATEMENT OF PROFIT OR LOSS | QAS1: STATEMENT OF PROFIT OR LOSS | QBA1: STATEMENT OF PROFIT OR LOSS | QBI1: STATEMENT OF PROFIT OR LOSS | QBQ1: STATEMENT OF PROFIT OR LOSS | QBY1: STATEMENT OF PROFIT OR LOSS | QCG1: STATEMENT OF PROFIT OR LOSS | QCO1: STATEMENT OF PROFIT OR LOSS | QCW1: STATEMENT OF PROFIT OR LOSS | QDE1: STATEMENT OF PROFIT OR LOSS | QDM1: STATEMENT OF PROFIT OR LOSS | QDU1: STATEMENT OF PROFIT OR LOSS | QEC1: STATEMENT OF PROFIT OR LOSS | QEK1: STATEMENT OF PROFIT OR LOSS | QES1: STATEMENT OF PROFIT OR LOSS | QFA1: STATEMENT OF PROFIT OR LOSS | QFI1: STATEMENT OF PROFIT OR LOSS | QFQ1: STATEMENT OF PROFIT OR LOSS | QFY1: STATEMENT OF PROFIT OR LOSS | QGG1: STATEMENT OF PROFIT OR LOSS | QGO1: STATEMENT OF PROFIT OR LOSS | QGW1: STATEMENT OF PROFIT OR LOSS | QHE1: STATEMENT OF PROFIT OR LOSS | QHM1: STATEMENT OF PROFIT OR LOSS | QHU1: STATEMENT OF PROFIT OR LOSS | QIC1: STATEMENT OF PROFIT OR LOSS | QIK1: STATEMENT OF PROFIT OR LOSS | QIS1: STATEMENT OF PROFIT OR LOSS | QJA1: STATEMENT OF PROFIT OR LOSS | QJI1: STATEMENT OF PROFIT OR LOSS | QJQ1: STATEMENT OF PROFIT OR LOSS | QJY1: STATEMENT OF PROFIT OR LOSS | QKG1: STATEMENT OF PROFIT OR LOSS | QKO1: STATEMENT OF PROFIT OR LOSS | QKW1: STATEMENT OF PROFIT OR LOSS | QLE1: STATEMENT OF PROFIT OR LOSS | QLM1: STATEMENT OF PROFIT OR LOSS | QLU1: STATEMENT OF PROFIT OR LOSS | QMC1: STATEMENT OF PROFIT OR LOSS | QMK1: STATEMENT OF PROFIT OR LOSS | QMS1: STATEMENT OF PROFIT OR LOSS | QNA1: STATEMENT OF PROFIT OR LOSS | QNI1: STATEMENT OF PROFIT OR LOSS | QNQ1: STATEMENT OF PROFIT OR LOSS | QNY1: STATEMENT OF PROFIT OR LOSS | QOG1: STATEMENT OF PROFIT OR LOSS | QOO1: STATEMENT OF PROFIT OR LOSS | QOW1: STATEMENT OF PROFIT OR LOSS | QPE1: STATEMENT OF PROFIT OR LOSS | QPM1: STATEMENT OF PROFIT OR LOSS | QPU1: STATEMENT OF PROFIT OR LOSS | QQC1: STATEMENT OF PROFIT OR LOSS | QQK1: STATEMENT OF PROFIT OR LOSS | QQS1: STATEMENT OF PROFIT OR LOSS | QRA1: STATEMENT OF PROFIT OR LOSS | QRI1: STATEMENT OF PROFIT OR LOSS | QRQ1: STATEMENT OF PROFIT OR LOSS | QRY1: STATEMENT OF PROFIT OR LOSS | QSG1: STATEMENT OF PROFIT OR LOSS | QSO1: STATEMENT OF PROFIT OR LOSS | QSW1: STATEMENT OF PROFIT OR LOSS | QTE1: STATEMENT OF PROFIT OR LOSS | QTM1: STATEMENT OF PROFIT OR LOSS | QTU1: STATEMENT OF PROFIT OR LOSS | QUC1: STATEMENT OF PROFIT OR LOSS | QUK1: STATEMENT OF PROFIT OR LOSS | QUS1: STATEMENT OF PROFIT OR LOSS | QVA1: STATEMENT OF PROFIT OR LOSS | QVI1: STATEMENT OF PROFIT OR LOSS | QVQ1: STATEMENT OF PROFIT OR LOSS | QVY1: STATEMENT OF PROFIT OR LOSS | QWG1: STATEMENT OF PROFIT OR LOSS | QWO1: STATEMENT OF PROFIT OR LOSS | QWW1: STATEMENT OF PROFIT OR LOSS | QXE1: STATEMENT OF PROFIT OR LOSS | QXM1: STATEMENT OF PROFIT OR LOSS | QXU1: STATEMENT OF PROFIT OR LOSS | QYC1: STATEMENT OF PROFIT OR LOSS | QYK1: STATEMENT OF PROFIT OR LOSS | QYS1: STATEMENT OF PROFIT OR LOSS | QZA1: STATEMENT OF PROFIT OR LOSS | QZI1: STATEMENT OF PROFIT OR LOSS | QZQ1: STATEMENT OF PROFIT OR LOSS | QZY1: STATEMENT OF PROFIT OR LOSS | RAG1: STATEMENT OF PROFIT OR LOSS | RAO1: STATEMENT OF PROFIT OR LOSS | RAW1: STATEMENT OF PROFIT OR LOSS | RBE1: STATEMENT OF PROFIT OR LOSS | RBM1: STATEMENT OF PROFIT OR LOSS | RBU1: STATEMENT OF PROFIT OR LOSS | RCC1: STATEMENT OF PROFIT OR LOSS | RCK1: STATEMENT OF PROFIT OR LOSS | RCS1: STATEMENT OF PROFIT OR LOSS | RDA1: STATEMENT OF PROFIT OR LOSS | RDI1: STATEMENT OF PROFIT OR LOSS | RDQ1: STATEMENT OF PROFIT OR LOSS | RDY1: STATEMENT OF PROFIT OR LOSS | REG1: STATEMENT OF PROFIT OR LOSS | REO1: STATEMENT OF PROFIT OR LOSS | REW1: STATEMENT OF PROFIT OR LOSS | RFE1: STATEMENT OF PROFIT OR LOSS | RFM1: STATEMENT OF PROFIT OR LOSS | RFU1: STATEMENT OF PROFIT OR LOSS | RGC1: STATEMENT OF PROFIT OR LOSS | RGK1: STATEMENT OF PROFIT OR LOSS | RGS1: STATEMENT OF PROFIT OR LOSS | RHA1: STATEMENT OF PROFIT OR LOSS | RHI1: STATEMENT OF PROFIT OR LOSS | RHQ1: STATEMENT OF PROFIT OR LOSS | RHY1: STATEMENT OF PROFIT OR LOSS | RIG1: STATEMENT OF PROFIT OR LOSS | RIO1: STATEMENT OF PROFIT OR LOSS | RIW1: STATEMENT OF PROFIT OR LOSS | RJE1: STATEMENT OF PROFIT OR LOSS | RJM1: STATEMENT OF PROFIT OR LOSS | RJU1: STATEMENT OF PROFIT OR LOSS | RKC1: STATEMENT OF PROFIT OR LOSS | RKK1: STATEMENT OF PROFIT OR LOSS | RKS1: STATEMENT OF PROFIT OR LOSS | RLA1: STATEMENT OF PROFIT OR LOSS | RLI1: STATEMENT OF PROFIT OR LOSS | RLQ1: STATEMENT OF PROFIT OR LOSS | RLY1: STATEMENT OF PROFIT OR LOSS | RMG1: STATEMENT OF PROFIT OR LOSS | RMO1: STATEMENT OF PROFIT OR LOSS | RMW1: STATEMENT OF PROFIT OR LOSS | RNE1: STATEMENT OF PROFIT OR LOSS | RNM1: STATEMENT OF PROFIT OR LOSS | RNU1: STATEMENT OF PROFIT OR LOSS | ROC1: STATEMENT OF PROFIT OR LOSS | ROK1: STATEMENT OF PROFIT OR LOSS | ROS1: STATEMENT OF PROFIT OR LOSS | RPA1: STATEMENT OF PROFIT OR LOSS | RPI1: STATEMENT OF PROFIT OR LOSS | RPQ1: STATEMENT OF PROFIT OR LOSS | RPY1: STATEMENT OF PROFIT OR LOSS | RQG1: STATEMENT OF PROFIT OR LOSS | RQO1: STATEMENT OF PROFIT OR LOSS | RQW1: STATEMENT OF PROFIT OR LOSS | RRE1: STATEMENT OF PROFIT OR LOSS | RRM1: STATEMENT OF PROFIT OR LOSS | RRU1: STATEMENT OF PROFIT OR LOSS | RSC1: STATEMENT OF PROFIT OR LOSS | RSK1: STATEMENT OF PROFIT OR LOSS | RSS1: STATEMENT OF PROFIT OR LOSS | RTA1: STATEMENT OF PROFIT OR LOSS | RTI1: STATEMENT OF PROFIT OR LOSS | RTQ1: STATEMENT OF PROFIT OR LOSS | RTY1: STATEMENT OF PROFIT OR LOSS | RUG1: STATEMENT OF PROFIT OR LOSS | RUO1: STATEMENT OF PROFIT OR LOSS | RUW1: STATEMENT OF PROFIT OR LOSS | RVE1: STATEMENT OF PROFIT OR LOSS | RVM1: STATEMENT OF PROFIT OR LOSS | RVU1: STATEMENT OF PROFIT OR LOSS | RWC1: STATEMENT OF PROFIT OR LOSS | RWK1: STATEMENT OF PROFIT OR LOSS | RWS1: STATEMENT OF PROFIT OR LOSS | RXA1: STATEMENT OF PROFIT OR LOSS | RXI1: STATEMENT OF PROFIT OR LOSS | RXQ1: STATEMENT OF PROFIT OR LOSS | RXY1: STATEMENT OF PROFIT OR LOSS | RYG1: STATEMENT OF PROFIT OR LOSS | RYO1: STATEMENT OF PROFIT OR LOSS | RYW1: STATEMENT OF PROFIT OR LOSS | RZE1: STATEMENT OF PROFIT OR LOSS | RZM1: STATEMENT OF PROFIT OR LOSS | RZU1: STATEMENT OF PROFIT OR LOSS | SAC1: STATEMENT OF PROFIT OR LOSS | SAK1: STATEMENT OF PROFIT OR LOSS | SAS1: STATEMENT OF PROFIT OR LOSS | SBA1: STATEMENT OF PROFIT OR LOSS | SBI1: STATEMENT OF PROFIT OR LOSS | SBQ1: STATEMENT OF PROFIT OR LOSS | SBY1: STATEMENT OF PROFIT OR LOSS | SCG1: STATEMENT OF PROFIT OR LOSS | SCO1: STATEMENT OF PROFIT OR LOSS | SCW1: STATEMENT OF PROFIT OR LOSS | SDE1: STATEMENT OF PROFIT OR LOSS | SDM1: STATEMENT OF PROFIT OR LOSS | SDU1: STATEMENT OF PROFIT OR LOSS | SEC1: STATEMENT OF PROFIT OR LOSS | SEK1: STATEMENT OF PROFIT OR LOSS | SES1: STATEMENT OF PROFIT OR LOSS | SFA1: STATEMENT OF PROFIT OR LOSS | SFI1: STATEMENT OF PROFIT OR LOSS | SFQ1: STATEMENT OF PROFIT OR LOSS | SFY1: STATEMENT OF PROFIT OR LOSS | SGG1: STATEMENT OF PROFIT OR LOSS | SGO1: STATEMENT OF PROFIT OR LOSS | SGW1: STATEMENT OF PROFIT OR LOSS | SHE1: STATEMENT OF PROFIT OR LOSS | SHM1: STATEMENT OF PROFIT OR LOSS | SHU1: STATEMENT OF PROFIT OR LOSS | SIC1: STATEMENT OF PROFIT OR LOSS | SIK1: STATEMENT OF PROFIT OR LOSS | SIS1: STATEMENT OF PROFIT OR LOSS | SJA1: STATEMENT OF PROFIT OR LOSS | SJI1: STATEMENT OF PROFIT OR LOSS | SJQ1: STATEMENT OF PROFIT OR LOSS | SJY1: STATEMENT OF PROFIT OR LOSS | SKG1: STATEMENT OF PROFIT OR LOSS | SKO1: STATEMENT OF PROFIT OR LOSS | SKW1: STATEMENT OF PROFIT OR LOSS | SLE1: STATEMENT OF PROFIT OR LOSS | SLM1: STATEMENT OF PROFIT OR LOSS | SLU1: STATEMENT OF PROFIT OR LOSS | SMC1: STATEMENT OF PROFIT OR LOSS | SMK1: STATEMENT OF PROFIT OR LOSS | SMS1: STATEMENT OF PROFIT OR LOSS | SNA1: STATEMENT OF PROFIT OR LOSS | SNI1: STATEMENT OF PROFIT OR LOSS | SNQ1: STATEMENT OF PROFIT OR LOSS | SNY1: STATEMENT OF PROFIT OR LOSS | SOG1: STATEMENT OF PROFIT OR LOSS | SOO1: STATEMENT OF PROFIT OR LOSS | SOW1: STATEMENT OF PROFIT OR LOSS | SPE1: STATEMENT OF PROFIT OR LOSS | SPM1: STATEMENT OF PROFIT OR LOSS | SPU1: STATEMENT OF PROFIT OR LOSS | SQC1: STATEMENT OF PROFIT OR LOSS | SQK1: STATEMENT OF PROFIT OR LOSS | SQS1: STATEMENT OF PROFIT OR LOSS | SRA1: STATEMENT OF PROFIT OR LOSS | SRI1: STATEMENT OF PROFIT OR LOSS | SRQ1: STATEMENT OF PROFIT OR LOSS | SRY1: STATEMENT OF PROFIT OR LOSS | SSG1: STATEMENT OF PROFIT OR LOSS | SSO1: STATEMENT OF PROFIT OR LOSS | SSW1: STATEMENT OF PROFIT OR LOSS | STE1: STATEMENT OF PROFIT OR LOSS | STM1: STATEMENT OF PROFIT OR LOSS | STU1: STATEMENT OF PROFIT OR LOSS | SUC1: STATEMENT OF PROFIT OR LOSS | SUK1: STATEMENT OF PROFIT OR LOSS | SUS1: STATEMENT OF PROFIT OR LOSS | SVA1: STATEMENT OF PROFIT OR LOSS | SVI1: STATEMENT OF PROFIT OR LOSS | SVQ1: STATEMENT OF PROFIT OR LOSS | SVY1: STATEMENT OF PROFIT OR LOSS | SWG1: STATEMENT OF PROFIT OR LOSS | SWO1: STATEMENT OF PROFIT OR LOSS | SWW1: STATEMENT OF PROFIT OR LOSS | SXE1: STATEMENT OF PROFIT OR LOSS | SXM1: STATEMENT OF PROFIT OR LOSS | SXU1: STATEMENT OF PROFIT OR LOSS | SYC1: STATEMENT OF PROFIT OR LOSS | SYK1: STATEMENT OF PROFIT OR LOSS | SYS1: STATEMENT OF PROFIT OR LOSS | SZA1: STATEMENT OF PROFIT OR LOSS | SZI1: STATEMENT OF PROFIT OR LOSS | SZQ1: STATEMENT OF PROFIT OR LOSS | SZY1: STATEMENT OF PROFIT OR LOSS | TAG1: STATEMENT OF PROFIT OR LOSS | TAO1: STATEMENT OF PROFIT OR LOSS | TAW1: STATEMENT OF PROFIT OR LOSS | TBE1: STATEMENT OF PROFIT OR LOSS | TBM1: STATEMENT OF PROFIT OR LOSS | TBU1: STATEMENT OF PROFIT OR LOSS | TCC1: STATEMENT OF PROFIT OR LOSS | TCK1: STATEMENT OF PROFIT OR LOSS | TCS1: STATEMENT OF PROFIT OR LOSS | TDA1: STATEMENT OF PROFIT OR LOSS | TDI1: STATEMENT OF PROFIT OR LOSS | TDQ1: STATEMENT OF PROFIT OR LOSS | TDY1: STATEMENT OF PROFIT OR LOSS | TEG1: STATEMENT OF PROFIT OR LOSS | TEO1: STATEMENT OF PROFIT OR LOSS | TEW1: STATEMENT OF PROFIT OR LOSS | TFE1: STATEMENT OF PROFIT OR LOSS | TFM1: STATEMENT OF PROFIT OR LOSS | TFU1: STATEMENT OF PROFIT OR LOSS | TGC1: STATEMENT OF PROFIT OR LOSS | TGK1: STATEMENT OF PROFIT OR LOSS | TGS1: STATEMENT OF PROFIT OR LOSS | THA1: STATEMENT OF PROFIT OR LOSS | THI1: STATEMENT OF PROFIT OR LOSS | THQ1: STATEMENT OF PROFIT OR LOSS | THY1: STATEMENT OF PROFIT OR LOSS | TIG1: STATEMENT OF PROFIT OR LOSS | TIO1: STATEMENT OF PROFIT OR LOSS | TIW1: STATEMENT OF PROFIT OR LOSS | TJE1: STATEMENT OF PROFIT OR LOSS | TJM1: STATEMENT OF PROFIT OR LOSS | TJU1: STATEMENT OF PROFIT OR LOSS | TKC1: STATEMENT OF PROFIT OR LOSS | TKK1: STATEMENT OF PROFIT OR LOSS | TKS1: STATEMENT OF PROFIT OR LOSS | TLA1: STATEMENT OF PROFIT OR LOSS | TLI1: STATEMENT OF PROFIT OR LOSS | TLQ1: STATEMENT OF PROFIT OR LOSS | TLY1: STATEMENT OF PROFIT OR LOSS | TMG1: STATEMENT OF PROFIT OR LOSS | TMO1: STATEMENT OF PROFIT OR LOSS | TMW1: STATEMENT OF PROFIT OR LOSS | TNE1: STATEMENT OF PROFIT OR LOSS | TNM1: STATEMENT OF PROFIT OR LOSS | TNU1: STATEMENT OF PROFIT OR LOSS | TOC1: STATEMENT OF PROFIT OR LOSS | TOK1: STATEMENT OF PROFIT OR LOSS | TOS1: STATEMENT OF PROFIT OR LOSS | TPA1: STATEMENT OF PROFIT OR LOSS | TPI1: STATEMENT OF PROFIT OR LOSS | TPQ1: STATEMENT OF PROFIT OR LOSS | TPY1: STATEMENT OF PROFIT OR LOSS | TQG1: STATEMENT OF PROFIT OR LOSS | TQO1: STATEMENT OF PROFIT OR LOSS | TQW1: STATEMENT OF PROFIT OR LOSS | TRE1: STATEMENT OF PROFIT OR LOSS | TRM1: STATEMENT OF PROFIT OR LOSS | TRU1: STATEMENT OF PROFIT OR LOSS | TSC1: STATEMENT OF PROFIT OR LOSS | TSK1: STATEMENT OF PROFIT OR LOSS | TSS1: STATEMENT OF PROFIT OR LOSS | TTA1: STATEMENT OF PROFIT OR LOSS | TTI1: STATEMENT OF PROFIT OR LOSS | TTQ1: STATEMENT OF PROFIT OR LOSS | TTY1: STATEMENT OF PROFIT OR LOSS | TUG1: STATEMENT OF PROFIT OR LOSS | TUO1: STATEMENT OF PROFIT OR LOSS | TUW1: STATEMENT OF PROFIT OR LOSS | TVE1: STATEMENT OF PROFIT OR LOSS | TVM1: STATEMENT OF PROFIT OR LOSS | TVU1: STATEMENT OF PROFIT OR LOSS | TWC1: STATEMENT OF PROFIT OR LOSS | TWK1: STATEMENT OF PROFIT OR LOSS | TWS1: STATEMENT OF PROFIT OR LOSS | TXA1: STATEMENT OF PROFIT OR LOSS | TXI1: STATEMENT OF PROFIT OR LOSS | TXQ1: STATEMENT OF PROFIT OR LOSS | TXY1: STATEMENT OF PROFIT OR LOSS | TYG1: STATEMENT OF PROFIT OR LOSS | TYO1: STATEMENT OF PROFIT OR LOSS | TYW1: STATEMENT OF PROFIT OR LOSS | TZE1: STATEMENT OF PROFIT OR LOSS | TZM1: STATEMENT OF PROFIT OR LOSS | TZU1: STATEMENT OF PROFIT OR LOSS | UAC1: STATEMENT OF PROFIT OR LOSS | UAK1: STATEMENT OF PROFIT OR LOSS | UAS1: STATEMENT OF PROFIT OR LOSS | UBA1: STATEMENT OF PROFIT OR LOSS | UBI1: STATEMENT OF PROFIT OR LOSS | UBQ1: STATEMENT OF PROFIT OR LOSS | UBY1: STATEMENT OF PROFIT OR LOSS | UCG1: STATEMENT OF PROFIT OR LOSS | UCO1: STATEMENT OF PROFIT OR LOSS | UCW1: STATEMENT OF PROFIT OR LOSS | UDE1: STATEMENT OF PROFIT OR LOSS | UDM1: STATEMENT OF PROFIT OR LOSS | UDU1: STATEMENT OF PROFIT OR LOSS | UEC1: STATEMENT OF PROFIT OR LOSS | UEK1: STATEMENT OF PROFIT OR LOSS | UES1: STATEMENT OF PROFIT OR LOSS | UFA1: STATEMENT OF PROFIT OR LOSS | UFI1: STATEMENT OF PROFIT OR LOSS | UFQ1: STATEMENT OF PROFIT OR LOSS | UFY1: STATEMENT OF PROFIT OR LOSS | UGG1: STATEMENT OF PROFIT OR LOSS | UGO1: STATEMENT OF PROFIT OR LOSS | UGW1: STATEMENT OF PROFIT OR LOSS | UHE1: STATEMENT OF PROFIT OR LOSS | UHM1: STATEMENT OF PROFIT OR LOSS | UHU1: STATEMENT OF PROFIT OR LOSS | UIC1: STATEMENT OF PROFIT OR LOSS | UIK1: STATEMENT OF PROFIT OR LOSS | UIS1: STATEMENT OF PROFIT OR LOSS | UJA1: STATEMENT OF PROFIT OR LOSS | UJI1: STATEMENT OF PROFIT OR LOSS | UJQ1: STATEMENT OF PROFIT OR LOSS | UJY1: STATEMENT OF PROFIT OR LOSS | UKG1: STATEMENT OF PROFIT OR LOSS | UKO1: STATEMENT OF PROFIT OR LOSS | UKW1: STATEMENT OF PROFIT OR LOSS | ULE1: STATEMENT OF PROFIT OR LOSS | ULM1: STATEMENT OF PROFIT OR LOSS | ULU1: STATEMENT OF PROFIT OR LOSS | UMC1: STATEMENT OF PROFIT OR LOSS | UMK1: STATEMENT OF PROFIT OR LOSS | UMS1: STATEMENT OF PROFIT OR LOSS | UNA1: STATEMENT OF PROFIT OR LOSS | UNI1: STATEMENT OF PROFIT OR LOSS | UNQ1: STATEMENT OF PROFIT OR LOSS | UNY1: STATEMENT OF PROFIT OR LOSS | UOG1: STATEMENT OF PROFIT OR LOSS | UOO1: STATEMENT OF PROFIT OR LOSS | UOW1: STATEMENT OF PROFIT OR LOSS | UPE1: STATEMENT OF PROFIT OR LOSS | UPM1: STATEMENT OF PROFIT OR LOSS | UPU1: STATEMENT OF PROFIT OR LOSS | UQC1: STATEMENT OF PROFIT OR LOSS | UQK1: STATEMENT OF PROFIT OR LOSS | UQS1: STATEMENT OF PROFIT OR LOSS | URA1: STATEMENT OF PROFIT OR LOSS | URI1: STATEMENT OF PROFIT OR LOSS | URQ1: STATEMENT OF PROFIT OR LOSS | URY1: STATEMENT OF PROFIT OR LOSS | USG1: STATEMENT OF PROFIT OR LOSS | USO1: STATEMENT OF PROFIT OR LOSS | USW1: STATEMENT OF PROFIT OR LOSS | UTE1: STATEMENT OF PROFIT OR LOSS | UTM1: STATEMENT OF PROFIT OR LOSS | UTU1: STATEMENT OF PROFIT OR LOSS | UUC1: STATEMENT OF PROFIT OR LOSS | UUK1: STATEMENT OF PROFIT OR LOSS | UUS1: STATEMENT OF PROFIT OR LOSS | UVA1: STATEMENT OF PROFIT OR LOSS | UVI1: STATEMENT OF PROFIT OR LOSS | UVQ1: STATEMENT OF PROFIT OR LOSS | UVY1: STATEMENT OF PROFIT OR LOSS | UWG1: STATEMENT OF PROFIT OR LOSS | UWO1: STATEMENT OF PROFIT OR LOSS | UWW1: STATEMENT OF PROFIT OR LOSS | UXE1: STATEMENT OF PROFIT OR LOSS | UXM1: STATEMENT OF PROFIT OR LOSS | UXU1: STATEMENT OF PROFIT OR LOSS | UYC1: STATEMENT OF PROFIT OR LOSS | UYK1: STATEMENT OF PROFIT OR LOSS | UYS1: STATEMENT OF PROFIT OR LOSS | UZA1: STATEMENT OF PROFIT OR LOSS | UZI1: STATEMENT OF PROFIT OR LOSS | UZQ1: STATEMENT OF PROFIT OR LOSS | UZY1: STATEMENT OF PROFIT OR LOSS | VAG1: STATEMENT OF PROFIT OR LOSS | VAO1: STATEMENT OF PROFIT OR LOSS | VAW1: STATEMENT OF PROFIT OR LOSS | VBE1: STATEMENT OF PROFIT OR LOSS | VBM1: STATEMENT OF PROFIT OR LOSS | VBU1: STATEMENT OF PROFIT OR LOSS | VCC1: STATEMENT OF PROFIT OR LOSS | VCK1: STATEMENT OF PROFIT OR LOSS | VCS1: STATEMENT OF PROFIT OR LOSS | VDA1: STATEMENT OF PROFIT OR LOSS | VDI1: STATEMENT OF PROFIT OR LOSS | VDQ1: STATEMENT OF PROFIT OR LOSS | VDY1: STATEMENT OF PROFIT OR LOSS | VEG1: STATEMENT OF PROFIT OR LOSS | VEO1: STATEMENT OF PROFIT OR LOSS | VEW1: STATEMENT OF PROFIT OR LOSS | VFE1: STATEMENT OF PROFIT OR LOSS | VFM1: STATEMENT OF PROFIT OR LOSS | VFU1: STATEMENT OF PROFIT OR LOSS | VGC1: STATEMENT OF PROFIT OR LOSS | VGK1: STATEMENT OF PROFIT OR LOSS | VGS1: STATEMENT OF PROFIT OR LOSS | VHA1: STATEMENT OF PROFIT OR LOSS | VHI1: STATEMENT OF PROFIT OR LOSS | VHQ1: STATEMENT OF PROFIT OR LOSS | VHY1: STATEMENT OF PROFIT OR LOSS | VIG1: STATEMENT OF PROFIT OR LOSS | VIO1: STATEMENT OF PROFIT OR LOSS | VIW1: STATEMENT OF PROFIT OR LOSS | VJE1: STATEMENT OF PROFIT OR LOSS | VJM1: STATEMENT OF PROFIT OR LOSS | VJU1: STATEMENT OF PROFIT OR LOSS | VKC1: STATEMENT OF PROFIT OR LOSS | VKK1: STATEMENT OF PROFIT OR LOSS | VKS1: STATEMENT OF PROFIT OR LOSS | VLA1: STATEMENT OF PROFIT OR LOSS | VLI1: STATEMENT OF PROFIT OR LOSS | VLQ1: STATEMENT OF PROFIT OR LOSS | VLY1: STATEMENT OF PROFIT OR LOSS | VMG1: STATEMENT OF PROFIT OR LOSS | VMO1: STATEMENT OF PROFIT OR LOSS | VMW1: STATEMENT OF PROFIT OR LOSS | VNE1: STATEMENT OF PROFIT OR LOSS | VNM1: STATEMENT OF PROFIT OR LOSS | VNU1: STATEMENT OF PROFIT OR LOSS | VOC1: STATEMENT OF PROFIT OR LOSS | VOK1: STATEMENT OF PROFIT OR LOSS | VOS1: STATEMENT OF PROFIT OR LOSS | VPA1: STATEMENT OF PROFIT OR LOSS | VPI1: STATEMENT OF PROFIT OR LOSS | VPQ1: STATEMENT OF PROFIT OR LOSS | VPY1: STATEMENT OF PROFIT OR LOSS | VQG1: STATEMENT OF PROFIT OR LOSS | VQO1: STATEMENT OF PROFIT OR LOSS | VQW1: STATEMENT OF PROFIT OR LOSS | VRE1: STATEMENT OF PROFIT OR LOSS | VRM1: STATEMENT OF PROFIT OR LOSS | VRU1: STATEMENT OF PROFIT OR LOSS | VSC1: STATEMENT OF PROFIT OR LOSS | VSK1: STATEMENT OF PROFIT OR LOSS | VSS1: STATEMENT OF PROFIT OR LOSS | VTA1: STATEMENT OF PROFIT OR LOSS | VTI1: STATEMENT OF PROFIT OR LOSS | VTQ1: STATEMENT OF PROFIT OR LOSS | VTY1: STATEMENT OF PROFIT OR LOSS | VUG1: STATEMENT OF PROFIT OR LOSS | VUO1: STATEMENT OF PROFIT OR LOSS | VUW1: STATEMENT OF PROFIT OR LOSS | VVE1: STATEMENT OF PROFIT OR LOSS | VVM1: STATEMENT OF PROFIT OR LOSS | VVU1: STATEMENT OF PROFIT OR LOSS | VWC1: STATEMENT OF PROFIT OR LOSS | VWK1: STATEMENT OF PROFIT OR LOSS | VWS1: STATEMENT OF PROFIT OR LOSS | VXA1: STATEMENT OF PROFIT OR LOSS | VXI1: STATEMENT OF PROFIT OR LOSS | VXQ1: STATEMENT OF PROFIT OR LOSS | VXY1: STATEMENT OF PROFIT OR LOSS | VYG1: STATEMENT OF PROFIT OR LOSS | VYO1: STATEMENT OF PROFIT OR LOSS | VYW1: STATEMENT OF PROFIT OR LOSS | VZE1: STATEMENT OF PROFIT OR LOSS | VZM1: STATEMENT OF PROFIT OR LOSS | VZU1: STATEMENT OF PROFIT OR LOSS | WAC1: STATEMENT OF PROFIT OR LOSS | WAK1: STATEMENT OF PROFIT OR LOSS | WAS1: STATEMENT OF PROFIT OR LOSS | WBA1: STATEMENT OF PROFIT OR LOSS | WBI1: STATEMENT OF PROFIT OR LOSS | WBQ1: STATEMENT OF PROFIT OR LOSS | WBY1: STATEMENT OF PROFIT OR LOSS | WCG1: STATEMENT OF PROFIT OR LOSS | WCO1: STATEMENT OF PROFIT OR LOSS | WCW1: STATEMENT OF PROFIT OR LOSS | WDE1: STATEMENT OF PROFIT OR LOSS | WDM1: STATEMENT OF PROFIT OR LOSS | WDU1: STATEMENT OF PROFIT OR LOSS | WEC1: STATEMENT OF PROFIT OR LOSS | WEK1: STATEMENT OF PROFIT OR LOSS | WES1: STATEMENT OF PROFIT OR LOSS | WFA1: STATEMENT OF PROFIT OR LOSS | WFI1: STATEMENT OF PROFIT OR LOSS | WFQ1: STATEMENT OF PROFIT OR LOSS | WFY1: STATEMENT OF PROFIT OR LOSS | WGG1: STATEMENT OF PROFIT OR LOSS | WGO1: STATEMENT OF PROFIT OR LOSS | WGW1: STATEMENT OF PROFIT OR LOSS | WHE1: STATEMENT OF PROFIT OR LOSS | WHM1: STATEMENT OF PROFIT OR LOSS | WHU1: STATEMENT OF PROFIT OR LOSS | WIC1: STATEMENT OF PROFIT OR LOSS | WIK1: STATEMENT OF PROFIT OR LOSS | WIS1: STATEMENT OF PROFIT OR LOSS | WJA1: STATEMENT OF PROFIT OR LOSS | WJI1: STATEMENT OF PROFIT OR LOSS | WJQ1: STATEMENT OF PROFIT OR LOSS | WJY1: STATEMENT OF PROFIT OR LOSS | WKG1: STATEMENT OF PROFIT OR LOSS | WKO1: STATEMENT OF PROFIT OR LOSS | WKW1: STATEMENT OF PROFIT OR LOSS | WLE1: STATEMENT OF PROFIT OR LOSS | WLM1: STATEMENT OF PROFIT OR LOSS | WLU1: STATEMENT OF PROFIT OR LOSS | WMC1: STATEMENT OF PROFIT OR LOSS | WMK1: STATEMENT OF PROFIT OR LOSS | WMS1: STATEMENT OF PROFIT OR LOSS | WNA1: STATEMENT OF PROFIT OR LOSS | WNI1: STATEMENT OF PROFIT OR LOSS | WNQ1: STATEMENT OF PROFIT OR LOSS | WNY1: STATEMENT OF PROFIT OR LOSS | WOG1: STATEMENT OF PROFIT OR LOSS | WOO1: STATEMENT OF PROFIT OR LOSS | WOW1: STATEMENT OF PROFIT OR LOSS | WPE1: STATEMENT OF PROFIT OR LOSS | WPM1: STATEMENT OF PROFIT OR LOSS | WPU1: STATEMENT OF PROFIT OR LOSS | WQC1: STATEMENT OF PROFIT OR LOSS | WQK1: STATEMENT OF PROFIT OR LOSS | WQS1: STATEMENT OF PROFIT OR LOSS | WRA1: STATEMENT OF PROFIT OR LOSS | WRI1: STATEMENT OF PROFIT OR LOSS | WRQ1: STATEMENT OF PROFIT OR LOSS | WRY1: STATEMENT OF PROFIT OR LOSS | WSG1: STATEMENT OF PROFIT OR LOSS | WSO1: STATEMENT OF PROFIT OR LOSS | WSW1: STATEMENT OF PROFIT OR LOSS | WTE1: STATEMENT OF PROFIT OR LOSS | WTM1: STATEMENT OF PROFIT OR LOSS | WTU1: STATEMENT OF PROFIT OR LOSS | WUC1: STATEMENT OF PROFIT OR LOSS | WUK1: STATEMENT OF PROFIT OR LOSS | WUS1: STATEMENT OF PROFIT OR LOSS | WVA1: STATEMENT OF PROFIT OR LOSS | WVI1: STATEMENT OF PROFIT OR LOSS | WVQ1: STATEMENT OF PROFIT OR LOSS | WVY1: STATEMENT OF PROFIT OR LOSS | WWG1: STATEMENT OF PROFIT OR LOSS | WWO1: STATEMENT OF PROFIT OR LOSS | WWW1: STATEMENT OF PROFIT OR LOSS | WXE1: STATEMENT OF PROFIT OR LOSS | WXM1: STATEMENT OF PROFIT OR LOSS | WXU1: STATEMENT OF PROFIT OR LOSS | WYC1: STATEMENT OF PROFIT OR LOSS | WYK1: STATEMENT OF PROFIT OR LOSS | WYS1: STATEMENT OF PROFIT OR LOSS | WZA1: STATEMENT OF PROFIT OR LOSS | WZI1: STATEMENT OF PROFIT OR LOSS | WZQ1: STATEMENT OF PROFIT OR LOSS | WZY1: STATEMENT OF PROFIT OR LOSS | XAG1: STATEMENT OF PROFIT OR LOSS | XAO1: STATEMENT OF PROFIT OR LOSS | XAW1: STATEMENT OF PROFIT OR LOSS | XBE1: STATEMENT OF PROFIT OR LOSS | XBM1: STATEMENT OF PROFIT OR LOSS | XBU1: STATEMENT OF PROFIT OR LOSS | XCC1: STATEMENT OF PROFIT OR LOSS | XCK1: STATEMENT OF PROFIT OR LOSS | XCS1: STATEMENT OF PROFIT OR LOSS | XDA1: STATEMENT OF PROFIT OR LOSS | XDI1: STATEMENT OF PROFIT OR LOSS | XDQ1: STATEMENT OF PROFIT OR LOSS | XDY1: STATEMENT OF PROFIT OR LOSS | XEG1: STATEMENT OF PROFIT OR LOSS | XEO1: STATEMENT OF PROFIT OR LOSS | XEW1: STATEMENT OF PROFIT OR LOSS
A2: As at 31st March (In Rs.’000s) | B2: 2019 | C2: 2020 | D2: 2021 | E2: 2022 | F2: 2023 | G2: 2024 | H2: 2025 | I2: 2026 | J2: 2027 | K2: 2028 | L2: 2029 | M2: 2030
A3: ASSETS
A4: Non-current assets
A5: Property, plant & equipment | B5: 18162978 | C5: 19221050 | D5: 18869754 | E5: 20574458 | F5: 22996451 | G5: 27161069 | H5: 29197945 | I5: =CapEx!I7 -> 31368114 | J5: =CapEx!J7 -> 33455503 | K5: =CapEx!K7 -> 35471083 | L5: =CapEx!L7 -> 37424856 | M5: =CapEx!M7 -> 39325951
A6: Investment properties | B6: 331261 | C6: 486870 | D6: 486870 | E6: 647100 | F6: 810200 | G6: 815200 | H6: 861000 | I6: =H6*(1+I7) -> 951233.21 | J6: =I6*(1+J7) -> 1050922.9 | K6: =J6*(1+K7) -> 1161060.1 | L6: =K6*(1+L7) -> 1282739.8 | M6: =L6*(1+M7) -> 1417171.6
A7: YoY% | C7: =C6/B6-1 -> 0.46974742 | D7: =D6/C6-1 -> 0 | E7: =E6/D6-1 -> 0.32910222 | F7: =F6/E6-1 -> 0.2520476 | G7: =G6/F6-1 -> 0.0061713157 | H7: =H6/G6-1 -> 0.056182532 | I7: =AVERAGE(F7:H7) -> 0.10480048 | J7: =I7 -> 0.10480048 | K7: =J7 -> 0.10480048 | L7: =K7 -> 0.10480048 | M7: =L7 -> 0.10480048
A8: Intangible assets | B8: 2442755 | C8: 1706873 | D8: 1289652 | E8: 819545 | F8: 458843 | G8: 768925 | H8: 212229 | I8: =CapEx!I15 -> 239963.21 | J8: =CapEx!J15 -> 270668.4 | K8: =CapEx!K15 -> 304786.96 | L8: =CapEx!L15 -> 342799.35 | M8: =CapEx!M15 -> 385231.98
A9: Right of use assets | B9: - | C9: 304355 | D9: 239149 | E9: 207281 | F9: 209947 | G9: 223969 | H9: 768078 | I9: =CapEx!I23 -> 663526.45 | J9: =CapEx!J23 -> 590520.3 | K9: =CapEx!K23 -> 542997.12 | L9: =CapEx!L23 -> 516371.7 | M9: =CapEx!M23 -> 507220.46
A10: Deferred tax assets | B10: 13496 | C10: 8691 | D10: 23860 | E10: 1548 | F10: 26378 | G10: 46716 | H10: 171724 | I10: =H10 -> 171724 | J10: =I10 -> 171724 | K10: =J10 -> 171724 | L10: =K10 -> 171724 | M10: =L10 -> 171724
A11: Investments in subsidiaries | E11: 0 | F11: 0 | G11: 0 | H11: 0 | I11: 0 | J11: 0 | K11: 0 | L11: 0 | M11: 0
A12: Total non-current assets | B12: =SUM(B5:B11) -> 20950490 | C12: =SUM(C5:C11) -> 21727839 | D12: =SUM(D5:D11) -> 20909285 | E12: =SUM(E5:E11) -> 22249932 | F12: =SUM(F5:F11) -> 24501819 | G12: =SUM(G5:G11) -> 29015879 | H12: 1611178 | I12: =SUM(I5:I11) -> 33394561 | J12: =SUM(J5:J11) -> 35539339 | K12: =SUM(K5:K11) -> 37651652 | L12: =SUM(L5:L11) -> 39738491 | M12: =SUM(M5:M11) -> 41807299
A14: Current assets
A15: Inventories | B15: 2512995 | C15: 3043692 | D15: 3721062 | E15: 4537111 | F15: 7451345 | G15: 9123121 | H15: 8285443 | I15: =WC!I6 -> 9373111.3 | J15: =WC!J6 -> 10510737 | K15: =WC!K6 -> 11786805 | L15: =WC!L6 -> 13218219 | M15: =WC!M6 -> 14823952
A16: Trade & other receivables | B16: 2345704 | C16: 1881002 | D16: 1796923 | E16: 2406133 | F16: 5530902 | G16: 6022460 | H16: 5675836 | I16: =WC!I4 -> 6364525 | J16: =WC!J4 -> 7136994.9 | K16: =WC!K4 -> 8003470.3 | L16: =WC!L4 -> 8975428.1 | M16: =WC!M4 -> 10065752
A17: Amounts due from related companies | B17: 0 | C17: 6500 | D17: 0 | E17: 0 | F17: 0 | G17: 0 | H17: 0 | I17: 0 | J17: 0 | K17: 0 | L17: 0 | M17: 0
A18: Current taxation | B18: 5653 | C18: 2477 | D18: 2477 | E18: 0 | F18: 639 | G18: 0 | H18: 4657842 | I18: =H18 -> 4657842 | J18: =I18 -> 4657842 | K18: =J18 -> 4657842 | L18: =K18 -> 4657842 | M18: =L18 -> 4657842
A19: Cash and cash equivalents | B19: 10564799 | C19: 13367260 | D19: 9701006 | E19: 13114311 | F19: 11348046 | G19: 12571174 | H19: 13475936 | I19: =CF!I65 -> 15756606 | J19: =CF!J65 -> 20745535 | K19: =CF!K65 -> 27206508 | L19: =CF!L65 -> 34973401 | M19: =CF!M65 -> 46057281
A20: YoY% | C20: =C19/B19-1 -> 0.26526401 | D20: =D19/C19-1 -> -0.27427117 | E20: =E19/D19-1 -> 0.35185062 | F20: =F19/E19-1 -> -0.13468226 | G20: =G19/F19-1 -> 0.10778314 | H20: =H19/G19-1 -> 0.071971162 | I20: =I19/H19-1 -> 0.16924021 | J20: =J19/I19-1 -> 0.31662455 | ... M20: =M19/L19-1 -> 0.31692316
A21: Total current assets | B21: 15429151 | C21: 18300931 | D21: 15221468 | E21: 20057555 | F21: 24330932 | G21: 27716755 | H21: 32095057 | I21: =I15+I16+I17+I18+I19 -> 36152085 | J21: =J15+J16+J17+J18+J19 -> 43051109 | K21: =K15+K16+K17+K18+K19 -> 51654626 | L21: =L15+L16+L17+L18+L19 -> 61824890 | M21: =M15+M16+M17+M18+M19 -> 75604828
A22: Total assets | B22: 36379641 | C22: 40028770 | D22: 36130753 | E22: 42307487 | F22: 48832751 | G22: 56732634 | H22: 64917211 | I22: =I12+I21 -> 69546645 | J22: =J12+J21 -> 78590448 | K22: =K12+K21 -> 89306278 | L22: =L12+L21 -> 1.0156338e+08 | M22: =M12+M21 -> 1.1741213e+08
A24: EQUITY AND LIABILITIES
A25: Equity
A26: Stated capital | B26: 533384 | C26: 533384 | D26: 533384 | E26: 533384 | F26: 533384 | G26: 533384 | H26: 533384 | I26: =H26 -> 533384 | J26: =I26 -> 533384 | K26: =J26 -> 533384 | L26: =K26 -> 533384 | M26: =L26 -> 533384
A27: Capital reserves | B27: 588521 | C27: 735712 | D27: 735712 | E27: 1103358 | F27: 1103358 | G27: 1491952 | H27: 1360069 | I27: =H27 -> 1360069 | J27: =I27 -> 1360069 | K27: =J27 -> 1360069 | L27: =K27 -> 1360069 | M27: =L27 -> 1360069
A28: Revenue reserves | B28: 5049101 | C28: 6321790 | D28: 7290140 | E28: 8720708 | F28: 10345024 | G28: 12591143 | H28: 16633227 | I28: =H28+IS!I21+CF!I55 -> 25685374 | J28: =I28+IS!J21-CF!J55 -> 41071707 | K28: =J28+IS!K21-CF!K55 -> 58380372 | L28: =K28+IS!L21-CF!L55 -> 77542419 | M28: =L28+IS!M21-CF!M55 -> 98891515
A29: Translation reserve | F29: - | G29: -3660 | H29: -11411 | I29: 0 | J29: 0 | K29: 0 | L29: 0 | M29: 0
A30: Equity attributable to equity holders of the company | B30: 6171006 | C30: 7590886 | D30: 8559236 | E30: 10357450 | F30: 11981766 | G30: 14612819 | H30: 18515269 | I30: =SUM(I26:I29) -> 27578827 | J30: =SUM(J26:J29) -> 42965160 | K30: =SUM(K26:K29) -> 60273825 | L30: =SUM(L26:L29) -> 79435872 | M30: =SUM(M26:M29) -> 1.0078497e+08
A31: Non controlling interest | B31: 5978375 | C31: 7230325 | D31: 8104994 | E31: 9515171 | F31: 11090491 | G31: 13178793 | H31: 16435215 | I31: =H31 -> 16435215 | J31: =I31 -> 16435215 | K31: =J31 -> 16435215 | L31: =K31 -> 16435215 | M31: =L31 -> 16435215
A32: Total equity | B32: 12149381 | C32: 14821211 | D32: 16664230 | E32: 19872621 | F32: 23072257 | G32: 27791612 | H32: 34950484 | I32: =I30+I31 -> 44014042 | J32: =SUM(J26:J31) -> 1.0236554e+08 | K32: =SUM(K26:K31) -> 1.3698287e+08 | L32: =SUM(L26:L31) -> 1.7530696e+08 | M32: =SUM(M26:M31) -> 2.1800515e+08
A34: Non current liabilities
A35: Loans and borrowings | B35: 3326271 | C35: 2658041 | D35: 3497060 | E35: 2300311 | F35: 1924442 | G35: 1373569 | H35: 2236667 | I35: ='Loan Schedule'!B7 -> 3996162.8 | J35: ='Loan Schedule'!C7 -> 2927903.2 | K35: ='Loan Schedule'!D7 -> 1623344.6 | L35: ='Loan Schedule'!E7 -> 30217.687 | M35: ='Loan Schedule'!F7 -> -125782.39
A36: Lease liabilities | B36: - | C36: 274532 | D36: 218088 | E36: 196109 | F36: 216501 | G36: 233800 | H36: 231728 | I36: =H36 -> 231728 | J36: =I36 -> 231728 | K36: =J36 -> 231728 | L36: =K36 -> 231728 | M36: =L36 -> 231728
A37: Employee benefits | B37: 204058 | C37: 207333 | D37: 243171 | E37: 182996 | F37: 257730 | G37: 293935 | H37: 399658 | I37: =AVERAGE(B37:H37) -> 255554.43 | J37: =I37 -> 255554.43 | K37: =J37 -> 255554.43 | L37: =K37 -> 255554.43 | M37: =L37 -> 255554.43
A38: Deferred tax liabilities | B38: 5002666 | C38: 5134844 | D38: 5106713 | E38: 5260140 | F38: 5687986 | G38: 6581796 | H38: 7325395 | I38: =AVERAGE(B38:H38) -> 5728505.7 | J38: =I38 -> 5728505.7 | K38: =J38 -> 5728505.7 | L38: =K38 -> 5728505.7 | M38: =L38 -> 5728505.7
A39: Total non- current liabilities | B39: 8532995 | C39: 8274750 | D39: 9065032 | E39: 7939556 | F39: 8086659 | G39: 8483100 | H39: 10193448 | I39: =I35+I36+I37+I38 -> 10211951 | J39: =J35+J36+J37+J38 -> 9143691.4 | K39: =K35+K36+K37+K38 -> 7839132.8 | L39: =L35+L36+L37+L38 -> 6246005.8 | M39: =M35+M36+M37+M38 -> 6090005.7
A41: Current liabilities
A42: Trade and other payables | B42: 1350370 | C42: 1780350 | D42: 1998429 | E42: 3492710 | F42: 4829899 | G42: 4567905 | H42: 5592536 | I42: =WC!I5 -> 6248127.9 | J42: =WC!J5 -> 7006470.6 | K42: =WC!K5 -> 7857099.5 | L42: =WC!L5 -> 8811281.8 | M42: =WC!M5 -> 9881665.4
A43: Amounts due to related companies | B43: 114945 | C43: 107748 | D43: 122828 | E43: 155757 | F43: 76041 | G43: 123606 | H43: 102233 | I43: =H43 -> 102233 | J43: =I43 -> 102233 | K43: =J43 -> 102233 | L43: =K43 -> 102233 | M43: =L43 -> 102233
A44: Refundable deposits | B44: 1456224 | C44: 1715620 | D44: 1900393 | E44: 2301181 | F44: 2742490 | G44: 2996694 | H44: 3539121 | I44: =AVERAGE(B44:H44) -> 2378817.6 | J44: =I44 -> 2378817.6 | K44: =J44 -> 2378817.6 | L44: =K44 -> 2378817.6 | M44: =L44 -> 2378817.6
A45: Current tax liabilities | B45: 2448319 | C45: 104398 | D45: 2414089 | E45: 3163706 | F45: 2855295 | G45: 6918504 | H45: 5931175 | I45: 0 | J45: =I45 -> 0 | K45: =J45 -> 0 | L45: =K45 -> 0 | M45: =L45 -> 0
A46: Debentures | B46: 2078285 | C46: 0 | D46: 0 | E46: 0 | F46: 0 | G46: 0 | H46: 0 | I46: 0 | J46: 0 | K46: 0 | L46: 0 | M46: 0
A47: Loans and borrowings | B47: 6353084 | C47: 9988456 | D47: 1893727 | E47: 3347696 | F47: 5080158 | G47: 3219699 | H47: 2634258 | I47: =H47-1500000 -> 1134258 | J47: 0 | K47: 0 | L47: 0 | M47: 0
A48: Lease liabilities | B48: 0 | C48: 50532 | D48: 57233 | E48: 57499 | F48: 45054 | G48: 44166 | H48: 40901 | I48: =H48 -> 40901 | J48: =I48 -> 40901 | K48: =J48 -> 40901 | L48: =K48 -> 40901 | M48: =L48 -> 40901
A49: Bank overdraft | B49: 1896038 | C49: 3185705 | D49: 2014792 | E49: 1976761 | F49: 2044898 | G49: 2587348 | H49: 1933055 | I49: =H49 -> 1933055 | J49: =I49 -> 1933055 | K49: =J49 -> 1933055 | L49: =K49 -> 1933055 | M49: =L49 -> 1933055
A50: Total current liabilities | B50: 15697265 | C50: 16932809 | D50: 10401491 | E50: 14495310 | F50: 17673835 | G50: 20457922 | H50: 19773279 | I50: =I42+I43+I44+I45+I46+I47+I48+I49 -> 11837392 | J50: =J42+J43+J44+J45+J46+J47+J48+J49 -> 11461477 | K50: =K42+K43+K44+K45+K46+K47+K48+K49 -> 12312106 | L50: =L42+L43+L44+L45+L46+L47+L48+L49 -> 13266288 | M50: =M42+M43+M44+M45+M46+M47+M48+M49 -> 14336672
A51: Total liabilities | B51: 24230260 | C51: 25207559 | D51: 19466523 | E51: 22434866 | F51: 25760494 | G51: 28941022 | H51: 29966727 | I51: =I39+I50 -> 22049343 | J51: =J39+J50 -> 20605169 | K51: =K39+K50 -> 20151239 | L51: =L39+L50 -> 19512294 | M51: =M39+M50 -> 20426678
A52: Total equity and liabilities | B52: =B51+B32 -> 36379641 | C52: =C51+C32 -> 40028770 | D52: =D51+D32 -> 36130753 | E52: =E51+E32 -> 42307487 | F52: =F51+F32 -> 48832751 | G52: =G51+G32 -> 56732634 | H52: 64917211 | I52: =I51+I32 -> 66063385 | J52: =J51+J32 -> 1.229707e+08 | K52: =K51+K32 -> 1.571341e+08 | L52: =L51+L32 -> 1.9481925e+08 | M52: =M51+M32 -> 2.3843183e+08

Sheet CF
A1: STATEMENT OF CASH FLOWS
A2: For the year ended 31st March (In Rs.’000s) | B2: 2019 | C2: 2020 | D2: 2021 | E2: 2022 | F2: 2023 | G2: 2024 | H2: 2025 | I2: 2026 | J2: 2027 | K2: 2028 | L2: 2029 | M2: 2030
A3: Cash flows from operating activities
A4: Profit before interest and taxation | B4: =IS!B15 -> 6300465 | C4: =IS!C15 -> 5233500 | D4: =IS!D15 -> 5321802 | E4: =IS!E15 -> 5712300 | F4: =IS!F15 -> 13464823 | G4: =IS!G15 -> 15657291 | H4: =IS!H15 -> 16598854 | I4: =IS!I15 -> 19320940 | ... M4: =IS!M15 -> 30384955
A5: Adjustments for:
A6: Depreciation on right of use assets | B6: - | C6: 69116 | D6: 77793 | E6: 70156 | F6: 65766 | G6: 63516 | H6: 56952 | I6: =CapEx!I21 -> 67239.853 | J6: =CapEx!J21 -> 75400.833 | K6: =CapEx!K21 -> 84554.961 | L6: =CapEx!L21 -> 94823.489 | M6: =CapEx!M21 -> 106342.53
A7: Gain on de-recognition of right of use assets | D7: -7106 | E7: -714 | F7: -1839 | G7: -14330 | H7: -4040 | I7: 0 | J7: 0 | K7: 0 | L7: 0 | M7: 0
A8: Depreciation on property, plant and equipment | B8: 1224466 | C8: 1233239 | D8: 1319131 | E8: 1532988 | F8: 1796689 | G8: 2359441 | H8: 2778103 | I8: =-CapEx!I5 -> 2778103 | J8: =-CapEx!J5 -> 2984588.5 | K8: =-CapEx!K5 -> 3183197.8 | L8: =-CapEx!L5 -> 3374974.6 | M8: =-CapEx!M5 -> 3560870.6
A9: Amortisation of intangible assets | B9: 53515 | C9: 4850 | D9: 7437 | E9: 12360 | F9: 12101 | G9: 13463 | H9: 16157 | I9: =-CapEx!I14 -> 42445.8 | J9: =-CapEx!J14 -> 47992.641 | K9: =-CapEx!K14 -> 54133.68 | L9: =-CapEx!L14 -> 60957.393 | M9: =-CapEx!M14 -> 68559.869
A10: Net inventory provisions/(reversal) | B10: -20818 | C10: 38847 | D10: 1096 | E10: -10317 | F10: 49011 | G10: -50310 | H10: 109225 | I10: 0 | J10: =CF!$I10 -> 0 | K10: =CF!$J10 -> 0 | L10: =CF!$K10 -> 0 | M10: =CF!$L10 -> 0
A11: Provision for retirement benefit obligations | B11: 36847 | C11: 40826 | D11: 43030 | E11: 14847 | F11: 41659 | G11: 71786 | H11: 69714 | I11: 0 | J11: =CF!$I11 -> 0 | K11: =CF!$J11 -> 0 | L11: =CF!$K11 -> 0 | M11: =CF!$I11 -> 0
A12: Impairment of property plant and equipment | B12: 60547 | C12: 4729 | D12: 160258 | E12: - | F12: 38460 | G12: 84888 | H12: -8045 | I12: 0 | J12: 0 | K12: 0 | L12: 0 | M12: 0
A13: Loss on disposal of returnable containers | B13: - | C13: 132443 | D13: - | E13: - | F13: - | G13: - | H13: 0 | I13: 0 | J13: 0 | K13: 0 | L13: 0 | M13: 0
A14: Impairment of intangible assets | B14: 881 | C14: 740315 | D14: 449084 | E14: 463578 | F14: 353229 | G14: -291063 | H14: - | I14: 0 | J14: 0 | K14: 0 | L14: 0 | M14: 0
A15: Provision/(reversal) for impairment of doubtful debtors | B15: 24651 | C15: - | D15: 2082 | E15: -162 | F15: 9930 | G15: 1976 | H15: 6780 | I15: 0 | J15: =CF!$I15 -> 0 | K15: =CF!$J15 -> 0 | L15: =CF!$K15 -> 0 | M15: =CF!$L15 -> 0
A16: Impairment of investments | B16: - | C16: - | D16: - | E16: - | F16: - | G16: - | H16: - | I16: 0 | J16: 0 | K16: 0 | L16: 0 | M16: 0
A17: Net gain arising from changes in fair value of investment properties | B17: - | C17: -155609 | D17: - | E17: -160230 | F17: -163100 | G17: -5000 | H17: -45800 | I17: 0 | J17: 0 | K17: 0 | L17: 0 | M17: 0
A18: Loss on disposal of property, plant and equipment | B18: -3529 | C18: -19246 | D18: 21011 | E18: 13896 | F18: 36372 | G18: -168417 | H18: 1847 | I18: 0 | J18: 0 | K18: 0 | L18: 0 | M18: 0
A19: Loss on disposal of intangible asset | B19: - | C19: 37567 | D19: - | E19: 1626 | F19: 5600 | G19: 8740 | H19: 357 | I19: 0 | J19: 0 | K19: 0 | L19: 0 | M19: 0
A20: ESC write off | B20: - | C20: - | D20: 30670 | E20: 5804 | F20: - | G20: - | I20: 0 | J20: 0 | K20: 0 | L20: 0 | M20: 0
A21: Deposit written back | B21: - | C21: - | D21: -168072 | E21: - | F21: - | G21: - | I21: 0 | J21: 0 | K21: 0 | L21: 0 | M21: 0
A22: Lease interest expense | B22: -4638 | C22: -13455 | D22: 48298 | E22: 36773 | F22: 43670 | G22: 45105 | I22: 0 | J22: 0 | K22: 0 | L22: 0 | M22: 0
A23: Unrealised foreign exchange gain | D23: -42012 | E23: -630047 | F23: -459624 | G23: -7694 | H23: -33682 | I23: 0 | J23: 0 | K23: 0 | L23: 0 | M23: 0
A24: Operating cash flow before working capital changes | B24: 7674516 | C24: 7366743 | D24: 6861261 | E24: 7670230 | F24: 15284206 | G24: 17583457 | H24: 19452848 | I24: =SUM(I4:I23) -> 22208729 | J24: =SUM(J4:J23) -> 24896199 | K24: =SUM(K4:K23) -> 27734478 | L24: =SUM(L4:L23) -> 30754408 | M24: =SUM(M4:M23) -> 34120728
A25: Increase in inventories | B25: -582036 | C25: -569544 | D25: -678466 | E25: -805732 | F25: -2963245 | G25: -1621465 | H25: 728453 | I25: =-(WC!I3-WC!H3) -> -971271.21 | J25: =-(WC!J3-WC!I3) -> -1123498.4 | K25: =-(WC!K3-WC!J3) -> -1260222.1 | L25: =-(WC!L3-WC!K3) -> -1413638.2 | M25: =-(WC!M3-WC!L3) -> -1585792.7
A26: (Increase)/decrease in trade and other receivables | B26: 762324 | C26: 464701 | D26: 51632 | E26: -629294 | F26: -3201632 | G26: -480105 | H26: 409692 | I26: =-(WC!I4-WC!H4) -> -688688.97 | J26: =-(WC!J4-WC!I4) -> -772469.95 | K26: =-(WC!K4-WC!J4) -> -866475.38 | L26: =-(WC!L4-WC!K4) -> -971957.83 | M26: =-(WC!M4-WC!L4) -> -1090324
A27: (Increase)/decrease in amounts due from related companies | B27: 58957 | C27: -6500 | D27: 6500 | E27: - | F27: - | G27: - | H27: - | I27: 0 | J27: 0 | K27: 0 | L27: 0 | M27: 0
A28: Increase/(decrease) in amounts due to related companies | B28: 9386 | C28: -7197 | D28: 15080 | E28: 32929 | F28: -79716 | G28: 47565 | H28: -21373 | I28: 0 | J28: 0 | K28: 0 | L28: 0 | M28: 0
A29: Increase/(decrease) tax payables | B29: 129007 | C29: -1802196 | D29: 1770600 | E29: 525126 | F29: -363065 | G29: 3087004 | H29: -753047 | I29: 0 | J29: 0 | K29: 0 | L29: 0 | M29: 0
A30: Increase/(decrease) in trade and other payables | B30: -41324 | C30: 429980 | D30: 221714 | E30: 1379096 | F30: 1478820 | G30: -266623 | H30: 1003267 | I30: =WC!I5-WC!H5 -> 655591.89 | J30: =WC!J5-WC!I5 -> 758342.7 | K30: =WC!K5-WC!J5 -> 850628.92 | L30: =WC!L5-WC!K5 -> 954182.26 | M30: =WC!M5-WC!L5 -> 1070383.7
A31: Cash generated from operations | B31: 8010830 | C31: 5875987 | D31: 8248321 | E31: 8172355 | F31: 10155368 | G31: 18349833 | H31: 20819839 | I31: =SUM(I24:I30) -> 21204360 | J31: =SUM(J24:J30) -> 23758573 | K31: =SUM(K24:K30) -> 26458409 | L31: =SUM(L24:L30) -> 29322994 | M31: =SUM(M24:M30) -> 32514995
A32: Finance expenses paid | B32: -1899035 | C32: -1558103 | D32: -1223962 | E32: -1004672 | F32: -3462910 | G32: -2769859 | H32: 0 | I32: 0 | J32: 0 | K32: 0 | L32: 0 | M32: 0
A33: Tax paid | B33: -460282 | C33: -2327810 | D33: -1368102 | E33: -2148065 | F33: -4037060 | G33: -4308380 | H33: -6021558 | I33: =IS!I20 -> -7940540.7 | J33: =IS!J20 -> -9154271 | K33: =IS!K20 -> -10245708 | L33: =IS!L20 -> -11663687 | M33: =IS!M20 -> -13182985
A34: Surcharge Tax Paid | F34: -1230756 | G34: - | H34: 0 | I34: 0 | J34: 0 | K34: 0 | L34: 0 | M34: 0
A35: Retirement benefits paid | B35: -11209 | C35: -26006 | D35: -6073 | E35: -29259 | F35: -17824 | G35: -73727 | H35: -32337 | I35: - | J35: =CF!$I35 -> - | K35: =CF!$J35 -> - | L35: =CF!$K35 -> - | M35: =CF!$L35 -> -
A36: Net cash generated from operating activities | B36: 5640305 | C36: 1964068 | D36: 5650184 | E36: 4990359 | F36: 1406818 | G36: 11197867 | H36: 14765944 | I36: =SUM(I31:I35) -> 13263820 | J36: =SUM(J31:J35) -> 14604302 | K36: =SUM(K31:K35) -> 16212702 | L36: =SUM(L31:L35) -> 17659307 | M36: =SUM(M31:M35) -> 19332010
A38: Cash Flows from Investing Activities
A39: Purchase and construction of property, plant and equipment | B39: -1022884 | C39: -1889651 | D39: -1161207 | E39: -2092880 | F39: -4295928 | G39: -5398293 | H39: -4827582 | I39: =-CapEx!I4 -> -4948271.5 | J39: =-CapEx!J4 -> -5071978.3 | K39: =-CapEx!K4 -> -5198777.8 | L39: =-CapEx!L4 -> -5328747.2 | M39: =-CapEx!M4 -> -5461965.9
A40: Purchase of intangible assets | B40: -49205 | C40: -5746 | D40: -27196 | E40: -7457 | F40: -7815 | G40: -41222 | H40: -26145 | I40: =-CapEx!I13 -> -70180.007 | J40: =-CapEx!J13 -> -78697.837 | K40: =-CapEx!K13 -> -88252.242 | L40: =-CapEx!L13 -> -98969.775 | M40: =-CapEx!M13 -> -110992.5
A41: Movement in other financial assets | G41: -500000 | H41: -3000000 | I41: 0 | J41: 0 | K41: 0 | L41: 0 | M41: 0
A42: Proceeds from disposal of property, plant and equipment | B42: 3529 | C42: 37351 | D42: 0 | E42: 14005 | F42: 0 | G42: 0 | H42: 0 | I42: =CF!$H42 -> 0 | J42: 0 | K42: 0 | L42: 0 | M42: 0
A43: Agent deposits received | B43: 298961 | C43: 259396 | D43: 366291 | E43: 400788 | F43: 441309 | G43: 451251 | H43: 10478 | I43: 0 | J43: 0 | K43: 0 | L43: 0 | M43: 0
A44: Agent deposits refunded | B44: -6998 | C44: - | D44: - | E44: - | H44: 561228 | I44: 0 | J44: 0 | K44: 0 | L44: 0 | M44: 0
A45: Interest received | B45: 1009923 | C45: 950902 | D45: 664193 | E45: 627596 | F45: 1411521 | G45: 1152128 | H45: 745375 | I45: 0 | J45: 0 | K45: 0 | L45: 0 | M45: 0
A46: Net cash used in investing activities | B46: =SUM(B39:B45) -> 233326 | C46: =SUM(C39:C45) -> -647748 | D46: =SUM(D39:D45) -> -157919 | E46: =SUM(E39:E45) -> -1057948 | F46: =SUM(F39:F45) -> -2450913 | G46: =SUM(G39:G45) -> -4336136 | H46: =SUM(H39:H45) -> -6536646 | I46: =SUM(I39:I45) -> -5018451.6 | ... M46: =SUM(M39:M45) -> -5572958.4
A48: Cash Flows from Financing Activities
A49: Finance expenses paid | H49: -2166862 | I49: =-'Loan Schedule'!B5 -> -1077448.6 | J49: =-'Loan Schedule'!C5 -> -883951.22 | K49: =-'Loan Schedule'!D5 -> -647652.2 | L49: =-'Loan Schedule'!E5 -> -359083.84 | M49: =-'Loan Schedule'!F5 -> -6684.1523
A50: Borrowings obtained | C50: 4373249 | D50: 3000000 | E50: 2000000 | F50: 2400000 | G50: 1900000 | H50: 16350000 | I50: 0 | J50: 0 | K50: 0 | L50: 0 | M50: 0
A51: Repayment of loans and borrowings | B51: -2442990 | C51: -1622619 | D51: -10330300 | E51: -1784300 | F51: -1187400 | G51: -4141667 | H51: -15333333 | I51: =-('Loan Schedule'!B6-'Loan Schedule'!B5)+(-1500000) -> -2374762.2 | J51: =-('Loan Schedule'!C6-'Loan Schedule'!C5) -> -1068259.6 | K51: =-('Loan Schedule'!D6-'Loan Schedule'!D5) -> -1304558.6 | L51: =-('Loan Schedule'!E6-'Loan Schedule'!E5) -> -1593127 | M51: =-('Loan Schedule'!F6-'Loan Schedule'!F5) -> -156000.08
A52: Repayment of debentures | B52: -998800 | C52: -2000000 | F52: - | G52: - | H52: - | I52: - | J52: - | K52: - | L52: - | M52: -
A53: Repayment lease rentals | B53: 0 | C53: -85974 | D53: -103523 | E53: -96060 | F53: -102316 | G53: -91901 | H53: -90554 | I53: -90554 | J53: -90554 | K53: -90554 | L53: -90554 | M53: -90554
A54: Forfeiture of unclaimed dividends | B54: - | C54: 6017 | D54: 987 | E54: 1621 | F54: 419 | G54: 252 | H54: 1152 | I54: 0 | J54: =CF!$I54 -> 0 | K54: =CF!$J54 -> 0 | L54: =CF!$K54 -> 0 | M54: =CF!$L54 -> 0
A55: Dividends paid net of tax | B55: -323139 | C55: -474199 | D55: -593147 | E55: -1337740 | F55: -2278002 | G55: -4326807 | H55: -2375329 | I55: =CF!$H55 -> -2375329 | J55: =CF!$I55 -> -2375329 | K55: =CF!$J55 -> -2375329 | L55: =CF!$K55 -> -2375329 | M55: =CF!$L55 -> -2375329
A56: Net cash used in financing activities | B56: -3764929 | C56: 196474 | D56: -8025983 | E56: -1216479 | F56: -1167299 | G56: -6660123 | H56: -3614926 | I56: =SUM(I49:I55) -> -5918093.8 | J56: =SUM(J49:J55) -> -4418093.8 | K56: =SUM(K49:K55) -> -4418093.8 | L56: =SUM(L49:L55) -> -4418093.8 | M56: =SUM(M49:M55) -> -2628567.2
A58: Net increase/(decrease) in cash and cash equivalents | B58: 2108702 | C58: 1512794 | D58: -2533718 | E58: 2715932 | F58: -2211394 | G58: 701608 | H58: 4614371 | I58: =I36+I46+I56 -> 2327274.3 | J58: =J36+J46+J56 -> 5035532.4 | K58: =K36+K46+K56 -> 6507577.7 | L58: =L36+L46+L56 -> 7813496.3 | M58: =M36+M46+M56 -> 11130485
A59: Cash and cash equivalents at the beginning of the year | B59: 6560059 | C59: 8668761 | D59: 10181555 | E59: 7686214 | F59: 11137550 | G59: 9303148 | H59: 6975114 | I59: =H62 -> 11542881 | J59: =I62 -> 13823551 | K59: =J62 -> 18812480 | L59: =K62 -> 25273453 | M59: =L62 -> 33040346
A60: Effect of movements in exchange rate on translation reserve | F60: - | G60: -7005 | H60: -14834 | I60: -14834 | J60: -14834 | K60: -14834 | L60: -14834 | M60: -14834
A61: Effect of exchange rate changes on cash and cash equivalents | B61: - | C61: - | D61: 38377 | E61: 735404 | F61: 376992 | G61: -13925 | H61: -31770 | I61: -31770 | J61: -31770 | K61: -31770 | L61: -31770 | M61: -31770
A62: Cash and cash equivalents at the end of the year | B62: 8668761 | C62: 10181555 | D62: 7686214 | E62: 11137550 | F62: 9303148 | G62: 9983826 | H62: 11542881 | I62: =SUM(I58:I61) -> 13823551 | J62: =SUM(J58:J61) -> 18812480 | K62: =SUM(K58:K61) -> 25273453 | L62: =SUM(L58:L61) -> 33040346 | M62: =SUM(M58:M61) -> 44124226
A64: Analysis of Cash and Cash Equivalents
A65: Cash and cash equivalents | B65: 10564799 | C65: 13367260 | D65: 9701006 | E65: 13114311 | F65: 11348046 | G65: 12571174 | H65: 13475936 | I65: =I67-I66 -> 15756606 | J65: =J67-J66 -> 20745535 | K65: =K67-K66 -> 27206508 | L65: =L67-L66 -> 34973401 | M65: =M67-M66 -> 46057281
A66: Bank overdraft | B66: -1896038 | C66: -3185705 | D66: -2014792 | E66: -1976761 | F66: -2044898 | G66: -2587348 | H66: -1933055 | I66: =CF!$H66 -> -1933055 | J66: =CF!$I66 -> -1933055 | K66: =CF!$J66 -> -1933055 | L66: =CF!$K66 -> -1933055 | M66: =CF!$L66 -> -1933055
B67: =SUM(B65:B66) -> 8668761 | C67: 10181555 | D67: 7686214 | E67: 11137550 | F67: 9303148 | G67: 9983826 | H67: 11542881 | I67: =I62 -> 13823551 | J67: =J62 -> 18812480 | K67: =K62 -> 25273453 | L67: =L62 -> 33040346 | M67: =M62 -> 44124226

Sheet CapEx
A1: Capital Expenditure
A2: Fiscal Year | B2: 2019 | C2: 2020 | D2: 2021 | E2: 2022 | F2: 2023 | G2: 2024 | H2: 2025 | I2: 2026 | J2: 2027 | K2: 2028 | L2: 2029 | M2: 2030
A3: Beginning PPE | B3: 18146017 | C3: =B7 -> 18162978 | D3: =C7 -> 19221050 | E3: =D7 -> 18869754 | F3: =E7 -> 20574458 | G3: =F7 -> 22996451 | H3: =G7 -> 27161069 | I3: =H7 -> 29197945 | J3: =I7 -> 31368114 | ... M3: =L7 -> 37424856
A4: Additions (Capex) | B4: =-CF!B39 -> 1022884 | C4: =-CF!C39 -> 1889651 | D4: =-CF!D39 -> 1161207 | E4: =-CF!E39 -> 2092880 | F4: =-CF!F39 -> 4295928 | G4: =-CF!G39 -> 5398293 | H4: =-CF!H39 -> 4827582 | I4: =H4*(1+Assumptions!I35) -> 4948271.5 | J4: =I4*(1+Assumptions!J35) -> 5071978.3 | K4: =J4*(1+Assumptions!K35) -> 5198777.8 | L4: =K4*(1+Assumptions!L35) -> 5328747.2 | M4: =L4*(1+Assumptions!M35) -> 5461965.9
A5: - Depreciation | B5: =-CF!B8 -> -1224466 | C5: =-CF!C8 -> -1233239 | D5: =-CF!D8 -> -1319131 | E5: =-CF!E8 -> -1532988 | F5: =-CF!F8 -> -1796689 | G5: =-CF!G8 -> -2359441 | H5: =-CF!H8 -> -2778103 | I5: =-I3*Assumptions!I31 -> -2778103 | J5: =-J3*Assumptions!J31 -> -2984588.5 | K5: =-K3*Assumptions!K31 -> -3183197.8 | L5: =-L3*Assumptions!L31 -> -3374974.6 | M5: =-M3*Assumptions!M31 -> -3560870.6
A6: - Disposal | B6: =-CF!B42 -> -3529 | C6: =-CF!C42 -> -37351 | D6: =-CF!D42 -> 0 | E6: =-CF!E42 -> -14005 | F6: =-CF!F42 -> 0 | G6: =-CF!G42 -> 0 | H6: =-CF!H42 -> 0 | I6: 0 | J6: 0 | K6: 0 | L6: 0 | M6: 0
A7: Ending PPE | B7: =SOFP!B5 -> 18162978 | C7: =SOFP!C5 -> 19221050 | D7: =SOFP!D5 -> 18869754 | E7: =SOFP!E5 -> 20574458 | F7: =SOFP!F5 -> 22996451 | G7: =SOFP!G5 -> 27161069 | H7: =SOFP!H5 -> 29197945 | I7: =SUM(I3:I6) -> 31368114 | J7: =SUM(J3:J6) -> 33455503 | K7: =SUM(K3:K6) -> 35471083 | L7: =SUM(L3:L6) -> 37424856 | M7: =SUM(M3:M6) -> 39325951
A10: Ammotization Expenditure
A11: Fiscal Year | B11: 2019 | C11: 2020 | D11: 2021 | E11: 2022 | F11: 2023 | G11: 2024 | H11: 2025 | I11: 2026 | J11: 2027 | K11: 2028 | L11: 2029 | M11: 2030
A12: Beginning PPE | B12: 2447946 | C12: =B15 -> 2442755 | D12: =C15 -> 1706873 | E12: =D15 -> 1289652 | F12: =E15 -> 819545 | G12: =F15 -> 458843 | H12: =G15 -> 768925 | I12: =H15 -> 212229 | J12: =I15 -> 239963.21 | ... M12: =L15 -> 342799.35
A13: Additions (Capex) | B13: =-CF!B40 -> 49205 | C13: =-CF!C40 -> 5746 | D13: =-CF!D40 -> 27196 | E13: =-CF!E40 -> 7457 | F13: =-CF!F40 -> 7815 | G13: =-CF!G40 -> 41222 | H13: =-CF!H40 -> 26145 | I13: =IS!I3*Assumptions!I36 -> 70180.007 | J13: =IS!J3*Assumptions!J36 -> 78697.837 | K13: =IS!K3*Assumptions!K36 -> 88252.242 | L13: =IS!L3*Assumptions!L36 -> 98969.775 | M13: =IS!M3*Assumptions!M36 -> 110992.5
A14: - Ammortization | B14: =-CF!B9 -> -53515 | C14: =-CF!C9 -> -4850 | D14: =-CF!D9 -> -7437 | E14: =-CF!E9 -> -12360 | F14: =-CF!F9 -> -12101 | G14: =-CF!G9 -> -13463 | H14: =-CF!H9 -> -16157 | I14: =-I12*Assumptions!I32 -> -42445.8 | J14: =-J12*Assumptions!J32 -> -47992.641 | K14: =-K12*Assumptions!K32 -> -54133.68 | L14: =-L12*Assumptions!L32 -> -60957.393 | M14: =-M12*Assumptions!M32 -> -68559.869
A15: Ending PPE | B15: =SOFP!B8 -> 2442755 | C15: =SOFP!C8 -> 1706873 | D15: =SOFP!D8 -> 1289652 | E15: =SOFP!E8 -> 819545 | F15: =SOFP!F8 -> 458843 | G15: =SOFP!G8 -> 768925 | H15: =SOFP!H8 -> 212229 | I15: =SUM(I12:I14) -> 239963.21 | J15: =SUM(J12:J14) -> 270668.4 | K15: =SUM(K12:K14) -> 304786.96 | L15: =SUM(L12:L14) -> 342799.35 | M15: =SUM(M12:M14) -> 385231.98
A18: ROU Asset Expenditure
A19: Fiscal Year | B19: 2019 | C19: 2020 | D19: 2021 | E19: 2022 | F19: 2023 | G19: 2024 | H19: 2025 | I19: 2026 | J19: 2027 | K19: 2028 | L19: 2029 | M19: 2030
A20: Beginning PPE | B20: 0 | C20: =B23 -> 0 | D20: =C23 -> 304355 | E20: =D23 -> 239149 | F20: =E23 -> 207281 | G20: =F23 -> 209947 | H20: =G23 -> 223969 | I20: =H23 -> 768078 | J20: =I23 -> 663526.45 | ... M20: =L23 -> 516371.7
A21: Additions (Capex) | B21: =-CF!B47 -> 0 | C21: =C22+C23 -> 235239 | D21: 49787 | E21: 40857 | F21: 76046 | G21: 91930 | H21: 59964 | I21: =IS!I3*Assumptions!I37 -> 67239.853 | J21: =IS!J3*Assumptions!J37 -> 75400.833 | K21: =IS!K3*Assumptions!K37 -> 84554.961 | L21: =IS!L3*Assumptions!L37 -> 94823.489 | M21: =IS!M3*Assumptions!M37 -> 106342.53
A22: - Depreciation | B22: 0 | C22: =-CF!C6 -> -69116 | D22: =-CF!D6 -> -77793 | E22: =-CF!E6 -> -70156 | F22: =-CF!F6 -> -65766 | G22: =-CF!G6 -> -63516 | H22: =-CF!H6 -> -56952 | I22: =-I20*Assumptions!I33 -> -171791.4 | J22: =-J20*Assumptions!J33 -> -148406.99 | K22: =-K20*Assumptions!K33 -> -132078.14 | L22: =-L20*Assumptions!L33 -> -121448.91 | M22: =-M20*Assumptions!M33 -> -115493.76
A23: Ending PPE | B23: 0 | C23: =SOFP!C9 -> 304355 | D23: =SOFP!D9 -> 239149 | E23: =SOFP!E9 -> 207281 | F23: =SOFP!F9 -> 209947 | G23: =SOFP!G9 -> 223969 | H23: =SOFP!H9 -> 768078 | I23: =SUM(I20:I22) -> 663526.45 | J23: =SUM(J20:J22) -> 590520.3 | K23: =SUM(K20:K22) -> 542997.12 | L23: =SUM(L20:L22) -> 516371.7 | M23: =SUM(M20:M22) -> 507220.46

Sheet WC
A1: Net Working Capital Changes
A2: Fiscal Year | B2: 2019 | C2: 2020 | D2: 2021 | E2: 2022 | F2: 2023 | G2: 2024 | H2: 2025 | I2: 2026 | J2: 2027 | K2: 2028 | L2: 2029 | M2: 2030
A3: Inventory | B3: =SOFP!B15 -> 2512995 | C3: =SOFP!C15 -> 3043692 | D3: =SOFP!D15 -> 3721062 | E3: =SOFP!E15 -> 4537111 | F3: =SOFP!F15 -> 7451345 | G3: =SOFP!G15 -> 9123121 | H3: =SOFP!H15 -> 8285443 | I3: =(I12*I10)/365 -> 9256714.2 | J3: =(J12*J10)/365 -> 10380213 | K3: =(K12*K10)/365 -> 11640435 | L3: =(L12*L10)/365 -> 13054073 | M3: =(M12*M10)/365 -> 14639866
A4: Receivables | B4: =SOFP!B16 -> 2345704 | C4: =SOFP!C16 -> 1881002 | D4: =SOFP!D16 -> 1796923 | E4: =SOFP!E16 -> 2406133 | F4: =SOFP!F16 -> 5530902 | G4: =SOFP!G16 -> 6022460 | H4: =SOFP!H16 -> 5675836 | I4: =(I13*I9)/365 -> 6364525 | J4: =(J13*J9)/365 -> 7136994.9 | K4: =(K13*K9)/365 -> 8003470.3 | L4: =(L13*L9)/365 -> 8975428.1 | M4: =(M13*M9)/365 -> 10065752
A5: Payables | B5: =SOFP!B42 -> 1350370 | C5: =SOFP!C42 -> 1780350 | D5: =SOFP!D42 -> 1998429 | E5: =SOFP!E42 -> 3492710 | F5: =SOFP!F42 -> 4829899 | G5: =SOFP!G42 -> 4567905 | H5: =SOFP!H42 -> 5592536 | I5: =(I14*I10)/365 -> 6248127.9 | J5: =(J14*J10)/365 -> 7006470.6 | K5: =(K14*K10)/365 -> 7857099.5 | L5: =(L14*L10)/365 -> 8811281.8 | M5: =(M14*M10)/365 -> 9881665.4
A6: WC Cycle | B6: =B3+B4-B5 -> 3508329 | C6: =C3+C4-C5 -> 3144344 | D6: =D3+D4-D5 -> 3519556 | E6: =E3+E4-E5 -> 3450534 | F6: =F3+F4-F5 -> 8152348 | G6: =G3+G4-G5 -> 10577676 | H6: =H3+H4-H5 -> 8368743 | I6: =I3+I4-I5 -> 9373111.3 | ... M6: =M3+M4-M5 -> 14823952
A7: WC requirement | C7: =C6-B6 -> -363985 | D7: =D6-C6 -> 375212 | E7: =E6-D6 -> -69022 | F7: =F6-E6 -> 4701814 | G7: =G6-F6 -> 2425328 | H7: =H6-G6 -> -2208933 | I7: =I6-H6 -> 1004368.3 | J7: =J6-I6 -> 1137625.6 | ... M7: =M6-L6 -> 1605733
A9: Revenue | B9: =IS!B3 -> 44216827 | C9: =IS!C3 -> 49215361 | D9: =IS!D3 -> 51172154 | E9: =IS!E3 -> 60211220 | F9: =IS!F3 -> 96938522 | G9: =IS!G3 -> 111930270 | H9: =IS!H3 -> 125172015 | I9: =IS!I3 -> 1.4036001e+08 | ... M9: =IS!M3 -> 2.21985e+08
A10: COS | B10: =-IS!B4 -> 32953571 | C10: =-IS!C4 -> 38202972 | D10: =-IS!D4 -> 40665744 | E10: =-IS!E4 -> 47833437 | F10: =-IS!F4 -> 73755671 | G10: =-IS!G4 -> 84863456 | H10: =-IS!H4 -> 95595789 | I10: =-IS!I4 -> 1.0680212e+08 | ... M10: =-IS!M4 -> 1.6891185e+08
A12: Inventory Days | B12: =(B3/B10)*365 -> 27.834409 | C12: =(C3/C10)*365 -> 29.080135 | D12: =(D3/D10)*365 -> 33.398814 | E12: =(E3/E10)*365 -> 34.621086 | F12: =(F3/F10)*365 -> 36.875008 | G12: =(G3/G10)*365 -> 39.238788 | H12: =(H3/H10)*365 -> 31.635146 | I12: =H12 -> 31.635146 | J12: =I12 -> 31.635146 | K12: =J12 -> 31.635146 | L12: =K12 -> 31.635146 | M12: =L12 -> 31.635146
A13: Receivable Days | B13: =(B4/B9)*365 -> 19.363261 | C13: =(C4/C9)*365 -> 13.950233 | D13: =(D4/D9)*365 -> 12.817066 | E13: =(E4/E9)*365 -> 14.585962 | F13: =(F4/F9)*365 -> 20.825356 | G13: =(G4/G9)*365 -> 19.638994 | H13: =(H4/H9)*365 -> 16.550665 | I13: =H13 -> 16.550665 | J13: =I13 -> 16.550665 | K13: =J13 -> 16.550665 | L13: =K13 -> 16.550665 | M13: =L13 -> 16.550665
A14: Payable days | B14: =(B5/B10)*365 -> 14.956954 | C14: =(C5/C10)*365 -> 17.009874 | D14: =(D5/D10)*365 -> 17.937126 | E14: =(E5/E10)*365 -> 26.651632 | F14: =(F5/F10)*365 -> 23.902069 | G14: =(G5/G10)*365 -> 19.646682 | H14: =(H5/H10)*365 -> 21.353196 | I14: =H14 -> 21.353196 | J14: =I14 -> 21.353196 | K14: =J14 -> 21.353196 | L14: =K14 -> 21.353196 | M14: =L14 -> 21.353196

Sheet Loan Schedule
A1: Loan Schedule
A2: Fiscal Year | B2: 2026 | C2: 2027 | D2: 2028 | E2: 2029 | F2: 2030
A3: Term | B3: 1 | C3: 2 | D3: 3 | E3: 4 | F3: 5
A4: Beginning Value | B4: =B10 -> 4870925 | C4: =B7 -> 3996162.8 | D4: =C7 -> 2927903.2 | E4: =D7 -> 1623344.6 | F4: =E7 -> 30217.687
A5: Interest | B5: =B4*$B$11 -> 1077448.6 | C5: =C4*$B$11 -> 883951.22 | D5: =D4*$B$11 -> 647652.2 | E5: =E4*$B$11 -> 359083.84 | F5: =F4*$B$11 -> 6684.1523
A6: Total Payment | B6: =$B$13 -> 1952210.8 | C6: =$B$13 -> 1952210.8 | D6: =$B$13 -> 1952210.8 | E6: =$B$13 -> 1952210.8 | F6: =($B$13/12) -> 162684.23
A7: Ending Value | B7: =B4+B5-B6 -> 3996162.8 | C7: =C4+C5-C6 -> 2927903.2 | D7: =D4+D5-D6 -> 1623344.6 | E7: =E4+E5-E6 -> 30217.687 | F7: =F4+F5-F6 -> -125782.39
A10: Loan Amount | B10: =SOFP!H35+SOFP!H47 -> 4870925
A11: Interest rate | B11: 0.2212
A12: Time Period -> WAM | B12: =((1500000*3.25)+(2400000*5)+(1900000*1.417))/B10 -> 4.0171631
A13: PMT | B13: =-PMT(B11,B12,B10,0) -> 1952210.8

Sheet NOPLAT
A1: NOPLAT
A3: All figures are in LKR Currency | B3: Historical | I3: Forcast
B4: 2019 | C4: 2020 | D4: 2021 | E4: 2022 | F4: 2023 | G4: 2024 | H4: 2025 | I4: 2026 | J4: 2027 | K4: 2028 | L4: 2029 | M4: 2030
A5: Revenue | B5: 44216827 | C5: ='5Y Fin. Summary'!B4 -> 49215361 | D5: ='5Y Fin. Summary'!C4 -> 51172154 | E5: ='5Y Fin. Summary'!D4 -> 60211220 | F5: ='5Y Fin. Summary'!E4 -> 96938522 | G5: ='5Y Fin. Summary'!F4 -> 111930270 | H5: ='5Y Fin. Summary'!G4 -> 125172015 | I5: =IS!I3 -> 1.4036001e+08 | J5: =IS!J3 -> 1.5739567e+08 | K5: =IS!K3 -> 1.7650448e+08 | L5: =IS!L3 -> 1.9793955e+08 | M5: =IS!M3 -> 2.21985e+08
A6: EBIT | B6: =IS!B15 -> 6300465 | C6: =IS!C15 -> 5233500 | D6: =IS!D15 -> 5321802 | E6: =IS!E15 -> 5712300 | F6: =IS!F15 -> 13464823 | G6: =IS!G15 -> 15657291 | H6: =IS!H15 -> 16598854 | I6: =IS!I15 -> 19320940 | ... M6: =IS!M15 -> 30384955
A7: Income Tax | B7: =IS!B20 -> -2150610 | C7: =IS!C20 -> -1677977 | D7: =IS!D20 -> -1850010 | E7: =IS!E20 -> -2063378 | F7: =IS!F20 -> -4514799 | G7: =IS!G20 -> -6047684 | H7: =IS!H20 -> -6378562 | I7: =IS!I20 -> -7940540.7 | ... M7: =IS!M20 -> -13182985
A8: EBT | B8: =IS!B19 -> 5215873 | C8: =IS!C19 -> 4494240 | D8: =IS!D19 -> 4284507 | E8: =IS!E19 -> 5885176 | F8: =IS!F19 -> 11260903 | G8: =IS!G19 -> 14023293 | H8: =IS!H19 -> 16036224 | I8: =IS!I19 -> 19368016 | ... M8: =IS!M19 -> 32156752
A9: Tax Rate | B9: =ABS(B7/B8) -> 0.41232024 | C9: =ABS(C7/C8) -> 0.37336168 | D9: =ABS(D7/D8) -> 0.43179064 | E9: =ABS(E7/E8) -> 0.350606 | F9: =ABS(F7/F8) -> 0.40092691 | G9: =ABS(G7/G8) -> 0.4312599 | H9: =ABS(H7/H8) -> 0.3977596 | I9: =Assumptions!I29 -> 0.40998214 | J9: =Assumptions!J29 -> 0.41300055 | K9: =Assumptions!K29 -> 0.40691409 | L9: =Assumptions!L29 -> 0.40996559 | M9: =Assumptions!M29 -> 0.40996008
A10: NOPLAT ( EBIT × (1 - Tax Rate)) | B10: =B6*(1-B9) -> 3702655.8 | C10: =C6*(1-C9) -> 3279511.6 | D10: =D6*(1-D9) -> 3023897.7 | E10: =E6*(1-E9) -> 3709533.4 | F10: =F6*(1-F9) -> 8066413.2 | G10: =G6*(1-G9) -> 8904929.2 | H10: =H6*(1-H9) -> 9996500.5 | I10: =I6*(1-I9) -> 11399700 | ... M10: =M6*(1-M9) -> 17928336
A11: Amortization | B11: =CF!B9 -> 53515 | C11: =CF!C9 -> 4850 | D11: =CF!D9 -> 7437 | E11: =CF!E9 -> 12360 | F11: =CF!F9 -> 12101 | G11: =CF!G9 -> 13463 | H11: =CF!H9 -> 16157 | I11: =-CapEx!I14 -> 42445.8 | J11: =-CapEx!J14 -> 47992.641 | K11: =-CapEx!K14 -> 54133.68 | L11: =-CapEx!L14 -> 60957.393 | M11: =-CapEx!M14 -> 68559.869
A12: Depreciation | B12: =-(CapEx!B5+CapEx!B22) -> 1224466 | C12: =-(CapEx!C5+CapEx!C22) -> 1302355 | D12: =-(CapEx!D5+CapEx!D22) -> 1396924 | E12: =-(CapEx!E5+CapEx!E22) -> 1603144 | F12: =-(CapEx!F5+CapEx!F22) -> 1862455 | G12: =-(CapEx!G5+CapEx!G22) -> 2422957 | H12: =-(CapEx!H5+CapEx!H22) -> 2835055 | I12: =-(CapEx!I5+CapEx!I22) -> 2949894.4 | ... M12: =-(CapEx!M5+CapEx!M22) -> 3676364.4
A13: Less: Capital Expenditure | B13: =-(CapEx!B4+CapEx!B13) -> -1072089 | C13: =-(CapEx!C4+CapEx!C13) -> -1895397 | D13: =-(CapEx!D4+CapEx!D13) -> -1188403 | E13: =-(CapEx!E4+CapEx!E13) -> -2100337 | F13: =-(CapEx!F4+CapEx!F13) -> -4303743 | G13: =-(CapEx!G4+CapEx!G13) -> -5439515 | H13: =-(CapEx!H4+CapEx!H13) -> -4853727 | I13: =-(CapEx!I4+CapEx!I13) -> -5018451.6 | ... M13: =-(CapEx!M4+CapEx!M13) -> -5572958.4
A14: Net Working Capital Changes | B14: =-WC!B7 -> 0 | C14: =-WC!C7 -> 363985 | D14: =-WC!D7 -> -375212 | E14: =-WC!E7 -> 69022 | F14: =-WC!F7 -> -4701814 | G14: =-WC!G7 -> -2425328 | H14: =-WC!H7 -> 2208933 | I14: =-WC!I7 -> -1004368.3 | ... M14: =-WC!M7 -> -1605733
A15: FCFF | B15: =SUM(B10:B14) -> 3908547.8 | C15: =SUM(C10:C14) -> 3055304.6 | D15: =SUM(D10:D14) -> 2864643.7 | E15: =SUM(E10:E14) -> 3293722.4 | F15: =SUM(F10:F14) -> 935412.17 | G15: =SUM(G10:G14) -> 3476506.2 | H15: =SUM(H10:H14) -> 10202919 | I15: =SUM(I10:I14) -> 8369220.1 | ... M15: =SUM(M10:M14) -> 14494569

Sheet WACC
B2: WACC Calculation
B3: Cost of Debt calculation | F3: Equity | G3: = Current share price × Number of outstanding shares | J3: S&P Sri Lanka 20
B4: Loans and borrowings | C4: 2236667 | G4: = 2,625.75 X 20988.090 | J4: Date | K4: Price | L4: Market return(%)
B5: Lease liabilities | C5: 231728 | G5: =2625.75*20988.09 -> 55109477 | J5: 43952 | K5: 2016.08
B6: Long term debt | C6: =SUM(C4:C5) -> 2468395 | J6: 43983 | K6: 2268.77 | L6: =LN(K6/K5) -> 0.1180828
B7: Debentures | C7: - | F7: Debt | G7: = Short-Term Debt + Long-Term Debt | J7: 44013 | K7: 2179.65 | L7: =LN(K7/K6) -> -0.040073521 | N7: Expected(rm) monthly | O7: =AVERAGE(L6:L65) -> 0.015076501
B8: Loans and borrowings | C8: 2634258 | J8: 44044 | K8: 2359.75 | L8: =LN(K8/K7) -> 0.079391368 | N8: Expected(rm) yearly | O8: =((1+O7)^12)-1 -> 0.19669999
B9: Lease liabilities | C9: 40901 | F9: =C26/C28 -> 0.1137973 | G9: Weight of Debt | J9: 44075 | K9: 2463.27 | L9: =LN(K9/K8) -> 0.042934054
B10: Bank overdraft | C10: 1933055 | F10: =C27/C28 -> 0.8862027 | G10: Weight of Equity | J10: 44105 | K10: 2282.2 | L10: =LN(K10/K9) -> -0.076349846
B11: Total Debt | C11: =SUM(C6:C10) -> 7076609 | J11: 44136 | K11: 2453.87 | L11: =LN(K11/K10) -> 0.07252648
B12: Cost of debt | C12: =C13/C11 -> 0.22121796 | J12: 44166 | K12: 2638.1 | L12: =LN(K12/K11) -> 0.072392591
B13: Finance Costs | C13: 1565473 | F13: From CBSL : | J13: 44197 | K13: 3514.18 | L13: =LN(K13/K12) -> 0.28674725
B14: Income Tax expense | C14: =-IS!H20 -> 6378562 | J14: 44228 | K14: 2966.63 | L14: =LN(K14/K13) -> -0.16937958
B15: Income before tax | C15: =IS!H19 -> 16036224 | F15: Maturity | G15: Yield (%) | J15: 44256 | K15: 2850.12 | L15: =LN(K15/K14) -> -0.04006553
B16: Effective Tax Rate | C16: =C14/C15 -> 0.3977596 | F16: 3-year | G16: 0.0885 | J16: 44287 | K16: 2869.25 | L16: =LN(K16/K15) -> 0.0066895729
B17: Cost of debt * (1-T) | C17: =C12*(1-C16) -> 0.13322639 | F17: 5-year | G17: 0.0947 | J17: 44317 | K17: 2978.81 | L17: =LN(K17/K16) -> 0.03747322
F18: 10-year | G18: 0.1046 | J18: 44348 | K18: 2968.26 | L18: =LN(K18/K17) -> -0.0035479694
B19: Cost of Equity | J19: 44378 | K19: 3062.17 | L19: =LN(K19/K18) -> 0.031147892
B20: Risk Free Rate | C20: =G18 -> 0.1046 | J20: 44409 | K20: 3364.59 | L20: =LN(K20/K19) -> 0.094182298
B21: Beta | C21: 0.61 | J21: 44440 | K21: 3534.82 | L21: =LN(K21/K20) -> 0.049356265
B22: Market Return | C22: =O8 -> 0.19669999 | J22: 44470 | K22: 3708.52 | L22: =LN(K22/K21) -> 0.047970497
B23: Cost of equity | C23: =C20+(C21*(C22-C20)) -> 0.160781 | J23: 44501 | K23: 3875.96 | L23: =LN(K23/K22) -> 0.044160499
J24: 44531 | K24: 4233.25 | L24: =LN(K24/K23) -> 0.088176646
B25: Weight of Debt and Equity | J25: 44562 | K25: 4397.57 | L25: =LN(K25/K24) -> 0.038082096
B26: Total Debt | C26: =C11 -> 7076609 | J26: 44593 | K26: 3936.81 | L26: =LN(K26/K25) -> -0.11068136
B27: Total Equity | C27: =G5 -> 55109477 | J27: 44621 | K27: 3031.16 | L27: =LN(K27/K26) -> -0.26142537
B28: Total | C28: =SUM(C26:C27) -> 62186086 | J28: 44652 | K28: 2509.24 | L28: =LN(K28/K27) -> -0.18896547
J29: 44682 | K29: 2679.33 | L29: =LN(K29/K28) -> 0.065586845
B30: WACC | C30: =(F10*C23) + (F9*C17) -> 0.15764536 | J30: 44713 | K30: 2334.36 | L30: =LN(K30/K29) -> -0.137829
J31: 44743 | K31: 2448.36 | L31: =LN(K31/K30) -> 0.047680649
J32: 44774 | K32: 2928.97 | L32: =LN(K32/K31) -> 0.17923241
J33: 44805 | K33: 3165.33 | L33: =LN(K33/K32) -> 0.07760649
J34: 44835 | K34: 2590.61 | L34: =LN(K34/K33) -> -0.20036395
J35: 44866 | K35: 2730.08 | L35: =LN(K35/K34) -> 0.052437544
J36: 44896 | K36: 2635.63 | L36: =LN(K36/K35) -> -0.03520867
J37: 44927 | K37: 2764.51 | L37: =LN(K37/K36) -> 0.047741161
J38: 44958 | K38: 2796.71 | L38: =LN(K38/K37) -> 0.011580322
J39: 44986 | K39: 2682.83 | L39: =LN(K39/K38) -> -0.041571519
J40: 45017 | K40: 2617.79 | L40: =LN(K40/K39) -> -0.024541757
J41: 45047 | K41: 2421.49 | L41: =LN(K41/K40) -> -0.077947397
J42: 45078 | K42: 2713.65 | L42: =LN(K42/K41) -> 0.11391154
... J65: 45778 | K65: 4981.57 | L65: =LN(K65/K64) -> 0.070242254

Sheet DCF
A1: Discounted CashFlow
A2: YEAR | B2: 2020 | C2: 2021 | D2: 2022 | E2: 2023 | F2: 2024 | G2: 2025 | H2: 2026 | I2: 2027 | J2: 2028 | K2: 2029 | L2: 2030
A3: NOPLAT | B3: =NOPLAT!C10 -> 3279511.6 | C3: =NOPLAT!D10 -> 3023897.7 | D3: =NOPLAT!E10 -> 3709533.4 | E3: =NOPLAT!F10 -> 8066413.2 | F3: =NOPLAT!G10 -> 8904929.2 | G3: =NOPLAT!H10 -> 9996500.5 | H3: =NOPLAT!I10 -> 11399700 | I3: =NOPLAT!J10 -> 12789672 | ... L3: =NOPLAT!M10 -> 17928336
A4: FCFF | B4: =NOPLAT!C15 -> 3055304.6 | C4: =NOPLAT!D15 -> 2864643.7 | D4: =NOPLAT!E15 -> 3293722.4 | E4: =NOPLAT!F15 -> 935412.17 | F4: =NOPLAT!G15 -> 3476506.2 | G4: =NOPLAT!H15 -> 10202919 | H4: =NOPLAT!I15 -> 8369220.1 | I4: =NOPLAT!J15 -> 9682357.8 | ... L4: =NOPLAT!M15 -> 14494569
A5: WACC | H5: =WACC!$C30 -> 0.15764536 | I5: =WACC!$C30 -> 0.15764536 | J5: =WACC!$C30 -> 0.15764536 | K5: =WACC!$C30 -> 0.15764536 | L5: =WACC!$C30 -> 0.15764536
A6: PV | H6: =H4/((1+H5)^1) -> 7229519.9 | I6: =I4/((1+I5)^2) -> 7224870.4 | J6: =J4/((1+J5)^3) -> 7274076.1 | K6: =K4/((1+K5)^4) -> 7105381.4 | L6: =L4/((1+L5)^5) -> 6971522.7
B10: Implied Share Price Calculation
B11: Sum of PV of FCF | C11: =SUM(H6:L6) -> 35805370
B12: Growth Rate | C12: 0.02
B13: WACC | C13: =WACC!C30 -> 0.15764536 | E13: Sensitivity Table
B14: Terminal Value | C14: =L4*(1+C12)/(C13-C12) -> 1.074098e+08
B15: PV of Terminal Value | C15: =C14/((1+C13)^5) -> 51661409 | G15: Growth Rate
B16: Enterprise Value | C16: =C11+C15 -> 87466780 | F16: =C22 -> 3689.2777 | G16: =H16-0.5% -> 0.01 | H16: =I16-0.5% -> 0.015 | I16: =C12 -> 0.02 | J16: =I16+0.5% -> 0.025 | K16: =J16+0.5% -> 0.03
B17: (+) Cash | C17: =SOFP!H19 -> 13475936 | E17: WACC | F17: =F18-0.5% -> 0.14764536 | G17: 3503.067 | H17: 3417.7576 | I17: 3417.7576 | J17: 3503.067 | K17: 3692.2791
B18: (-) Debt | C18: =-WACC!C11 -> -7076609 | F18: =F19-0.5% -> 0.15264536 | G18: 3504.5874 | H18: 3419.278 | I18: 3419.278 | J18: 3504.5874 | K18: 3693.7995
B19: (-) Minority Interest | C19: =-SOFP!H31 -> -16435215 | F19: =H5 -> 0.15764536 | G19: 3504.5874 | H19: 3419.278 | I19: 3419.278 | J19: 3504.5874 | K19: 3693.7995
B20: Equity Value | C20: =SUM(C16:C19) -> 77430892 | F20: =F19+0.5% -> 0.16264536 | G20: 3503.067 | H20: 3417.7576 | I20: 3417.7576 | J20: 3503.067 | K20: 3692.2791
B21: Diluted Shares Outstanding | C21: 20988.09 | F21: =F20+0.5% -> 0.16764536 | G21: 3500.0656 | H21: 3414.7562 | I21: 3414.7562 | J21: 3500.0656 | K21: 3689.2777
B22: Implied Share Price | C22: =C20/C21 -> 3689.2777
B23: Market Price as at 18th Sep | C23: 2625.75
B24: Gap | C24: =C23-C22 -> -1063.5277
B25: % Upside/Downside | C25: =C22/C23-1 -> 0.40503768

Sheet Ratios
